Workbook
Name act_gulf: Assumptions!$B$56
Name act_india: Assumptions!$B$57
Name act_referral: Assumptions!$B$55
Name act_s0: Assumptions!$B$49
Name act_s1a: Assumptions!$B$47
Name act_s1b: Assumptions!$B$48
Name act_s2: Assumptions!$B$51
Name act_s3: Assumptions!$B$50
Name act_s4: Assumptions!$B$52
Name act_s5: Assumptions!$B$53
Name act_s6: Assumptions!$B$54
Name aed_usd: Assumptions!$B$7
Name agent_commission: 'Scenario Parameters'!$B$113
Name agent_productivity: 'Scenario Parameters'!$B$17
Name agents_gulf_y1: Assumptions!$B$100
Name agents_gulf_y2: Assumptions!$B$101
Name agents_gulf_y3: Assumptions!$B$102
Name agents_gulf_y4: Assumptions!$B$103
Name agents_gulf_y5: Assumptions!$B$104
Name agents_gulf_y6: Assumptions!$B$105
Name agents_gulf_y7: Assumptions!$B$106
Name agents_india_y1: Assumptions!$B$107
Name agents_india_y2: Assumptions!$B$108
Name agents_india_y3: Assumptions!$B$109
Name agents_india_y4: Assumptions!$B$110
Name agents_india_y5: Assumptions!$B$111
Name agents_india_y6: Assumptions!$B$112
Name agents_india_y7: Assumptions!$B$113
Name agents_uae_y1: Assumptions!$B$93
Name agents_uae_y2: Assumptions!$B$94
Name agents_uae_y3: Assumptions!$B$95
Name agents_uae_y4: Assumptions!$B$96
Name agents_uae_y5: Assumptions!$B$97
Name agents_uae_y6: Assumptions!$B$98
Name agents_uae_y7: Assumptions!$B$99
Name atm_a1500: 'Scenario Parameters'!$B$55
Name atm_a3000: 'Scenario Parameters'!$B$56
Name atm_a3000p: 'Scenario Parameters'!$B$57
Name atm_a500: 'Scenario Parameters'!$B$54
Name atm_allowance: Assumptions!$B$18
Name atm_fee: Assumptions!$B$19
Name atmm_a1500: 'Scenario Parameters'!$B$59
Name atmm_a3000: 'Scenario Parameters'!$B$60
Name atmm_a3000p: 'Scenario Parameters'!$B$61
Name atmm_a500: 'Scenario Parameters'!$B$58
Name audit_usd: 'Scenario Parameters'!$B$106
Name aum_per_partner: 'Scenario Parameters'!$B$83
Name aum_per_partner_user: 'Scenario Parameters'!$B$82
Name b2b_fee: 'Scenario Parameters'!$B$79
Name bar_grams: Assumptions!$B$10
Name benef_count: 'Scenario Parameters'!$B$70
Name benef_fee: Assumptions!$B$26
Name cac7_gulf: 'Scenario Parameters'!$B$22
Name cac7_india: 'Scenario Parameters'!$B$23
Name cac7_uae: 'Scenario Parameters'!$B$21
Name cac_gulf: 'Scenario Parameters'!$B$19
Name cac_india: 'Scenario Parameters'!$B$20
Name cac_uae: 'Scenario Parameters'!$B$18
Name card_activation: 'Scenario Parameters'!$B$49
Name card_fixed_usd: 'Scenario Parameters'!$B$115

Sheet Cover
B2: Aurumix Revenue Model
B3: Hybrid Monthly + Annual View | 7-Year Projection
B5: Date | C5: =TODAY()
B6: Scope | C6: Six revenue streams at their full charge, with the fabrication premium as cost of goods sold, plus the modelled cost base, net profit, unit economics, regulatory capital, the float and the peak funding need. Headcount and tax are not yet in the cost base, so every profit figure is an upper bound.
B7: Periods | C7: 24 monthly (M1-M24) + 5 annual (Y3-Y7) = 29 total. M1 = January 2027
B8: Engine | C8: Rolling customer balance: opening + new - churned = closing, by region. Customers who stop paying keep their gold and move to a HOLDERS balance.
B9: Metal | C9: 100 g bars throughout. One entry fee, one fabrication premium.
B10: Prepared by | C10: Tokenomics.net: Custom Data Room Engagement
B12: COLOR LEGEND
B13: BLUE text | C13: Hardcoded inputs (Assumptions & Scenario Parameters)
B14: BLACK text | C14: In-sheet formulas
B15: GREEN text | C15: Cross-sheet references
B17: SHEETS
B18: Cover: This page
B19: Assumptions: Fixed inputs, activation calendar, seasonality, market ceilings
B20: Scenario Parameters: Base / Aggressive / Conservative, plus structural switches
B21: Model: Customer engine, AUM and the six revenue streams (29 periods)
B22: Summary: Annual revenue by stream (Y1-Y7), revenue mix, key metrics
B24: SIMPLIFIED BUILD - cohort and archetype detail moves to the Phase 5 simulation.
B25: Kept as inputs rather than engines: the holders balance, the fabrication premium inside stream 1, and the ICS qualification rate (a memo that prices benefits; it no longer gates the card).

Sheet Assumptions
A1: =Cover!$B$2
A2: Inputs and Assumptions
A4: PRICING AND METAL
A5: Parameter | B5: Value | C5: Unit | D5: Source
A6: Gold price at M1 | B6: 141.46 | C6: USD/g | D6: USD 4,400/oz verified 2026-08-17. THE STARTING PRICE - it no longer holds for the whole horizon; see the appreciation rate below and the live 'Gold price (this period)' row on the Model. CITED.
A7: AED/USD peg | B7: 3.6725 | C7: AED/USD | D7: CBUAE peg. CITED.
A8: Entry fee charged | B8: 0.05 | C8: % of contribution | D8: Decision 9, client-stated. A SINGLE RATE throughout. CLIENT INPUT.
A9: Fabrication premium paid | B9: 0.015 | C9: % over spot | D9: 100 g bars. OBSERVED (D28): goldtrade.ae 19 Aug 2026 measured 100 g at +1.71% (PAMP 1.75, Valcambi 1.67), less the published 25 bp bulk gradient. THE ENTRY FEE IS A MARGIN, NOT A FEE - this is netted off stream 1, because it is cost OF REVENUE. Reporting stream 1 gross would read ~43% high.
A10: Bar denomination | B10: 100 | C10: grams | D10: 100 g throughout, by agreement. OBSERVED.
A12: CARD ECONOMICS
A13: Parameter | B13: Value | C13: Unit | D13: Source
A14: Interchange - Gold | B14: 0.018 | C14: % of spend | D14: Visa UAE IRF schedule, 18 Oct 2025. CITED, PRIMARY. The live model reads the FLAT GOLD RATE: replacing the full 1.80/2.05/2.10 ladder with it moves stream 2 by only ~2% of gross profit at Y7, because Sovereign is 1.2% of tiered accounts.
A15: Per-transaction processor fee | B15: 0.1 | C15: USD/authorised txn | D15: WHAT THE PROCESSOR CHARGES AURUMIX to authorise and switch each transaction - NOT passed to the cardholder, and it cannot be: no consumer card charges per swipe on normal purchases, the card here is a REWARD for saving rather than a product sold, and a declined authorisation cannot be billed to anyone. Issuing economics are structurally: earn interchange, pay scheme and processing costs out of it. USD 0.10 is Stripe Issuing's PUBLISHED RACK RATE, used as a proxy because NO UAE PROCESSOR PUBLISHES PRICING. At volume, processors commonly reach USD 0.02-0.05 - a term-sheet negotiation, and at USD 0.03 the minimum profitable transaction falls from ~AED 77 to ~AED 23. CITED as a proxy.
A16: Decline uplift on authorised txns | B16: 0.06 | C16: % uplift | D16: The processor fee is charged per AUTHORISATION, not per settled transaction, so declined attempts are billable to Aurumix and chargeable to nobody. ASSUMPTION.
A17: FX margin on foreign spend | B17: 0.02 | C17: % of foreign spend | D17: Market rate ~2%, converged across four comparables. CITED.
A18: Free ATM allowance (Gold) | B18: 1000 | C18: AED/month | D18: Monthly and NOT rolling. Set deliberately ABOVE the median draw - that is the finding. CITED.
A19: ATM fee over the allowance | B19: 0.02 | C19: % of the excess | D19: Sector converged. CITED.
A20: Card issuance fee | B20: 75 | C20: AED one-off | D20: Charged at base level, waived at upper tiers. CITED structure, ASSUMPTION rate.
A21: Card replacement fee | B21: 100 | C21: AED per event | D21: Market-normal UAE replacement is AED 75-150. ASSUMPTION.
A23: OTHER STREAM PRICING
A24: Parameter | B24: Value | C24: Unit | D24: Source
A25: Family plan / Digital Will price | B25: 50 | C25: USD/yr | D25: RE-PRICED 2026-08-21 from USD 120/yr. THE OLD PRICE WAS ABOVE TRUST & WILL'S PREMIUM US MEMBERSHIP (USD 49/yr) AND WAS 33% OF EVERYTHING THE CUSTOMER SAVES IN A YEAR - a USD 30/month saver puts away USD 360, and we were charging 120 of it. THE INDUSTRY MODEL IS A ONE-OFF FEE PLUS A SMALL ANNUAL UPDATE LAYER, and it is the annual layer this row represents: Trust & Will USD 199 one-off + USD 49/yr; Farewill GBP 100 + GBP 10/yr; Epilogue C$139 with NO subscription at all; other platforms renew updates at ~C$4.50/yr. Formal UAE will registration is a different product entirely and one-off - DIFC AED 10,000 single / 15,000 mirror, Abu Dhabi Civil Court AED 950 as the cheapest formal route. Indian online wills run INR 500-4,000 basic. Family add-ons on finance apps are usually BUNDLED FREE; where charged it is USD 5-15/month for a WHOLE HOUSEHOLD (Monarch 99.99/yr, Zeta 59.99/yr, Greenlight 5.99/mo). SET AT USD 50/yr, client instruction 2026-08-21. That is essentially TRUST & WILL'S USD 49/yr MEMBERSHIP - a defensible anchor in that it matches the best-known product in the category, but NOTE WHOSE PRODUCT IT IS: Trust & Will sells to US customers who paid 199-599 up front for an estate plan, not to a migrant worker saving USD 30 a month. At 50 the plan is 14% OF EVERYTHING THE CUSTOMER SAVES IN A YEAR, against 10% at 36 and 33% at the original 120. It is no longer absurd, but it is priced at a developed-market benchmark for an emerging-market customer, and that is the line an adviser would push on. A ONE-OFF SETUP FEE IS NOT MODELLED - if the client wants the full industry structure, that is a second row, not a bigger number here. CITED comparators, ASSUMPTION on the point in the range.
A26: Additional beneficiary fee | B26: 6 | C26: USD/yr each | D26: ADDED 2026-08-21, client instruction. Charged per named beneficiary BEYOND THE FIRST, which the plan includes - the standard shape for this kind of add-on, and the reason the formula carries a MAX(0, n-1) rather than charging every beneficiary. NO COMPARABLE EXISTS: will services price PER WILL, not per beneficiary. DIFC charges more for a MIRROR will (two people) and more again for guardianship, but nobody publishes a per-beneficiary tariff. So this is priced on COST RECOVERY, which is the defensible basis available: every named beneficiary needs identity capture and AML screening, and Sumsub screening already sits in this model at ~USD 1.85 per check in the redemption cost memo. USD 6/yr covers that with margin without becoming a second subscription. DELIBERATELY SMALL. At 1.5 chargeable beneficiaries it adds USD 9/yr to a USD 50 plan - an 18% uplift on a stream worth ~3.5% of revenue, so it cannot move the model and should not be tuned to try. ASSUMPTION on a cost-recovery basis.
A27: Credit origination fee - gross | B27: 0.01 | C27: % of draw | D27: Finance House UAE gold loan Key Facts Statement carries a 1% processing fee - the one gross rate with a real UAE anchor. CITED.
A28: Credit origination - Aurumix share | B28: 0.5 | C28: % of gross | D28: ASSUMPTION.
A29: Credit servicing fee - gross | B29: 0.005 | C29: %/yr of drawn | D29: ASSUMPTION.
A30: Credit servicing - Aurumix share | B30: 0.7 | C30: % of gross | D30: The highest of the heads: servicing is where Aurumix does the actual work. ASSUMPTION.
A31: LTV against collateral | B31: 0.5 | C31: % of collateral | D31: _draft_ics-scoring.md sec 6.2, settled 2026-08-13. CITED.
A32: Spot ticket - UAE | B32: 190 | C32: USD/purchase | D32: OBSERVED, PRIMARY. Botim gold: average ticket AED 700, Khaleej Times, Nov 2025 (= USD 191 at the peg). CROSS-CHECKS against the same platform's own volume disclosure - AED 100m over 128,000 trades implies AED 781. THE STRONGEST COMPARABLE IN THIS MODEL: Botim is a messaging app that became the default for Gulf expats and added gold in Aug 2025, so its users ARE Aurumix's customers - same country, same segment, same product, same period. Note 64% of its users buy under AED 500, so the mean sits above the median and this figure is, if anything, generous.
A33: Spot ticket - Oman and Bahrain | B33: 145 | C33: USD/purchase | D33: INFERRED - THE WEAKEST OF THE THREE. No GCC platform outside the UAE publishes an average ticket; this is a CONFIRMED NEGATIVE, not a gap in the search. Taken as the UAE figure scaled by the regional income gap (SIP 26.00/33.60 = 0.77x). Do not present this as sourced.
A34: Spot ticket - India | B34: 40 | C34: USD/purchase | D34: OBSERVED, PROXY. Augmont: average festive-season purchase Rs 3,300, Times of India, Sep 2025 (= ~USD 38). Augmont is a licensed refiner and digital gold platform; a festive lump is structurally the same act as a spot purchase, which is why it is preferred to the alternatives. REJECTED: SafeGold Rs 5,000-8,000 (May 2026) - that book skews to investors, while Aurumix's Indian customer saves USD 30 a month; MMTC-PAMP Rs 800-1,200 - closer to routine micro-saving than a lump; Rs 230 industry-wide - a LinkedIn aggregate, not a citable source. WEAKER THAN THE UAE FIGURE: right country and right behaviour, but Aurumix's Indian customer is poorer than Augmont's average buyer, so 40 may be generous.
A35: Spot attach rate - UAE | B35: 0.12 | C35: % of customers/yr | D35: Share of paying customers who make ANY spot purchase in a year - NOT a monthly rate, and NOT how often a buyer buys (that is the separate frequency input). Set on the affordability ratio above: the spot ticket as a multiple of the same customer's monthly SIP. NO PUBLISHED BENCHMARK EXISTS - confirmed negative. KNOWN SIMPLIFICATION: v2.6 applied a TENURE UPLIFT here ('a 3-year account is ~2x as likely to buy spot as a 6-month account') which v3.0 dropped, so this is flat from day one and OVERSTATES SPOT IN THE EARLY YEARS, when nearly every account is young. Restore the uplift in the Phase 5 simulation. ASSUMPTION, structured on an observable driver.
A36: Spot attach rate - Oman and Bahrain | B36: 0.1 | C36: % of customers/yr | D36: Share of paying customers who make ANY spot purchase in a year - NOT a monthly rate, and NOT how often a buyer buys (that is the separate frequency input). Set on the affordability ratio above: the spot ticket as a multiple of the same customer's monthly SIP. NO PUBLISHED BENCHMARK EXISTS - confirmed negative. KNOWN SIMPLIFICATION: v2.6 applied a TENURE UPLIFT here ('a 3-year account is ~2x as likely to buy spot as a 6-month account') which v3.0 dropped, so this is flat from day one and OVERSTATES SPOT IN THE EARLY YEARS, when nearly every account is young. Restore the uplift in the Phase 5 simulation. ASSUMPTION, structured on an observable driver.
A37: Spot attach rate - India | B37: 0.35 | C37: % of customers/yr | D37: Share of paying customers who make ANY spot purchase in a year - NOT a monthly rate, and NOT how often a buyer buys (that is the separate frequency input). Set on the affordability ratio above: the spot ticket as a multiple of the same customer's monthly SIP. NO PUBLISHED BENCHMARK EXISTS - confirmed negative. KNOWN SIMPLIFICATION: v2.6 applied a TENURE UPLIFT here ('a 3-year account is ~2x as likely to buy spot as a 6-month account') which v3.0 dropped, so this is flat from day one and OVERSTATES SPOT IN THE EARLY YEARS, when nearly every account is young. Restore the uplift in the Phase 5 simulation. ASSUMPTION, structured on an observable driver.
A39: SIP RULES
A40: Parameter | B40: Value | C40: Unit | D40: Source
A41: SIP hard floor | B41: 20 | C41: USD/month | D41: Rejected outright below; never partially credited. CITED.
A42: Confirmed SIP gate | B42: 6 | C42: consecutive payments | D42: Client's own figure. The gate is why eligibility is NOT universal - see the two eligibility parameters on the Scenario sheet. CLIENT INPUT.
A43: Cost per redemption event | B43: 1.85 | C43: USD | D43: CUT TWICE, AND BOTH CUTS WERE DELIBERATE. From 4.20 to 3.20 on 2026-08-20, removing the outbound bank transfer fee (USD 1.00-2.50) as the customer's cost to bear. From 3.20 to 1.85 on 2026-08-26, client instruction, removing the ~1.35 of operational handling. WHAT REMAINS IS SUMSUB AML RE-SCREENING AT 1.85, the same published per-verification rate the onboarding line uses - a redemption triggers a re-screen. NOT a double count with the KYC line: that one charges new customers at onboarding, this one charges a different event. WHAT WAS REMOVED IS NOT ZERO. Operational handling - the staff time to check, approve and settle a redemption - is real work; it is now assumed to sit inside headcount rather than being priced per event. WHEN HEADCOUNT LANDS, CONFIRM IT IS ACTUALLY CARRIED THERE, or this cost has quietly vanished from the model rather than moved. NOT IN THE REVENUE MODEL: redemption is a COST and arrives with the cost build. This row is carried so the driver is documented and the unit rate already agreed. THE FINDING IT CARRIES IS UNCHANGED AND IS THE POINT - VARA Annex 2 III.E.4 forbids charging ANY fee on redemption, verified verbatim at primary source, so the cost is 100% absorbed, no offsetting revenue exists or can exist, and THERE CAN NEVER BE AN EXIT FEE. DERIVED.
A45: ACTIVATION CALENDAR - the single source of every activation period
A46: Parameter | B46: Value | C46: Unit | D46: Source
A47: Stream 1a - Entry fee, SIP | B47: 1 | C47: period # (from) | D47: M1. The core product - live at launch.
A48: Stream 1b - Entry fee, SPOT | B48: 1 | C48: period # (from) | D48: M1. A sub-stream of 1: the same fee on the same gold through a different rail, so it needs no additional build.
A49: Stream 0 - Redemption cost | B49: 1 | C49: period # (from) | D49: M1. A mandatory cost from day one. VARA Annex 2 III.E.4 forbids charging any fee on redemption, so there is no offsetting revenue and there can never be an exit fee.
A50: Stream 3 - Family plan and Digital Will | B50: 7 | C50: period # (from) | D50: M7 (client decision 2026-08-20). RATIONALE: this is a paid add-on sold INTO an existing base, not an acquisition product. At M1 there is no base to attach it to, and the Digital Will needs the legal template and beneficiary flow finished. Six months lets the first cohort establish before they are asked to buy a second product.
A51: Stream 2 - Card interchange | B51: 13 | C51: period # (from) | D51: M13 (client decision 2026-08-20, moved earlier from M18). RATIONALE FOR ANY DELAY AT ALL: the card is not ours to launch. It needs a sponsor bank (BIN sponsorship), Visa scheme certification and a processor integration - all commercial gates outside our control. It also needs customers who have cleared the six-payment gate, which takes ~8 months on average, so a card launched much earlier would have almost nobody eligible to hold it.
A52: Stream 4 - Cardholder fees | B52: 13 | C52: period # (from) | D52: M13, necessarily with stream 2 - FX, ATM and issuance fees cannot exist before the card does.
A53: Stream 5 - Lending revenue share | B53: 13 | C53: period # (from) | D53: M13 (client decision 2026-08-20, moved earlier from Y3). RATIONALE FOR ANY DELAY AT ALL: lending needs a partner lender under contract, and it needs collateral that has SEASONED 90 days. A customer joining at M1 has enough seasoned gold by M13; one joining at M10 does not, which the model handles because borrowers are drawn from the gate-cleared population, not from everyone.
A54: Stream 6 - B2B platform fee | B54: 13 | C54: period # (from) | D54: M13 (client decision 2026-08-20, moved earlier from Y3). RATIONALE FOR ANY DELAY AT ALL: it needs a signed partner and multi-tenant capability at register and mint. NOTE: at Y3 this stream had to be placed at the START of the annual block to avoid a one-twelfth-year stub column sitting beside a full annual one. At M13 it sits safely inside the monthly block, so that complication disappears.
A55: Referral channel begins | B55: 13 | C55: period # (from) | D55: M13, and this one is STRUCTURAL rather than commercial: a referrer must clear their own six-payment gate before they can refer, and the referee must then clear theirs. Two six-month gates IN SERIES. Year 1 pays nothing and the channel does not reach steady state until roughly M25.
A56: Region opens - Oman and Bahrain | B56: 13 | C56: period # (from) | D56: M13 (client decision 2026-08-20). THE ONLY STAGED REGION, and the reason is regulatory: it requires local authorisation in a second and third jurisdiction. These customers are also NOT UAE-resident, so the VAT and reporting treatment differs.
A57: Region opens - India | B57: 1 | C57: period # (from) | D57: M1 (client decision 2026-08-20, moved earlier from M13). The India payment route is ASSUMED SOLVED in this model. That is a live assumption, not a settled fact - if the route is not solved, this region does not open at all and roughly a quarter of terminal revenue goes with it.
A59: SEASONALITY VECTORS (raw - the Model normalises to exactly 12.000)
A60: Vector | F60: Jan | G60: Feb | H60: Mar | I60: Apr | J60: May | K60: Jun | L60: Jul | M60: Aug | N60: Sep | O60: Oct | P60: Nov | Q60: Dec
A61: Acquisition seasonality | D61: SOURCED TIMING, JUDGED AMPLITUDE. Peaks at Akshaya Tritiya (Apr/May), the most concentrated gold-buying day globally by value, and Dhanteras/Diwali (Oct/Nov), India's peak gold occasion with demand up 8-12% in the fortnight before. Wedding season Nov-Mar supports the winter. Trough Jul-Sep, the sourced annual low. Jan carries the Dubai Shopping Festival. DAMPED to ~+/-25% against the ~+/-33% swing in raw jewellery demand, because a USD 20/month savings mandate is far less impulsive than buying jewellery. Two traps avoided: India's Q3 2024 spike was an IMPORT DUTY CUT, not seasonality; and Ramadan/Eid moves ~11 days a year, so a fixed-month Eid bump would be wrong by construction over 7 years. | F61: 1.01 | G61: 0.96 | H61: 0.92 | I61: 1.15 | J61: 1.04 | K61: 0.88 | L61: 0.85 | M61: 0.85 | N61: 0.93 | O61: 1.25 | P61: 1.15 | Q61: 1.01
A62: Card spend seasonality | D62: UAE RESIDENT CARD SPEND, not gold. Peaks Dec-Jan on the Dubai Shopping Festival and year-end holidays; troughs Jul-Aug when residents leave for the summer. NARROWER than acquisition (+/-14% vs +/-25%) because everyday spend is less culturally spiky. Note the deliberate OPPOSITION to the foreign-spend vector: Jul-Aug is the weakest total-spend month and the strongest foreign-share month. | F62: 1.1 | G62: 1 | H62: 0.98 | I62: 0.98 | J62: 1 | K62: 0.95 | L62: 0.88 | M62: 0.9 | N62: 1 | O62: 1.02 | P62: 1.05 | Q62: 1.14
A63: Foreign-spend share vector | D63: The one seasonality vector the brief itself tabulates. Raw mean 39.75, rescaled on the Model to the foreign-spend-share parameter. THE SUMMER TRAVEL SEASON IS THE LARGEST STREAM-4 MONTH on the weakest total-spend base. | F63: 30 | G63: 30 | H63: 30 | I63: 32 | J63: 34 | K63: 55 | L63: 60 | M63: 56 | N63: 36 | O63: 42 | P63: 40 | Q63: 32
A65: REGION KEY - who each region is
A66: Parameter | B66: Value | C66: Unit | D66: Source
A67: UAE | B67: opens M1 | D67: UAE residents - Indian plus other South Asian (Pakistani, Bangladeshi, Sri Lankan, Nepali). COMBINED 2026-08-20 from two separate regions: both sit under one licence, one set of rails and one agent channel, both open at M1, and both are UAE-resident for VAT. They differed only on average ticket (USD 38 vs USD 26), which the blended USD 33.60 preserves at the book level. The core market - the gold-savings habit and the agent network originate here.
A68: Oman and Bahrain | B68: opens M13 | D68: Expatriate workers in Oman and Bahrain. ~600,000 addressable. NOT UAE-resident, so VAT and reporting treatment differ. Requires local authorisation in a second and third jurisdiction, which is why it is the only staged region.
A69: India | B69: opens M1 | D69: India-resident retail investors. ~12.5m addressable, sized BEHAVIOURALLY from gold ETF folios intersected with active digital-gold holders rather than demographically. The payment route is ASSUMED SOLVED in this model - if it is not, this region does not open at all.
A71: MARKET SIZING - how each region's reachable SIP account ceiling is derived
A72: Funnel step | F72: UAE - Indian | G72: UAE - other South Asian | H72: Oman and Bahrain | I72: India
A73: Source population | D73: UPDATED 2026-08-20. UAE-Indian is 4.36m - the Indian consulate's official count at December 2024, also given as 4.3m by the Embassy of India. The brief carried 3.5m, which is roughly a 2021-22 vintage: the community was 3.89m at December 2023 and 4.36m a year later, having doubled from 2.2m over the decade. UAE-other South Asian is 3.46m, the sum of Pakistani 1.90m, Bangladeshi 0.84m, Nepali 0.36m and Sri Lankan 0.36m - the brief's 3.4m was already correct. These are TOTAL RESIDENT NATIONALS including dependants, which is why the economically-active filter below applies. Oman and Bahrain is an expatriate WORKER count. INDIA IS NOT A DEMOGRAPHIC BASE - it is sized BEHAVIOURALLY from gold ETF folios intersected with active digital-gold holders, so its filters are 100%. HELD STATIC over the horizon, which is conservative: the UAE Indian community grew ~12% in the single year to Dec 2024. | F73: 4360000 | G73: 3460000 | H73: 2630000 | I73: 12500000
A74: x Economically active | D74: Oman and Bahrain is 100% because the source counts EXPAT WORKERS, who are working-age and economically active by definition - applying a labour-force filter would double-count. | F74: 0.8 | G74: 0.8 | H74: 1 | I74: 1
A75: x Payment capable (IBAN able to carry a direct debit) | D75: A SIP needs a standing mandate, not just an account. This is the filter that replaced an unsourced gold-savings propensity filter, which was flagged as the weakest link in the entire sizing and had no published source. This one has a stated mechanism behind it. | F75: 0.57 | G75: 0.57 | H75: 0.57 | I75: 1
A76: x Money capable (USD 20/month after remittances) | D76: Discretionary capacity for a RECURRING USD 240/year commitment, tested after remittance obligations rather than before them. | F76: 0.4 | G76: 0.4 | H76: 0.4 | I76: 1
A77: = Addressable base | D77: Population x the three filters. The UAE-Indian column reproduces the brief's worked figure of ~640,000. | F77: =F73*F74*F75*F76 | G77: =G73*G74*G75*G76 | H77: =H73*H74*H75*H76 | I77: =I73*I74*I75*I76
A78: x Penetration ceiling | D78: The share of the addressable base the product could ever reach. 'base x ceiling' is the INVARIANT - changing one without the other silently re-scales the whole model. | F78: 0.1 | G78: 0.1 | H78: 0.06 | I78: 0.01
A79: = REACHABLE SIP ACCOUNTS | D79: This is what the acquisition engine saturates against. | F79: =F77*F78 | G79: =G77*G78 | H79: =H77*H78 | I79: =I77*I78
A80: Feeds model region | F80: UAE | G80: UAE | H80: Oman and Bahrain | I80: India
A82: MARKET CEILINGS AND ACQUISITION DRIVERS
A83: Parameter | B83: Value | C83: Unit | D83: Source
A84: Reachable SIP ceiling - UAE | B84: =F79+G79 | C84: accounts | D84: DERIVED from the market sizing funnel above - the sum of its source populations (UAE - Indian, UAE - other South Asian), not a typed number. Change any filter and this follows.
A85: Reachable SIP ceiling - Oman and Bahrain | B85: =H79 | C85: accounts | D85: DERIVED from the market sizing funnel above - the sum of its source populations (Oman and Bahrain), not a typed number. Change any filter and this follows.
A86: Reachable SIP ceiling - India | B86: =I79 | C86: accounts | D86: DERIVED from the market sizing funnel above - the sum of its source populations (India), not a typed number. Change any filter and this follows.
A87: Total reachable SIP accounts | B87: =$B$84+$B$85+$B$86 | C87: accounts | D87: ~181,150, against the brief's 165,750. THE BRIEF'S 'base x ceiling is the invariant' RULE IS DELIBERATELY BROKEN HERE, and the distinction matters: that rule guards against a METHODOLOGICAL re-cut quietly inflating the market by re-tuning filters, which proves nothing. This is not that - it is a DATA CORRECTION. The UAE Indian population really is 4.36m rather than 3.5m, so the addressable market really is larger. Holding the invariant would mean asserting that penetration falls exactly as population rises, which has no basis. The penetration ceilings are untouched.
A88: CROSS-CHECK vs observed market evidence (memo - feeds nothing)
A89: O Gold active users, UAE (observed) | B89: 75000 | C89: users | D89: OBSERVED. O Gold, the gold engine behind Botim, reported at 75,000 ACTIVE users. The same product is also reported at 775,000 'explored the feature', 1.5m 'users' and 8.5m 'can access' - ACTIVE is the only one of the four comparable to a reachable-accounts figure, and it is the most conservative. CITED.
A90: Our UAE ceiling as a multiple of observed active users | B90: =$B$84/$B$89 | C90: x observed | D90: LIVE, SO IT MOVES IF ANYONE RAISES A CEILING - which is the point. Two INDEPENDENT methods landing within ~2x is the strongest defence of the funnel in this model: the funnel says the UAE can reach ~113,000 SIP accounts, and a real UAE gold app in the same segment has ~75,000 active users today. Our addressable base of ~1.43m sits against 775,000 who explored that product - same order again. If this multiple drifts far above ~2x, the ceiling has stopped being defensible by evidence and is being set by the answer someone wanted. DERIVED from a cited observation.
A91: Oman & Bahrain / India (no comparable figure) | B91: n/a | C91: - | D91: CONFIRMED NEGATIVE, recorded so it is not re-searched. No GCC platform outside the UAE publishes a user count. India publishes only REGISTERED counts (Jar 35m, Augmont 42m) which cannot be deduplicated or converted to active users, so no comparable cross-check can be built. NOTE THAT INDIA'S OWN BASE IS ALREADY user-derived - its 12.5m is 'holds a gold ETF folio or actively buys digital gold', which is why its three filters all sit at 1.00 - AND IT IS THE LEAST TRACEABLE BASE IN THE MODEL. That is the evidence that a user-based method does not automatically produce a better-sourced number.
A93: Active agents - UAE - Y1 | B93: 0 | C93: agents | D93: REGIONALISED 2026-08-26, replacing a single national pool split 45/10/45 by a 'share of salesforce' input. AGENTS NOW BELONG TO A REGION. UAE and Oman & Bahrain are set to ZERO: those markets are acquired top-down through marketing at their own CAC, plus referral. India carries the agent network. THE RAMP IS NO LONGER TYPED - and the schedule it replaces was never the client's. The old 5/15/40/90/200 entered the corpus in the v1.0 brief as 'Active agents | Client input REQUIRED', a placeholder flagged as a question to ask; by the v2.6 rebuild spec the word 'required' had dropped and the source column read 'CLIENT INPUT'. That sequence appears in four documents, all of them ours, and in no client source: the 100 G Business Model gives the three-tier agent STRUCTURE (S11.1) and the 15% commission, but no headcount anywhere. The only genuine client instruction was a +50% raise on 2026-08-21, which scaled a placeholder rather than replacing it. THIS ROW IS NOW OBSERVED. It is Angel One's DISCLOSED Authorised Person count - 42 / 40 / 63 / 186 / 313 across FY18-FY22, a 7.45x rise over four years from a small base - indexed to Y1 and anchored at 40 (client decision 2026-08-26). An Angel One AP is a SEBI-registered independent person who acquires and services retail investors on commission, which is the same animal as an Aurumix agent. The tail (Y6-Y7) is extended at Prudent Corporate Advisory's mature rate, whose MFD base went 14,007 (FY20) to 33,308 (FY25), ~19%/yr. THE OBSERVED Y2 DIP IS FLATTENED, client instruction: Angel One's own FY19 fell 5% on FY18, which is what real networks do - you recruit, most wash out, the survivors compound from year 3. Held FLAT at Y2 instead, which is not a free year: at 45% attrition it still means ~18 hires purely to stand still. TWO CAVEATS ON THE COMPARATORS. Angel One's FY18 is NOT that company's year one - it was founded in 1996 and was rebuilding the AP channel, so this is 'a distributor network scaling from a small base', not 'a startup's first five years'. And both comparators RECRUIT PRE-LICENSED PROFESSIONALS onto a platform rather than creating agents from nothing; gold is not a securities product so Aurumix needs no ARN or SEBI registration, which removes the barrier but also removes the ready pool to poach from. CROSS-CHECKED, AND THIS IS THE STRONGEST PART: sizing agents bottom-up so they are India's primary channel independently gives ~470 at Y7 against this curve's 420 - two unrelated methods, 12% apart. Y4 IS THE YEAR TO QUESTION: 60 to 177 needs 144 hires against a base of 60, nearly tripling the network in twelve months. It is inherited from Angel One's real FY20-FY21 jump (63 to 186), so it is observed rather than invented, but it is the year the plan has to actually deliver. AND IT IS A COST THIS MODEL CANNOT SEE: 857 hires across seven years to end with 420 active, ~224 in Y7 alone, needing 5-6 full-time recruiters and ~28 supervisors at a 1:15 span. OBSERVED (Angel One FY18-FY22, Prudent FY20-FY25); the Y1 anchor is a CLIENT DECISION.
A94: Active agents - UAE - Y2 | B94: 0 | C94: agents | D94: REGIONALISED 2026-08-26, replacing a single national pool split 45/10/45 by a 'share of salesforce' input. AGENTS NOW BELONG TO A REGION. UAE and Oman & Bahrain are set to ZERO: those markets are acquired top-down through marketing at their own CAC, plus referral. India carries the agent network. THE RAMP IS NO LONGER TYPED - and the schedule it replaces was never the client's. The old 5/15/40/90/200 entered the corpus in the v1.0 brief as 'Active agents | Client input REQUIRED', a placeholder flagged as a question to ask; by the v2.6 rebuild spec the word 'required' had dropped and the source column read 'CLIENT INPUT'. That sequence appears in four documents, all of them ours, and in no client source: the 100 G Business Model gives the three-tier agent STRUCTURE (S11.1) and the 15% commission, but no headcount anywhere. The only genuine client instruction was a +50% raise on 2026-08-21, which scaled a placeholder rather than replacing it. THIS ROW IS NOW OBSERVED. It is Angel One's DISCLOSED Authorised Person count - 42 / 40 / 63 / 186 / 313 across FY18-FY22, a 7.45x rise over four years from a small base - indexed to Y1 and anchored at 40 (client decision 2026-08-26). An Angel One AP is a SEBI-registered independent person who acquires and services retail investors on commission, which is the same animal as an Aurumix agent. The tail (Y6-Y7) is extended at Prudent Corporate Advisory's mature rate, whose MFD base went 14,007 (FY20) to 33,308 (FY25), ~19%/yr. THE OBSERVED Y2 DIP IS FLATTENED, client instruction: Angel One's own FY19 fell 5% on FY18, which is what real networks do - you recruit, most wash out, the survivors compound from year 3. Held FLAT at Y2 instead, which is not a free year: at 45% attrition it still means ~18 hires purely to stand still. TWO CAVEATS ON THE COMPARATORS. Angel One's FY18 is NOT that company's year one - it was founded in 1996 and was rebuilding the AP channel, so this is 'a distributor network scaling from a small base', not 'a startup's first five years'. And both comparators RECRUIT PRE-LICENSED PROFESSIONALS onto a platform rather than creating agents from nothing; gold is not a securities product so Aurumix needs no ARN or SEBI registration, which removes the barrier but also removes the ready pool to poach from. CROSS-CHECKED, AND THIS IS THE STRONGEST PART: sizing agents bottom-up so they are India's primary channel independently gives ~470 at Y7 against this curve's 420 - two unrelated methods, 12% apart. Y4 IS THE YEAR TO QUESTION: 60 to 177 needs 144 hires against a base of 60, nearly tripling the network in twelve months. It is inherited from Angel One's real FY20-FY21 jump (63 to 186), so it is observed rather than invented, but it is the year the plan has to actually deliver. AND IT IS A COST THIS MODEL CANNOT SEE: 857 hires across seven years to end with 420 active, ~224 in Y7 alone, needing 5-6 full-time recruiters and ~28 supervisors at a 1:15 span. OBSERVED (Angel One FY18-FY22, Prudent FY20-FY25); the Y1 anchor is a CLIENT DECISION.
A95: Active agents - UAE - Y3 | B95: 0 | C95: agents | D95: REGIONALISED 2026-08-26, replacing a single national pool split 45/10/45 by a 'share of salesforce' input. AGENTS NOW BELONG TO A REGION. UAE and Oman & Bahrain are set to ZERO: those markets are acquired top-down through marketing at their own CAC, plus referral. India carries the agent network. THE RAMP IS NO LONGER TYPED - and the schedule it replaces was never the client's. The old 5/15/40/90/200 entered the corpus in the v1.0 brief as 'Active agents | Client input REQUIRED', a placeholder flagged as a question to ask; by the v2.6 rebuild spec the word 'required' had dropped and the source column read 'CLIENT INPUT'. That sequence appears in four documents, all of them ours, and in no client source: the 100 G Business Model gives the three-tier agent STRUCTURE (S11.1) and the 15% commission, but no headcount anywhere. The only genuine client instruction was a +50% raise on 2026-08-21, which scaled a placeholder rather than replacing it. THIS ROW IS NOW OBSERVED. It is Angel One's DISCLOSED Authorised Person count - 42 / 40 / 63 / 186 / 313 across FY18-FY22, a 7.45x rise over four years from a small base - indexed to Y1 and anchored at 40 (client decision 2026-08-26). An Angel One AP is a SEBI-registered independent person who acquires and services retail investors on commission, which is the same animal as an Aurumix agent. The tail (Y6-Y7) is extended at Prudent Corporate Advisory's mature rate, whose MFD base went 14,007 (FY20) to 33,308 (FY25), ~19%/yr. THE OBSERVED Y2 DIP IS FLATTENED, client instruction: Angel One's own FY19 fell 5% on FY18, which is what real networks do - you recruit, most wash out, the survivors compound from year 3. Held FLAT at Y2 instead, which is not a free year: at 45% attrition it still means ~18 hires purely to stand still. TWO CAVEATS ON THE COMPARATORS. Angel One's FY18 is NOT that company's year one - it was founded in 1996 and was rebuilding the AP channel, so this is 'a distributor network scaling from a small base', not 'a startup's first five years'. And both comparators RECRUIT PRE-LICENSED PROFESSIONALS onto a platform rather than creating agents from nothing; gold is not a securities product so Aurumix needs no ARN or SEBI registration, which removes the barrier but also removes the ready pool to poach from. CROSS-CHECKED, AND THIS IS THE STRONGEST PART: sizing agents bottom-up so they are India's primary channel independently gives ~470 at Y7 against this curve's 420 - two unrelated methods, 12% apart. Y4 IS THE YEAR TO QUESTION: 60 to 177 needs 144 hires against a base of 60, nearly tripling the network in twelve months. It is inherited from Angel One's real FY20-FY21 jump (63 to 186), so it is observed rather than invented, but it is the year the plan has to actually deliver. AND IT IS A COST THIS MODEL CANNOT SEE: 857 hires across seven years to end with 420 active, ~224 in Y7 alone, needing 5-6 full-time recruiters and ~28 supervisors at a 1:15 span. OBSERVED (Angel One FY18-FY22, Prudent FY20-FY25); the Y1 anchor is a CLIENT DECISION.
A96: Active agents - UAE - Y4 | B96: 0 | C96: agents | D96: REGIONALISED 2026-08-26, replacing a single national pool split 45/10/45 by a 'share of salesforce' input. AGENTS NOW BELONG TO A REGION. UAE and Oman & Bahrain are set to ZERO: those markets are acquired top-down through marketing at their own CAC, plus referral. India carries the agent network. THE RAMP IS NO LONGER TYPED - and the schedule it replaces was never the client's. The old 5/15/40/90/200 entered the corpus in the v1.0 brief as 'Active agents | Client input REQUIRED', a placeholder flagged as a question to ask; by the v2.6 rebuild spec the word 'required' had dropped and the source column read 'CLIENT INPUT'. That sequence appears in four documents, all of them ours, and in no client source: the 100 G Business Model gives the three-tier agent STRUCTURE (S11.1) and the 15% commission, but no headcount anywhere. The only genuine client instruction was a +50% raise on 2026-08-21, which scaled a placeholder rather than replacing it. THIS ROW IS NOW OBSERVED. It is Angel One's DISCLOSED Authorised Person count - 42 / 40 / 63 / 186 / 313 across FY18-FY22, a 7.45x rise over four years from a small base - indexed to Y1 and anchored at 40 (client decision 2026-08-26). An Angel One AP is a SEBI-registered independent person who acquires and services retail investors on commission, which is the same animal as an Aurumix agent. The tail (Y6-Y7) is extended at Prudent Corporate Advisory's mature rate, whose MFD base went 14,007 (FY20) to 33,308 (FY25), ~19%/yr. THE OBSERVED Y2 DIP IS FLATTENED, client instruction: Angel One's own FY19 fell 5% on FY18, which is what real networks do - you recruit, most wash out, the survivors compound from year 3. Held FLAT at Y2 instead, which is not a free year: at 45% attrition it still means ~18 hires purely to stand still. TWO CAVEATS ON THE COMPARATORS. Angel One's FY18 is NOT that company's year one - it was founded in 1996 and was rebuilding the AP channel, so this is 'a distributor network scaling from a small base', not 'a startup's first five years'. And both comparators RECRUIT PRE-LICENSED PROFESSIONALS onto a platform rather than creating agents from nothing; gold is not a securities product so Aurumix needs no ARN or SEBI registration, which removes the barrier but also removes the ready pool to poach from. CROSS-CHECKED, AND THIS IS THE STRONGEST PART: sizing agents bottom-up so they are India's primary channel independently gives ~470 at Y7 against this curve's 420 - two unrelated methods, 12% apart. Y4 IS THE YEAR TO QUESTION: 60 to 177 needs 144 hires against a base of 60, nearly tripling the network in twelve months. It is inherited from Angel One's real FY20-FY21 jump (63 to 186), so it is observed rather than invented, but it is the year the plan has to actually deliver. AND IT IS A COST THIS MODEL CANNOT SEE: 857 hires across seven years to end with 420 active, ~224 in Y7 alone, needing 5-6 full-time recruiters and ~28 supervisors at a 1:15 span. OBSERVED (Angel One FY18-FY22, Prudent FY20-FY25); the Y1 anchor is a CLIENT DECISION.
A97: Active agents - UAE - Y5 | B97: 0 | C97: agents | D97: REGIONALISED 2026-08-26, replacing a single national pool split 45/10/45 by a 'share of salesforce' input. AGENTS NOW BELONG TO A REGION. UAE and Oman & Bahrain are set to ZERO: those markets are acquired top-down through marketing at their own CAC, plus referral. India carries the agent network. THE RAMP IS NO LONGER TYPED - and the schedule it replaces was never the client's. The old 5/15/40/90/200 entered the corpus in the v1.0 brief as 'Active agents | Client input REQUIRED', a placeholder flagged as a question to ask; by the v2.6 rebuild spec the word 'required' had dropped and the source column read 'CLIENT INPUT'. That sequence appears in four documents, all of them ours, and in no client source: the 100 G Business Model gives the three-tier agent STRUCTURE (S11.1) and the 15% commission, but no headcount anywhere. The only genuine client instruction was a +50% raise on 2026-08-21, which scaled a placeholder rather than replacing it. THIS ROW IS NOW OBSERVED. It is Angel One's DISCLOSED Authorised Person count - 42 / 40 / 63 / 186 / 313 across FY18-FY22, a 7.45x rise over four years from a small base - indexed to Y1 and anchored at 40 (client decision 2026-08-26). An Angel One AP is a SEBI-registered independent person who acquires and services retail investors on commission, which is the same animal as an Aurumix agent. The tail (Y6-Y7) is extended at Prudent Corporate Advisory's mature rate, whose MFD base went 14,007 (FY20) to 33,308 (FY25), ~19%/yr. THE OBSERVED Y2 DIP IS FLATTENED, client instruction: Angel One's own FY19 fell 5% on FY18, which is what real networks do - you recruit, most wash out, the survivors compound from year 3. Held FLAT at Y2 instead, which is not a free year: at 45% attrition it still means ~18 hires purely to stand still. TWO CAVEATS ON THE COMPARATORS. Angel One's FY18 is NOT that company's year one - it was founded in 1996 and was rebuilding the AP channel, so this is 'a distributor network scaling from a small base', not 'a startup's first five years'. And both comparators RECRUIT PRE-LICENSED PROFESSIONALS onto a platform rather than creating agents from nothing; gold is not a securities product so Aurumix needs no ARN or SEBI registration, which removes the barrier but also removes the ready pool to poach from. CROSS-CHECKED, AND THIS IS THE STRONGEST PART: sizing agents bottom-up so they are India's primary channel independently gives ~470 at Y7 against this curve's 420 - two unrelated methods, 12% apart. Y4 IS THE YEAR TO QUESTION: 60 to 177 needs 144 hires against a base of 60, nearly tripling the network in twelve months. It is inherited from Angel One's real FY20-FY21 jump (63 to 186), so it is observed rather than invented, but it is the year the plan has to actually deliver. AND IT IS A COST THIS MODEL CANNOT SEE: 857 hires across seven years to end with 420 active, ~224 in Y7 alone, needing 5-6 full-time recruiters and ~28 supervisors at a 1:15 span. OBSERVED (Angel One FY18-FY22, Prudent FY20-FY25); the Y1 anchor is a CLIENT DECISION.
A98: Active agents - UAE - Y6 | B98: 0 | C98: agents | D98: REGIONALISED 2026-08-26, replacing a single national pool split 45/10/45 by a 'share of salesforce' input. AGENTS NOW BELONG TO A REGION. UAE and Oman & Bahrain are set to ZERO: those markets are acquired top-down through marketing at their own CAC, plus referral. India carries the agent network. THE RAMP IS NO LONGER TYPED - and the schedule it replaces was never the client's. The old 5/15/40/90/200 entered the corpus in the v1.0 brief as 'Active agents | Client input REQUIRED', a placeholder flagged as a question to ask; by the v2.6 rebuild spec the word 'required' had dropped and the source column read 'CLIENT INPUT'. That sequence appears in four documents, all of them ours, and in no client source: the 100 G Business Model gives the three-tier agent STRUCTURE (S11.1) and the 15% commission, but no headcount anywhere. The only genuine client instruction was a +50% raise on 2026-08-21, which scaled a placeholder rather than replacing it. THIS ROW IS NOW OBSERVED. It is Angel One's DISCLOSED Authorised Person count - 42 / 40 / 63 / 186 / 313 across FY18-FY22, a 7.45x rise over four years from a small base - indexed to Y1 and anchored at 40 (client decision 2026-08-26). An Angel One AP is a SEBI-registered independent person who acquires and services retail investors on commission, which is the same animal as an Aurumix agent. The tail (Y6-Y7) is extended at Prudent Corporate Advisory's mature rate, whose MFD base went 14,007 (FY20) to 33,308 (FY25), ~19%/yr. THE OBSERVED Y2 DIP IS FLATTENED, client instruction: Angel One's own FY19 fell 5% on FY18, which is what real networks do - you recruit, most wash out, the survivors compound from year 3. Held FLAT at Y2 instead, which is not a free year: at 45% attrition it still means ~18 hires purely to stand still. TWO CAVEATS ON THE COMPARATORS. Angel One's FY18 is NOT that company's year one - it was founded in 1996 and was rebuilding the AP channel, so this is 'a distributor network scaling from a small base', not 'a startup's first five years'. And both comparators RECRUIT PRE-LICENSED PROFESSIONALS onto a platform rather than creating agents from nothing; gold is not a securities product so Aurumix needs no ARN or SEBI registration, which removes the barrier but also removes the ready pool to poach from. CROSS-CHECKED, AND THIS IS THE STRONGEST PART: sizing agents bottom-up so they are India's primary channel independently gives ~470 at Y7 against this curve's 420 - two unrelated methods, 12% apart. Y4 IS THE YEAR TO QUESTION: 60 to 177 needs 144 hires against a base of 60, nearly tripling the network in twelve months. It is inherited from Angel One's real FY20-FY21 jump (63 to 186), so it is observed rather than invented, but it is the year the plan has to actually deliver. AND IT IS A COST THIS MODEL CANNOT SEE: 857 hires across seven years to end with 420 active, ~224 in Y7 alone, needing 5-6 full-time recruiters and ~28 supervisors at a 1:15 span. OBSERVED (Angel One FY18-FY22, Prudent FY20-FY25); the Y1 anchor is a CLIENT DECISION.
A99: Active agents - UAE - Y7 | B99: 0 | C99: agents | D99: REGIONALISED 2026-08-26, replacing a single national pool split 45/10/45 by a 'share of salesforce' input. AGENTS NOW BELONG TO A REGION. UAE and Oman & Bahrain are set to ZERO: those markets are acquired top-down through marketing at their own CAC, plus referral. India carries the agent network. THE RAMP IS NO LONGER TYPED - and the schedule it replaces was never the client's. The old 5/15/40/90/200 entered the corpus in the v1.0 brief as 'Active agents | Client input REQUIRED', a placeholder flagged as a question to ask; by the v2.6 rebuild spec the word 'required' had dropped and the source column read 'CLIENT INPUT'. That sequence appears in four documents, all of them ours, and in no client source: the 100 G Business Model gives the three-tier agent STRUCTURE (S11.1) and the 15% commission, but no headcount anywhere. The only genuine client instruction was a +50% raise on 2026-08-21, which scaled a placeholder rather than replacing it. THIS ROW IS NOW OBSERVED. It is Angel One's DISCLOSED Authorised Person count - 42 / 40 / 63 / 186 / 313 across FY18-FY22, a 7.45x rise over four years from a small base - indexed to Y1 and anchored at 40 (client decision 2026-08-26). An Angel One AP is a SEBI-registered independent person who acquires and services retail investors on commission, which is the same animal as an Aurumix agent. The tail (Y6-Y7) is extended at Prudent Corporate Advisory's mature rate, whose MFD base went 14,007 (FY20) to 33,308 (FY25), ~19%/yr. THE OBSERVED Y2 DIP IS FLATTENED, client instruction: Angel One's own FY19 fell 5% on FY18, which is what real networks do - you recruit, most wash out, the survivors compound from year 3. Held FLAT at Y2 instead, which is not a free year: at 45% attrition it still means ~18 hires purely to stand still. TWO CAVEATS ON THE COMPARATORS. Angel One's FY18 is NOT that company's year one - it was founded in 1996 and was rebuilding the AP channel, so this is 'a distributor network scaling from a small base', not 'a startup's first five years'. And both comparators RECRUIT PRE-LICENSED PROFESSIONALS onto a platform rather than creating agents from nothing; gold is not a securities product so Aurumix needs no ARN or SEBI registration, which removes the barrier but also removes the ready pool to poach from. CROSS-CHECKED, AND THIS IS THE STRONGEST PART: sizing agents bottom-up so they are India's primary channel independently gives ~470 at Y7 against this curve's 420 - two unrelated methods, 12% apart. Y4 IS THE YEAR TO QUESTION: 60 to 177 needs 144 hires against a base of 60, nearly tripling the network in twelve months. It is inherited from Angel One's real FY20-FY21 jump (63 to 186), so it is observed rather than invented, but it is the year the plan has to actually deliver. AND IT IS A COST THIS MODEL CANNOT SEE: 857 hires across seven years to end with 420 active, ~224 in Y7 alone, needing 5-6 full-time recruiters and ~28 supervisors at a 1:15 span. OBSERVED (Angel One FY18-FY22, Prudent FY20-FY25); the Y1 anchor is a CLIENT DECISION.
A100: Active agents - Oman and Bahrain - Y1 | B100: 0 | C100: agents | D100: REGIONALISED 2026-08-26, replacing a single national pool split 45/10/45 by a 'share of salesforce' input. AGENTS NOW BELONG TO A REGION. UAE and Oman & Bahrain are set to ZERO: those markets are acquired top-down through marketing at their own CAC, plus referral. India carries the agent network. THE RAMP IS NO LONGER TYPED - and the schedule it replaces was never the client's. The old 5/15/40/90/200 entered the corpus in the v1.0 brief as 'Active agents | Client input REQUIRED', a placeholder flagged as a question to ask; by the v2.6 rebuild spec the word 'required' had dropped and the source column read 'CLIENT INPUT'. That sequence appears in four documents, all of them ours, and in no client source: the 100 G Business Model gives the three-tier agent STRUCTURE (S11.1) and the 15% commission, but no headcount anywhere. The only genuine client instruction was a +50% raise on 2026-08-21, which scaled a placeholder rather than replacing it. THIS ROW IS NOW OBSERVED. It is Angel One's DISCLOSED Authorised Person count - 42 / 40 / 63 / 186 / 313 across FY18-FY22, a 7.45x rise over four years from a small base - indexed to Y1 and anchored at 40 (client decision 2026-08-26). An Angel One AP is a SEBI-registered independent person who acquires and services retail investors on commission, which is the same animal as an Aurumix agent. The tail (Y6-Y7) is extended at Prudent Corporate Advisory's mature rate, whose MFD base went 14,007 (FY20) to 33,308 (FY25), ~19%/yr. THE OBSERVED Y2 DIP IS FLATTENED, client instruction: Angel One's own FY19 fell 5% on FY18, which is what real networks do - you recruit, most wash out, the survivors compound from year 3. Held FLAT at Y2 instead, which is not a free year: at 45% attrition it still means ~18 hires purely to stand still. TWO CAVEATS ON THE COMPARATORS. Angel One's FY18 is NOT that company's year one - it was founded in 1996 and was rebuilding the AP channel, so this is 'a distributor network scaling from a small base', not 'a startup's first five years'. And both comparators RECRUIT PRE-LICENSED PROFESSIONALS onto a platform rather than creating agents from nothing; gold is not a securities product so Aurumix needs no ARN or SEBI registration, which removes the barrier but also removes the ready pool to poach from. CROSS-CHECKED, AND THIS IS THE STRONGEST PART: sizing agents bottom-up so they are India's primary channel independently gives ~470 at Y7 against this curve's 420 - two unrelated methods, 12% apart. Y4 IS THE YEAR TO QUESTION: 60 to 177 needs 144 hires against a base of 60, nearly tripling the network in twelve months. It is inherited from Angel One's real FY20-FY21 jump (63 to 186), so it is observed rather than invented, but it is the year the plan has to actually deliver. AND IT IS A COST THIS MODEL CANNOT SEE: 857 hires across seven years to end with 420 active, ~224 in Y7 alone, needing 5-6 full-time recruiters and ~28 supervisors at a 1:15 span. OBSERVED (Angel One FY18-FY22, Prudent FY20-FY25); the Y1 anchor is a CLIENT DECISION.
A101: Active agents - Oman and Bahrain - Y2 | B101: 0 | C101: agents | D101: REGIONALISED 2026-08-26, replacing a single national pool split 45/10/45 by a 'share of salesforce' input. AGENTS NOW BELONG TO A REGION. UAE and Oman & Bahrain are set to ZERO: those markets are acquired top-down through marketing at their own CAC, plus referral. India carries the agent network. THE RAMP IS NO LONGER TYPED - and the schedule it replaces was never the client's. The old 5/15/40/90/200 entered the corpus in the v1.0 brief as 'Active agents | Client input REQUIRED', a placeholder flagged as a question to ask; by the v2.6 rebuild spec the word 'required' had dropped and the source column read 'CLIENT INPUT'. That sequence appears in four documents, all of them ours, and in no client source: the 100 G Business Model gives the three-tier agent STRUCTURE (S11.1) and the 15% commission, but no headcount anywhere. The only genuine client instruction was a +50% raise on 2026-08-21, which scaled a placeholder rather than replacing it. THIS ROW IS NOW OBSERVED. It is Angel One's DISCLOSED Authorised Person count - 42 / 40 / 63 / 186 / 313 across FY18-FY22, a 7.45x rise over four years from a small base - indexed to Y1 and anchored at 40 (client decision 2026-08-26). An Angel One AP is a SEBI-registered independent person who acquires and services retail investors on commission, which is the same animal as an Aurumix agent. The tail (Y6-Y7) is extended at Prudent Corporate Advisory's mature rate, whose MFD base went 14,007 (FY20) to 33,308 (FY25), ~19%/yr. THE OBSERVED Y2 DIP IS FLATTENED, client instruction: Angel One's own FY19 fell 5% on FY18, which is what real networks do - you recruit, most wash out, the survivors compound from year 3. Held FLAT at Y2 instead, which is not a free year: at 45% attrition it still means ~18 hires purely to stand still. TWO CAVEATS ON THE COMPARATORS. Angel One's FY18 is NOT that company's year one - it was founded in 1996 and was rebuilding the AP channel, so this is 'a distributor network scaling from a small base', not 'a startup's first five years'. And both comparators RECRUIT PRE-LICENSED PROFESSIONALS onto a platform rather than creating agents from nothing; gold is not a securities product so Aurumix needs no ARN or SEBI registration, which removes the barrier but also removes the ready pool to poach from. CROSS-CHECKED, AND THIS IS THE STRONGEST PART: sizing agents bottom-up so they are India's primary channel independently gives ~470 at Y7 against this curve's 420 - two unrelated methods, 12% apart. Y4 IS THE YEAR TO QUESTION: 60 to 177 needs 144 hires against a base of 60, nearly tripling the network in twelve months. It is inherited from Angel One's real FY20-FY21 jump (63 to 186), so it is observed rather than invented, but it is the year the plan has to actually deliver. AND IT IS A COST THIS MODEL CANNOT SEE: 857 hires across seven years to end with 420 active, ~224 in Y7 alone, needing 5-6 full-time recruiters and ~28 supervisors at a 1:15 span. OBSERVED (Angel One FY18-FY22, Prudent FY20-FY25); the Y1 anchor is a CLIENT DECISION.
A102: Active agents - Oman and Bahrain - Y3 | B102: 0 | C102: agents | D102: REGIONALISED 2026-08-26, replacing a single national pool split 45/10/45 by a 'share of salesforce' input. AGENTS NOW BELONG TO A REGION. UAE and Oman & Bahrain are set to ZERO: those markets are acquired top-down through marketing at their own CAC, plus referral. India carries the agent network. THE RAMP IS NO LONGER TYPED - and the schedule it replaces was never the client's. The old 5/15/40/90/200 entered the corpus in the v1.0 brief as 'Active agents | Client input REQUIRED', a placeholder flagged as a question to ask; by the v2.6 rebuild spec the word 'required' had dropped and the source column read 'CLIENT INPUT'. That sequence appears in four documents, all of them ours, and in no client source: the 100 G Business Model gives the three-tier agent STRUCTURE (S11.1) and the 15% commission, but no headcount anywhere. The only genuine client instruction was a +50% raise on 2026-08-21, which scaled a placeholder rather than replacing it. THIS ROW IS NOW OBSERVED. It is Angel One's DISCLOSED Authorised Person count - 42 / 40 / 63 / 186 / 313 across FY18-FY22, a 7.45x rise over four years from a small base - indexed to Y1 and anchored at 40 (client decision 2026-08-26). An Angel One AP is a SEBI-registered independent person who acquires and services retail investors on commission, which is the same animal as an Aurumix agent. The tail (Y6-Y7) is extended at Prudent Corporate Advisory's mature rate, whose MFD base went 14,007 (FY20) to 33,308 (FY25), ~19%/yr. THE OBSERVED Y2 DIP IS FLATTENED, client instruction: Angel One's own FY19 fell 5% on FY18, which is what real networks do - you recruit, most wash out, the survivors compound from year 3. Held FLAT at Y2 instead, which is not a free year: at 45% attrition it still means ~18 hires purely to stand still. TWO CAVEATS ON THE COMPARATORS. Angel One's FY18 is NOT that company's year one - it was founded in 1996 and was rebuilding the AP channel, so this is 'a distributor network scaling from a small base', not 'a startup's first five years'. And both comparators RECRUIT PRE-LICENSED PROFESSIONALS onto a platform rather than creating agents from nothing; gold is not a securities product so Aurumix needs no ARN or SEBI registration, which removes the barrier but also removes the ready pool to poach from. CROSS-CHECKED, AND THIS IS THE STRONGEST PART: sizing agents bottom-up so they are India's primary channel independently gives ~470 at Y7 against this curve's 420 - two unrelated methods, 12% apart. Y4 IS THE YEAR TO QUESTION: 60 to 177 needs 144 hires against a base of 60, nearly tripling the network in twelve months. It is inherited from Angel One's real FY20-FY21 jump (63 to 186), so it is observed rather than invented, but it is the year the plan has to actually deliver. AND IT IS A COST THIS MODEL CANNOT SEE: 857 hires across seven years to end with 420 active, ~224 in Y7 alone, needing 5-6 full-time recruiters and ~28 supervisors at a 1:15 span. OBSERVED (Angel One FY18-FY22, Prudent FY20-FY25); the Y1 anchor is a CLIENT DECISION.
A103: Active agents - Oman and Bahrain - Y4 | B103: 0 | C103: agents | D103: REGIONALISED 2026-08-26, replacing a single national pool split 45/10/45 by a 'share of salesforce' input. AGENTS NOW BELONG TO A REGION. UAE and Oman & Bahrain are set to ZERO: those markets are acquired top-down through marketing at their own CAC, plus referral. India carries the agent network. THE RAMP IS NO LONGER TYPED - and the schedule it replaces was never the client's. The old 5/15/40/90/200 entered the corpus in the v1.0 brief as 'Active agents | Client input REQUIRED', a placeholder flagged as a question to ask; by the v2.6 rebuild spec the word 'required' had dropped and the source column read 'CLIENT INPUT'. That sequence appears in four documents, all of them ours, and in no client source: the 100 G Business Model gives the three-tier agent STRUCTURE (S11.1) and the 15% commission, but no headcount anywhere. The only genuine client instruction was a +50% raise on 2026-08-21, which scaled a placeholder rather than replacing it. THIS ROW IS NOW OBSERVED. It is Angel One's DISCLOSED Authorised Person count - 42 / 40 / 63 / 186 / 313 across FY18-FY22, a 7.45x rise over four years from a small base - indexed to Y1 and anchored at 40 (client decision 2026-08-26). An Angel One AP is a SEBI-registered independent person who acquires and services retail investors on commission, which is the same animal as an Aurumix agent. The tail (Y6-Y7) is extended at Prudent Corporate Advisory's mature rate, whose MFD base went 14,007 (FY20) to 33,308 (FY25), ~19%/yr. THE OBSERVED Y2 DIP IS FLATTENED, client instruction: Angel One's own FY19 fell 5% on FY18, which is what real networks do - you recruit, most wash out, the survivors compound from year 3. Held FLAT at Y2 instead, which is not a free year: at 45% attrition it still means ~18 hires purely to stand still. TWO CAVEATS ON THE COMPARATORS. Angel One's FY18 is NOT that company's year one - it was founded in 1996 and was rebuilding the AP channel, so this is 'a distributor network scaling from a small base', not 'a startup's first five years'. And both comparators RECRUIT PRE-LICENSED PROFESSIONALS onto a platform rather than creating agents from nothing; gold is not a securities product so Aurumix needs no ARN or SEBI registration, which removes the barrier but also removes the ready pool to poach from. CROSS-CHECKED, AND THIS IS THE STRONGEST PART: sizing agents bottom-up so they are India's primary channel independently gives ~470 at Y7 against this curve's 420 - two unrelated methods, 12% apart. Y4 IS THE YEAR TO QUESTION: 60 to 177 needs 144 hires against a base of 60, nearly tripling the network in twelve months. It is inherited from Angel One's real FY20-FY21 jump (63 to 186), so it is observed rather than invented, but it is the year the plan has to actually deliver. AND IT IS A COST THIS MODEL CANNOT SEE: 857 hires across seven years to end with 420 active, ~224 in Y7 alone, needing 5-6 full-time recruiters and ~28 supervisors at a 1:15 span. OBSERVED (Angel One FY18-FY22, Prudent FY20-FY25); the Y1 anchor is a CLIENT DECISION.
A104: Active agents - Oman and Bahrain - Y5 | B104: 0 | C104: agents | D104: REGIONALISED 2026-08-26, replacing a single national pool split 45/10/45 by a 'share of salesforce' input. AGENTS NOW BELONG TO A REGION. UAE and Oman & Bahrain are set to ZERO: those markets are acquired top-down through marketing at their own CAC, plus referral. India carries the agent network. THE RAMP IS NO LONGER TYPED - and the schedule it replaces was never the client's. The old 5/15/40/90/200 entered the corpus in the v1.0 brief as 'Active agents | Client input REQUIRED', a placeholder flagged as a question to ask; by the v2.6 rebuild spec the word 'required' had dropped and the source column read 'CLIENT INPUT'. That sequence appears in four documents, all of them ours, and in no client source: the 100 G Business Model gives the three-tier agent STRUCTURE (S11.1) and the 15% commission, but no headcount anywhere. The only genuine client instruction was a +50% raise on 2026-08-21, which scaled a placeholder rather than replacing it. THIS ROW IS NOW OBSERVED. It is Angel One's DISCLOSED Authorised Person count - 42 / 40 / 63 / 186 / 313 across FY18-FY22, a 7.45x rise over four years from a small base - indexed to Y1 and anchored at 40 (client decision 2026-08-26). An Angel One AP is a SEBI-registered independent person who acquires and services retail investors on commission, which is the same animal as an Aurumix agent. The tail (Y6-Y7) is extended at Prudent Corporate Advisory's mature rate, whose MFD base went 14,007 (FY20) to 33,308 (FY25), ~19%/yr. THE OBSERVED Y2 DIP IS FLATTENED, client instruction: Angel One's own FY19 fell 5% on FY18, which is what real networks do - you recruit, most wash out, the survivors compound from year 3. Held FLAT at Y2 instead, which is not a free year: at 45% attrition it still means ~18 hires purely to stand still. TWO CAVEATS ON THE COMPARATORS. Angel One's FY18 is NOT that company's year one - it was founded in 1996 and was rebuilding the AP channel, so this is 'a distributor network scaling from a small base', not 'a startup's first five years'. And both comparators RECRUIT PRE-LICENSED PROFESSIONALS onto a platform rather than creating agents from nothing; gold is not a securities product so Aurumix needs no ARN or SEBI registration, which removes the barrier but also removes the ready pool to poach from. CROSS-CHECKED, AND THIS IS THE STRONGEST PART: sizing agents bottom-up so they are India's primary channel independently gives ~470 at Y7 against this curve's 420 - two unrelated methods, 12% apart. Y4 IS THE YEAR TO QUESTION: 60 to 177 needs 144 hires against a base of 60, nearly tripling the network in twelve months. It is inherited from Angel One's real FY20-FY21 jump (63 to 186), so it is observed rather than invented, but it is the year the plan has to actually deliver. AND IT IS A COST THIS MODEL CANNOT SEE: 857 hires across seven years to end with 420 active, ~224 in Y7 alone, needing 5-6 full-time recruiters and ~28 supervisors at a 1:15 span. OBSERVED (Angel One FY18-FY22, Prudent FY20-FY25); the Y1 anchor is a CLIENT DECISION.
... A127: Agent blended ramp - Y7 | B127: 1 | C127: x productivity | D127: Six months to full productivity, which happens to match the six-payment gate.
A129: SCENARIO-LINKED INPUTS (live values - move with the scenario switch)
A130: Parameter | B130: Value | C130: Unit | D130: Source
A131: Gold price appreciation | B131: ='Scenario Parameters'!$B$10 | C131: %/yr | D131: ADDED 2026-08-21, client instruction, replacing a flat price. 8.1% is the COMPOUND ANNUAL GROWTH RATE SINCE 1971, the end of the gold standard - chosen because it is the LONGEST window and therefore the least cherry-picked. The shorter the window the better gold looks: ~8.6% over 50 years, ~9-10% over 20, ~13-14% over 10, and over 20% over the last 5. Taking the recent decade would have flattered the model on a rally. CITED. THIS IS A NOMINAL RATE AND NOTHING ELSE IN THE MODEL INFLATES. SIP tickets, spot tickets, CAC, card fees and the B2B fee are all frozen in 2027 dollars. There is NO CONSENSUS POSITIVE LONG-RUN REAL RETURN for gold - it is generally treated as a store of value with a near-zero real yield - so most of this 8.1% IS INFLATION. Applying it to the metal while freezing everything else quietly asserts that gold outruns wages, prices and costs by 8% a year for seven years, which is not a claim anyone would defend out loud. The Model therefore also carries AUM AT THE CONSTANT M1 PRICE, and that is the honest series for judging whether the BUSINESS grew. Conservative is set at 0.0% deliberately: it restores the original flat-price design, under which every revenue change is attributable to the business rather than the metal.
A132: Float buffer - days of demand held | B132: ='Scenario Parameters'!$B$11 | C132: days | D132: S50, the SOFT HALF of the float sizing rule. The corpus states the rule as 'one bar denomination plus a buffer of N days trailing inflow' and NEVER SETS N. WHAT THE BUFFER IS FOR: how long it takes to get REPLACEMENT metal into the vault - dealer lead time, weekend and holiday gaps, payment clearing, and the days a dealer cannot fill 100 g. It is a REPLENISHMENT question. NOT the fill window, which is how long demand takes to CONSUME a bar. The brief anchors the 10 days on the fill window and that is the wrong anchor - how fast the shelf empties and how fast it can be restocked are different questions that only happen to give a similar answer at launch. Corrected here 2026-08-26; the brief still carries the old reasoning. 10 days is a working number for a dealer who has not been chosen yet, and it is DEALER-DEPENDENT: a T+2 commitment would cut the float by roughly two-thirds. IT CHANGES NOTHING AT LAUNCH. Below 10 grams a day - which is about month six - the two-bar floor is larger, so M1 is USD 28,716 for ANY buffer from 0 to 49 days. It binds only at scale, where it is worth USD 64,669 per day of buffer by Y7 and USD 905k between the Aggressive and Conservative settings. ASSUMPTION, and the one to flex: the only number in the float calculation that was neither observed nor settled in the design docs.
A133: Persistency - customers still paying after 12 months | B133: ='Scenario Parameters'!$B$15 | C133: % | D133: THE HEADLINE RETENTION NUMBER, and the one a client can argue with. Everything about churn is derived from it. Governs lifetime value, referral economics and agent commission at once. DERIVED from the archetype work: the simulation can refine it, but 55% is what that engine produced.
...

Sheet Scenario Parameters
A1: =Cover!$B$2
A2: Scenario Parameters
A4: SCENARIO SELECTOR
A6: Select Scenario: | B6: Base | C6: =IF($B$6="Base",1,IF($B$6="Aggressive",2,3)) | D6: <- index | G6: One switch, three columns. Every parameter below resolves through it.
A8: GROUP A0: THE METAL
A9: Parameter | B9: Active Value | C9: Base | D9: Aggressive | E9: Conservative | F9: Unit
A10: Gold price appreciation | B10: =CHOOSE($C$6,C10,D10,E10) | C10: 0.081 | D10: 0.12 | E10: 0 | F10: %/yr | G10: ADDED 2026-08-21, client instruction, replacing a flat price. 8.1% is the COMPOUND ANNUAL GROWTH RATE SINCE 1971, the end of the gold standard - chosen because it is the LONGEST window and therefore the least cherry-picked. The shorter the window the better gold looks: ~8.6% over 50 years, ~9-10% over 20, ~13-14% over 10, and over 20% over the last 5. Taking the recent decade would have flattered the model on a rally. CITED. THIS IS A NOMINAL RATE AND NOTHING ELSE IN THE MODEL INFLATES. SIP tickets, spot tickets, CAC, card fees and the B2B fee are all frozen in 2027 dollars. There is NO CONSENSUS POSITIVE LONG-RUN REAL RETURN for gold - it is generally treated as a store of value with a near-zero real yield - so most of this 8.1% IS INFLATION. Applying it to the metal while freezing everything else quietly asserts that gold outruns wages, prices and costs by 8% a year for seven years, which is not a claim anyone would defend out loud. The Model therefore also carries AUM AT THE CONSTANT M1 PRICE, and that is the honest series for judging whether the BUSINESS grew. Conservative is set at 0.0% deliberately: it restores the original flat-price design, under which every revenue change is attributable to the business rather than the metal.
A11: Float buffer - days of demand held | B11: =CHOOSE($C$6,C11,D11,E11) | C11: 10 | D11: 6 | E11: 20 | F11: days | G11: S50, the SOFT HALF of the float sizing rule. The corpus states the rule as 'one bar denomination plus a buffer of N days trailing inflow' and NEVER SETS N. WHAT THE BUFFER IS FOR: how long it takes to get REPLACEMENT metal into the vault - dealer lead time, weekend and holiday gaps, payment clearing, and the days a dealer cannot fill 100 g. It is a REPLENISHMENT question. NOT the fill window, which is how long demand takes to CONSUME a bar. The brief anchors the 10 days on the fill window and that is the wrong anchor - how fast the shelf empties and how fast it can be restocked are different questions that only happen to give a similar answer at launch. Corrected here 2026-08-26; the brief still carries the old reasoning. 10 days is a working number for a dealer who has not been chosen yet, and it is DEALER-DEPENDENT: a T+2 commitment would cut the float by roughly two-thirds. IT CHANGES NOTHING AT LAUNCH. Below 10 grams a day - which is about month six - the two-bar floor is larger, so M1 is USD 28,716 for ANY buffer from 0 to 49 days. It binds only at scale, where it is worth USD 64,669 per day of buffer by Y7 and USD 905k between the Aggressive and Conservative settings. ASSUMPTION, and the one to flex: the only number in the float calculation that was neither observed nor settled in the design docs.
A13: GROUP A: CUSTOMERS AND CHURN
A14: Parameter | B14: Active Value | C14: Base | D14: Aggressive | E14: Conservative | F14: Unit
A15: Persistency - customers still paying after 12 months | B15: =CHOOSE($C$6,C15,D15,E15) | C15: 0.55 | D15: 0.65 | E15: 0.45 | F15: % | G15: THE HEADLINE RETENTION NUMBER, and the one a client can argue with. Everything about churn is derived from it. Governs lifetime value, referral economics and agent commission at once. DERIVED from the archetype work: the simulation can refine it, but 55% is what that engine produced.
A16: Monthly churn rate (derived) | B16: =1-'Scenario Parameters'!$B$15^(1/12) | F16: %/month | G16: DERIVED, not typed: the monthly rate that reproduces the persistency above over twelve months. Change persistency and this follows. Base 55% implies ~4.9%/month.
A17: Agent productivity | B17: =CHOOSE($C$6,C17,D17,E17) | C17: 6 | D17: 9 | E17: 3 | F17: accounts/agent/month | G17: RE-EVIDENCED 2026-08-26. Base HOLDS at 6; the BANDS widen from 8/3 to 9/3 and the justification is rebuilt on measured comparators instead of resting on a single insurance-agency analogy. WHAT THE EVIDENCE SAYS. IRDAI's Annual Report FY25 gives 270.22 lakh new individual policies against 31.23 lakh individual agents - 8.65 policies per agent per YEAR, or 0.72/month, across the whole book INCLUDING dormant agents. Adjusting for dormancy (MicroSave measures up to 43% inactive across the top four BC network managers) puts an ACTIVE Indian life agent at roughly 1.5-3 per month. BEWARE ONE WIDELY-CIRCULATED FIGURE: an analyst piece states Indian productivity as '0.87 policies per agent per year'. That is an ARITHMETIC SLIP - it divides 27.02 lakh by 31.23 lakh when the numerator is 270.22 lakh. The correct figure is 8.65. Do not cite the 0.87. THE CLOSER COMPARATOR IS THE BANK MITRA / BC NETWORK, which opens a light, form-based account for the same demographic through the same field model: 20-30 accounts per month when the account is FREE, and about 2 per month once a fee is introduced - a 93% collapse, measured by MicroSave. AURUMIX CHARGES 5% ON ENTRY. That is the datapoint arguing 6 is at the OPTIMISTIC end rather than the conservative one, and it is why the conservative band moves from 3 to... 3, but now for a stated reason rather than as a round number. THE OLD NOTE argued 6 was conservative because a gold SIP signup is a fraction of the work of an underwritten insurance policy. That is true, and it is why 6 survives as Base - but it argues only against the insurance figure and is silent on the fee-friction evidence, which points the other way. COMPOUNDS WITH HEADCOUNT: both are execution assumptions, and if either disappoints the other does not compensate. TRIANGULATED at 6, with the band now evidence-led in both directions.
A18: Marketing CAC - UAE | B18: =CHOOSE($C$6,C18,D18,E18) | C18: 85 | D18: 55 | E18: 140 | F18: USD per customer | G18: REGIONALISED 2026-08-20. A single global USD 120 was applied everywhere, which is roughly right for the UAE and badly wrong for India. PUBLISHED BENCHMARKS: Dubai consumer fintech USD 65-220; retail neobank account paid-only USD 35-70; GCC wealthtech funded accounts USD 80-220; 'true' fully-loaded CAC per ACTIVATED customer USD 85-350 against USD 50-100 reported, once KYC, onboarding and non-activating signups are counted. INDIA IS A DIFFERENT MARKET ENTIRELY: consumer fintech INR 500-1,500 (~USD 6-18), neobank savings activation INR 1,100-1,800, wealth and broking apps INR 2,500-5,500 (~USD 30-65); Jupiter reports a USD 5-6 paid CAC. USD 120 is ~INR 10,500 - some 7-20x the Indian mass-market benchmark and still 2-4x its premium wealth apps. UAE is held at 120 as a FULLY-LOADED figure; note it sits at the top of the range for a LOW-TICKET product, and the published low-ticket band is USD 4-70. TRIANGULATED. THIS IS THE YEAR-1 VALUE. CAC now ramps DOWN to the Y7 parameter below - see that note.
A19: Marketing CAC - Oman and Bahrain | B19: =CHOOSE($C$6,C19,D19,E19) | C19: 75 | D19: 50 | E19: 125 | F19: USD per customer | G19: REGIONALISED 2026-08-20. A single global USD 120 was applied everywhere, which is roughly right for the UAE and badly wrong for India. PUBLISHED BENCHMARKS: Dubai consumer fintech USD 65-220; retail neobank account paid-only USD 35-70; GCC wealthtech funded accounts USD 80-220; 'true' fully-loaded CAC per ACTIVATED customer USD 85-350 against USD 50-100 reported, once KYC, onboarding and non-activating signups are counted. INDIA IS A DIFFERENT MARKET ENTIRELY: consumer fintech INR 500-1,500 (~USD 6-18), neobank savings activation INR 1,100-1,800, wealth and broking apps INR 2,500-5,500 (~USD 30-65); Jupiter reports a USD 5-6 paid CAC. USD 120 is ~INR 10,500 - some 7-20x the Indian mass-market benchmark and still 2-4x its premium wealth apps. UAE is held at 120 as a FULLY-LOADED figure; note it sits at the top of the range for a LOW-TICKET product, and the published low-ticket band is USD 4-70. TRIANGULATED. THIS IS THE YEAR-1 VALUE. CAC now ramps DOWN to the Y7 parameter below - see that note.
A20: Marketing CAC - India | B20: =CHOOSE($C$6,C20,D20,E20) | C20: 15 | D20: 9 | E20: 26 | F20: USD per customer | G20: REGIONALISED 2026-08-20. A single global USD 120 was applied everywhere, which is roughly right for the UAE and badly wrong for India. PUBLISHED BENCHMARKS: Dubai consumer fintech USD 65-220; retail neobank account paid-only USD 35-70; GCC wealthtech funded accounts USD 80-220; 'true' fully-loaded CAC per ACTIVATED customer USD 85-350 against USD 50-100 reported, once KYC, onboarding and non-activating signups are counted. INDIA IS A DIFFERENT MARKET ENTIRELY: consumer fintech INR 500-1,500 (~USD 6-18), neobank savings activation INR 1,100-1,800, wealth and broking apps INR 2,500-5,500 (~USD 30-65); Jupiter reports a USD 5-6 paid CAC. USD 120 is ~INR 10,500 - some 7-20x the Indian mass-market benchmark and still 2-4x its premium wealth apps. UAE is held at 120 as a FULLY-LOADED figure; note it sits at the top of the range for a LOW-TICKET product, and the published low-ticket band is USD 4-70. TRIANGULATED. THIS IS THE YEAR-1 VALUE. CAC now ramps DOWN to the Y7 parameter below - see that note.
A21: Marketing CAC at Y7 - UAE | B21: =CHOOSE($C$6,C21,D21,E21) | C21: 55 | D21: 36 | E21: 91 | F21: USD per customer | G21: CLIENT INSTRUCTION 2026-08-26: CAC RAMPS DOWN over the horizon rather than sitting flat. UAE 85->55, Oman and Bahrain 75->45, India 15->10, interpolated LINEARLY on model year. Aggressive and Conservative hold the same proportional decline as Base. WHY IT FALLS: brand recognition compounds, organic and word-of-mouth grow off a larger base, and paid channels get cheaper per acquisition as creative, targeting and funnel conversion are tuned. IT CUTS AGAINST THE MODEL'S OWN CAUTION ELSEWHERE - S25's convexity switch says CAC RISES with spend because you buy progressively worse audiences. Both are real and they pull in opposite directions; this ramp asserts that the learning effect wins over seven years. IT IS NOT A COST SAVING - IT IS A REVENUE INCREASE. The marketing budget is fixed by schedule, so a lower CAC buys MORE CUSTOMERS for the same money. Marketing spend does not fall by a dollar.
A22: Marketing CAC at Y7 - Oman and Bahrain | B22: =CHOOSE($C$6,C22,D22,E22) | C22: 45 | D22: 30 | E22: 75 | F22: USD per customer | G22: CLIENT INSTRUCTION 2026-08-26: CAC RAMPS DOWN over the horizon rather than sitting flat. UAE 85->55, Oman and Bahrain 75->45, India 15->10, interpolated LINEARLY on model year. Aggressive and Conservative hold the same proportional decline as Base. WHY IT FALLS: brand recognition compounds, organic and word-of-mouth grow off a larger base, and paid channels get cheaper per acquisition as creative, targeting and funnel conversion are tuned. IT CUTS AGAINST THE MODEL'S OWN CAUTION ELSEWHERE - S25's convexity switch says CAC RISES with spend because you buy progressively worse audiences. Both are real and they pull in opposite directions; this ramp asserts that the learning effect wins over seven years. IT IS NOT A COST SAVING - IT IS A REVENUE INCREASE. The marketing budget is fixed by schedule, so a lower CAC buys MORE CUSTOMERS for the same money. Marketing spend does not fall by a dollar.
A23: Marketing CAC at Y7 - India | B23: =CHOOSE($C$6,C23,D23,E23) | C23: 10 | D23: 6 | E23: 17 | F23: USD per customer | G23: CLIENT INSTRUCTION 2026-08-26: CAC RAMPS DOWN over the horizon rather than sitting flat. UAE 85->55, Oman and Bahrain 75->45, India 15->10, interpolated LINEARLY on model year. Aggressive and Conservative hold the same proportional decline as Base. WHY IT FALLS: brand recognition compounds, organic and word-of-mouth grow off a larger base, and paid channels get cheaper per acquisition as creative, targeting and funnel conversion are tuned. IT CUTS AGAINST THE MODEL'S OWN CAUTION ELSEWHERE - S25's convexity switch says CAC RISES with spend because you buy progressively worse audiences. Both are real and they pull in opposite directions; this ramp asserts that the learning effect wins over seven years. IT IS NOT A COST SAVING - IT IS A REVENUE INCREASE. The marketing budget is fixed by schedule, so a lower CAC buys MORE CUSTOMERS for the same money. Marketing spend does not fall by a dollar.
A24: Marketing spend share - UAE | B24: =CHOOSE($C$6,C24,D24,E24) | C24: 0.74 | D24: 0.74 | E24: 0.74 | F24: % of budget | G24: RE-BASED 2026-08-26 from 58/16/26, when India moved to an agent-led channel. India falls to 8% - a SUPPORT budget, not an acquisition engine - and UAE and Oman & Bahrain absorb the residual, split roughly 80:20 by each region's share of its own reachable ceiling. THE REASON IS STRUCTURAL, NOT A PREFERENCE. UAE and Oman & Bahrain now have NO agent channel at all, so marketing plus referral is the WHOLE of their acquisition and the budget has to carry it. India's 420 agents carry ~57% of its new accounts by Y7, so its budget does not. WHAT THIS FIXES: holding India at 26% meant a USD 1.65m budget at a USD 15 CAC buying 35,750 accounts a year, which is what the model did before. India LOOKED agent-led while actually being carried by a cheap-CAC assumption - marketing was 67% of Indian raw demand at Y7 and agents only 11%, the reverse of how the business is described. Does not vary by scenario - it is a management decision, not an uncertainty. Must sum to 100%.
A25: Marketing spend share - Oman and Bahrain | B25: =CHOOSE($C$6,C25,D25,E25) | C25: 0.18 | D25: 0.18 | E25: 0.18 | F25: % of budget | G25: RE-BASED 2026-08-26 from 58/16/26, when India moved to an agent-led channel. India falls to 8% - a SUPPORT budget, not an acquisition engine - and UAE and Oman & Bahrain absorb the residual, split roughly 80:20 by each region's share of its own reachable ceiling. THE REASON IS STRUCTURAL, NOT A PREFERENCE. UAE and Oman & Bahrain now have NO agent channel at all, so marketing plus referral is the WHOLE of their acquisition and the budget has to carry it. India's 420 agents carry ~57% of its new accounts by Y7, so its budget does not. WHAT THIS FIXES: holding India at 26% meant a USD 1.65m budget at a USD 15 CAC buying 35,750 accounts a year, which is what the model did before. India LOOKED agent-led while actually being carried by a cheap-CAC assumption - marketing was 67% of Indian raw demand at Y7 and agents only 11%, the reverse of how the business is described. Does not vary by scenario - it is a management decision, not an uncertainty. Must sum to 100%.
A26: Marketing spend share - India | B26: =CHOOSE($C$6,C26,D26,E26) | C26: 0.08 | D26: 0.08 | E26: 0.08 | F26: % of budget | G26: RE-BASED 2026-08-26 from 58/16/26, when India moved to an agent-led channel. India falls to 8% - a SUPPORT budget, not an acquisition engine - and UAE and Oman & Bahrain absorb the residual, split roughly 80:20 by each region's share of its own reachable ceiling. THE REASON IS STRUCTURAL, NOT A PREFERENCE. UAE and Oman & Bahrain now have NO agent channel at all, so marketing plus referral is the WHOLE of their acquisition and the budget has to carry it. India's 420 agents carry ~57% of its new accounts by Y7, so its budget does not. WHAT THIS FIXES: holding India at 26% meant a USD 1.65m budget at a USD 15 CAC buying 35,750 accounts a year, which is what the model did before. India LOOKED agent-led while actually being carried by a cheap-CAC assumption - marketing was 67% of Indian raw demand at Y7 and agents only 11%, the reverse of how the business is described. Does not vary by scenario - it is a management decision, not an uncertainty. Must sum to 100%.
A27: Referral rate | B27: =CHOOSE($C$6,C27,D27,E27) | C27: 0.6 | D27: 1.1 | E27: 0.25 | F27: referrals/customer/yr | G27: RAISED 2026-08-21 from 0.45, client instruction. Cap removed deliberately, so the distribution is right-skewed - MODEL THE MEAN, NOT THE MEDIAN. 0.60 means the average customer produces roughly three referrals every five years; the mean is pulled up by a small number of highly social referrers, which is the normal shape for a trust-based product inside a tight diaspora community. IT IS STILL AN ASSUMPTION WITH NO EXTERNAL ANCHOR, and it compounds: referrals feed the paying base, which feeds more referrals. That loop is the reason this parameter is more load-bearing than its size suggests. ASSUMPTION.
A28: Referral conversion | B28: =CHOOSE($C$6,C28,D28,E28) | C28: 0.62 | D28: 0.72 | E28: 0.48 | F28: % | G28: The M7 survival of the referred cohort, uplifted ~1.1x. DERIVED.
... A30: Seasonality amplitude | B30: =CHOOSE($C$6,C30,D30,E30) | C30: 1 | D30: 1.4 | E30: 0.6 | F30: x deviation from 1.0 | G30: Festival TIMING is sourced; how hard a Dubai savings signup responds to Dhanteras is the open question. Applied to the deviation from 1.0, then renormalised, so the vectors stay at exactly 12.000.
A32: GROUP B: ICS BENEFIT ENTITLEMENT - no longer gates ACCESS, only BENEFITS
A33: Parameter | B33: Active Value | C33: Base | D33: Aggressive | E33: Conservative | F33: Unit
A34: Customers who EVER reach an ICS benefit tier | B34: =CHOOSE($C$6,C34,D34,E34) | C34: 0.55 | D34: 0.65 | E34: 0.45 | F34: % of customers | G34: REPURPOSED 2026-08-26 (CG decision). THIS CELL NO LONGER GATES ACCESS TO ANYTHING. The card and the credit facility are now open to the whole book regardless of SIP status or ICS tier; what ICS still governs is BENEFITS - fee discounts, better FX rates, family-wallet pricing, gold reward rebates. IT FEEDS NO REVENUE ROW TODAY. It is carried as a memo on the Model so the ICS-entitled population is already computed when the cost and discount build lands, because every one of those benefits is a give-back that has to be sized against a population. Deleting it would mean rebuilding it a day later. WHAT IT USED TO DO, AND WHY THE CHANGE IS LARGE: it restricted the card streams to the 55% who ever cleared a six-payment gate, so removing it widens the card population by 1/0.55 = 1.82x AND removes the ~8-month lag before anyone qualified. The old note called this 'the single most load-bearing parameter in the model' and claimed the card streams were ~83% of gross profit; BOTH STATEMENTS ARE NOW STALE - there is no gross-profit line in this build at all, and on the current numbers the card streams are a far smaller share of revenue than that. The 55% itself is unchanged and still the OUTPUT of the run-of-6 first-passage engine validated against the archetype mix, which now lives in the Phase 5 simulation. Whether ICS ENTITLEMENT should use the same threshold as the old payment gate is an OPEN QUESTION for the mechanism-design update - it is inherited here, not decided.
A35: Average months to reach an ICS benefit tier | B35: =CHOOSE($C$6,C35,D35,E35) | C35: 8 | D35: 6 | E35: 11 | F35: months | G35: REPURPOSED 2026-08-26 with the row above - it no longer delays card access, only benefit entitlement. Tier arrival is a DISTRIBUTION, not a date: a customer who misses month 4 cannot qualify before month 9. The validated mean is M8.0, against the naive assumption of M6. UNDER THE OLD DESIGN those two extra months pushed every card ladder date to the right and were worth real revenue; under the new one they delay only the point at which a customer starts COSTING money in discounts, which is the opposite sign. DERIVED.
A37: GROUP C: AUM, LEAKAGE AND SPOT
A38: Parameter | B38: Active Value | C38: Base | D38: Aggressive | E38: Conservative | F38: Unit
A39: Gold moved out of Aurumix's control | B39: =CHOOSE($C$6,C39,D39,E39) | C39: 0.06 | D39: 0.03 | E39: 0.18 | F39: % of AUM/yr | G39: HALVED 2026-08-21 from 0.12, client instruction. NOTE IT HAS ZERO EFFECT ON GOLD UNDER CUSTODY - measured, not asserted - because self-custodied metal never left the vault and was never in that measure. It moves ONLY the collateral-eligible base and therefore the card credit limit, worth ~0.2% of Y7 revenue. RELABELLED earlier the same day after the client correctly objected to the old name, 'self-custody leakage'. THE GOLD DOES NOT LEAVE THE VAULT: a token moving to a customer's own wallet sells nothing and burns nothing, so calling it an AUM decrease was wrong. What it does leave is Aurumix's COLLATERAL-ELIGIBLE base - Aurumix cannot foreclose on a token sitting in a private wallet, so that gold can no longer back a credit limit. In this model AUM has exactly ONE consumer, the card credit limit, so the arithmetic was always right and only the label was misleading. THAT ONE-CONSUMER PROPERTY IS WHAT MAKES THIS SAFE: if a later build points anything else at AUM - a custody fee, a reported-AUM headline - this row must be split in two first. Contrast the redemption line, which IS gold genuinely gone. ASSUMPTION.
A40: Redemption rate | B40: =CHOOSE($C$6,C40,D40,E40) | C40: 0.06 | D40: 0.035 | E40: 0.12 | F40: % of AUM/yr | G40: LOWERED 2026-08-21 from 0.08, client instruction - AND THIS ONE MOVES TOWARDS THE EVIDENCE, not away from it. PAXG turnover of 5.9% is the only comparator that exists, and 8% sat above it for no stated reason; 6% sits essentially on it. A DIFFERENT EVENT from gold moving out of Aurumix's control, and a separate line: this is metal actually sold and tokens burned. VARA forbids charging any fee on it. ASSUMPTION, now aligned to the single available comparator.
A41: Holder redemption multiplier | B41: =CHOOSE($C$6,C41,D41,E41) | C41: 1.6 | D41: 1.3 | E41: 2.8 | F41: x the paying rate | G41: LOWERED 2026-08-21 from 2.2, client instruction. THIS IS THE WEAKEST OF THE THREE DECAY CHANGES. The LOGIC behind a multiplier above 1.0 is untouched and still holds: customers who stopped paying redeem faster, because they have no accruing benefit left to protect. Lowering it to 1.6 weakens that argument without new evidence for the smaller number - it says lapsed customers are stickier than previously assumed, which is the convenient direction. Because holders become the majority of the book by Y4, this remains the DOMINANT AUM DECAY TERM from roughly Y4, so the change is not cosmetic. ASSUMPTION, and the first one to revisit if AUM is challenged.
A42: Spot attach scenario multiplier | B42: =CHOOSE($C$6,C42,D42,E42) | C42: 1 | D42: 1.7 | E42: 0.5 | F42: x the regional attach | G42: REGIONALISED 2026-08-21. The attach LEVEL now sits per region on Assumptions (UAE 12%, Oman & Bahrain 10%, India 25%); this dial carries only the uncertainty around it, preserving the old 14/24/7 spread (1.00 / 1.70 / 0.50). ONE DIAL, NOT THREE TRIPLETS - nine numbers to defend, and a scenario could otherwise silently invert the regional ordering that affordability establishes. See the regional rows on Assumptions for the reasoning. ASSUMPTION about spread.
A43: Spot ticket scenario multiplier | B43: =CHOOSE($C$6,C43,D43,E43) | C43: 1 | D43: 1.35 | E43: 0.7 | F43: x the observed ticket | G43: REPLACED the global 'Average spot ticket' on 2026-08-21. The LEVEL is no longer a scenario input: each region now carries its own OBSERVED ticket on Assumptions (UAE 190 from Botim, India 40 from Augmont, Oman & Bahrain 145 inferred). This parameter carries only the UNCERTAINTY around those observations, as a single dial. WHY ONE DIAL AND NOT THREE: three regional triplets would be nine numbers to defend and would let a scenario silently invert the regional ordering that the sources establish. One multiplier flexes the level and PRESERVES the ordering. Aggressive 1.35 puts the UAE at ~257, still under the AED 1,000 mark; conservative 0.70 puts it at ~133, below Botim's own sub-AED-500 majority. ASSUMPTION about spread, applied to observed levels.
A44: Spot frequency | B44: =CHOOSE($C$6,C44,D44,E44) | C44: 1.7 | D44: 2.4 | E44: 1.2 | F44: events/attacher/yr | G44: PROVENANCE CORRECTED 2026-08-21 - THE NUMBER STANDS, ITS OLD CITATION DID NOT. The previous note read 'Botim's 128,000 trades against ~45,000 buyers implies ~1.9/yr'. THE 45,000 IS NOT A BUYER COUNT, IT IS A TRANSACTION COUNT: Khaleej Times, Nov 2025, says 775,000 users EXPLORED the feature, 'completing over 45,000 transactions'. The 128,000 is also transactions, to Feb 2026. So the old derivation divided transactions by transactions across two different windows - the result was the growth in cumulative trades, not a frequency. CONFIRMED NEGATIVE: Botim has never published a unique-buyer count, so no frequency can be derived from it, and no published frequency exists ANYWHERE for ad-hoc lump gold purchases. Comparators are 0.85/yr (Augmont, per REGISTERED user, at an average transaction of Rs 331 - micro-saving, not lumps) and 264/yr (Jar, Rs 10/day auto-roundups) - a 300x spread, neither being this product. WHAT DOES SUPPORT 1.7 is a cross-check on the COMBINED basis, attach x frequency x ticket, which is comparable: Aurumix India implies ~Rs 838/yr of gold per paying customer against Augmont's ~Rs 281/yr per registered user. 3x, and defensible - our customers are engaged SIP savers, not dormant registrations. Behaviourally 1.7 is also about right for festive lumps: Dhanteras, Akshaya Tritiya and a wedding is roughly two events. ASSUMPTION, cross-checked on the combined basis, NOT directly sourced.
A46: GROUP D: CARD
A47: Parameter | B47: Active Value | C47: Base | D47: Aggressive | E47: Conservative | F47: Unit
A48: Programme manager share of interchange | B48: =CHOOSE($C$6,C48,D48,E48) | C48: 0.6 | D48: 0.36 | E48: 0.85 | F48: % | G48: LOWERED 2026-08-21 from 0.72, client instruction - AURUMIX NOW KEEPS 40% RATHER THAN 28%. 0.60 sits comfortably inside the 36-85% observed range and is roughly its midpoint, so the base case moves from the pessimistic end to a neutral one. It assumes a NEGOTIATED deal rather than a take-it-or-leave-it one, which is reasonable for a programme with a gold-collateral proposition the manager cannot source elsewhere - but it IS an assumption about a contract that does not exist yet, and the only honest way to hold it is to treat 40% as a target to negotiate to, not a rate already won. BANDS CORRECTED earlier the same day - THEY WERE INVERTED. Aggressive was 0.85 and conservative 0.55, meaning the OPTIMISTIC scenario handed MORE of the interchange to the programme manager and cut Aurumix's share from 28% to 15%. Every other cost-like parameter in this model improves under Aggressive - redemption, CAC, self-custody, the holder multiplier - and this one moved the other way. Flipping the scenario made interchange fall 46% in the good case and rise 61% in the bad one. Aggressive is now 0.36, THE DOCUMENTED FLOOR, which is the best deal observed anywhere and the right walk-away to take into a sponsor conversation - at that level Aurumix keeps 64% rather than 28%, and interchange more than doubles. Conservative is 0.85. WHY AURUMIX ONLY GETS A SLICE AT ALL: it is not a bank and cannot issue cards, so a programme manager holds the BIN, the scheme membership, settlement and dispute handling, and takes the majority for it. That much is normal. 72% is near the BAD END of the 36-85% range, so the base case is deliberately unfavourable - THIS IS A COMMERCIAL NEGOTIATION, NOT A MODELLING ASSUMPTION, and it is one of the few places where a better contract directly doubles a revenue line. No UAE/MENA figure is published. TRIANGULATED.
A49: Facility take-up - customers who take AND use the card | B49: =CHOOSE($C$6,C49,D49,E49) | C49: 0.18 | D49: 0.3 | E49: 0.08 | F49: % of card-eligible base | G49: RE-BASED AGAIN 2026-08-26 (CG decision): the denominator changed from GATE-CLEARED customers to the WHOLE CARD-ELIGIBLE BASE, because access is no longer gated. The RATE holds at 18% on client instruction, and that decision deserves to be stated plainly rather than buried. 18% WAS CALIBRATED ON A PRE-SELECTED POPULATION. It is Indian gold-loan penetration - under 10% at a point in time - uplifted BECAUSE the customers it applied to had already proven six consecutive payments. Removing the gate removes that pre-selection but keeps the uplift, so the rate is now applied to a materially less committed population than the one it was derived from. The arithmetic is unambiguous: the base widens 1.82x and the conversion rate does not fall, so the card population rises 1.82x on this change alone. IF CARD REVENUE IS CHALLENGED, THIS IS THE FIRST CELL TO LOOK AT - the defensible alternative is ~10%, the unadjusted benchmark. AGAINST THAT: open access plus ICS discounts is a genuinely different proposition from a gated facility, and there is no benchmark at all for an open gold-collateralised card, so 18% is not refutable either. It is a judgement, and it should be presented as one. CLIENT DECISION on the level; DERIVED on the benchmark beneath it. CARRIED FORWARD FROM 2026-08-20, and still true: THE CARD IS A DRAWDOWN ON THE GOLD-COLLATERALISED FACILITY, not a salary-repaid revolving card. Aurumix has no balance sheet to lend from - it can only extend credit against collateral it holds, which is the customer's gold. Using the card IS borrowing, so card activation and credit take-up are the SAME behaviour; they were once modelled as two different populations (50% activating a card, 18% taking credit) doing what is in fact one thing. THE OLD 50% CAME FROM NEOBANK COMPARABLES (PULSE 68.2%, Monzo 68%) WHERE THE CARD IS THE PRODUCT - wrong in kind for a card that only lets you borrow against your own savings, and worth remembering now that access is open, because an open card invites exactly that comparison again.
A50: Transactions per drawdown event | B50: =CHOOSE($C$6,C50,D50,E50) | C50: 4 | D50: 6 | E50: 2 | F50: transactions/draw | G50: RE-BASED 2026-08-20 from 12 transactions/MONTH once the card became a drawdown on the gold facility. Under that model the customer borrows a lump (limit x drawn share) a couple of times a year and spends it down, so the meaningful unit is transactions PER DRAW, not per month. At 12/month the implied ticket collapsed to ~AED 12, which is a coffee, not a reason to pledge your gold. THE AVERAGE TICKET FALLS OUT AS drawn amount / this number, and the draw events cancel - so the ticket depends only on how large a draw is and how many purchases it is spent across. IT ALSO CHANGES WHAT THE CARD IS FOR: not daily groceries, but occasional larger needs - school fees, a medical bill, an emergency - funded by borrowing against savings rather than liquidating them. That is a materially different product story and should be put to the client in those words. ASSUMPTION.
A51: Foreign spend share (mean) | B51: =CHOOSE($C$6,C51,D51,E51) | C51: 0.34 | D51: 0.45 | E51: 0.24 | F51: % of card spend | G51: Applied through the seasonal vector, not as a constant. ASSUMPTION.
A52: Card REISSUE rate (excludes first issue) | B52: =CHOOSE($C$6,C52,D52,E52) | C52: 0.06 | D52: 0.04 | E52: 0.1 | F52: reissues/card/yr | G52: CORRECTED 2026-08-26, and this replaces 'Card issuance events' at 1.06/card/yr. THE OLD ROW WAS A REAL DEFECT, not a re-cut. 1.06 events per card per YEAR was applied to the STOCK of active cards, which charged the AED 75 issuance fee to every existing cardholder every single year - an ANNUAL FEE, not an issuance fee, and the row's own note said so: '1.00 at activation plus reissues'. The 1.00 belongs to the year a card is ACTIVATED and must be charged on NEW cards; only the 0.06 residual is a recurring per-card event. WHAT IT WAS WORTH. At Y7 it charged ~33,980 issuance events against ~9,100 real ones, roughly 3.7x too many, or ~USD 507,000 - about 11% of total revenue. It predates the 2026-08-26 access change, but that change multiplied the card stock by 1.82x and so multiplied the error with it, taking issuance from ~6% of revenue to ~15% before this fix. IT WAS THE LARGEST SINGLE ERROR IN THE MODEL. 0.06 is what remains once first issue is removed: a tier upgrade forces a physical reissue, and under the ICS design tier changes are the main trigger. ASSUMPTION. STILL NOT IMPLEMENTED, and it belongs to the discount build: the fee input's own note says issuance is 'waived at upper tiers'. Nothing waives it. Under the new design that waiver is exactly the kind of ICS benefit being priced tomorrow, so wire it there rather than here.
A53: Card replacement events | B53: =CHOOSE($C$6,C53,D53,E53) | C53: 0.11 | D53: 0.07 | E53: 0.18 | F53: events/card/yr | G53: Industry-normal loss/theft/damage is 8-15% annually. ASSUMPTION.
A54: ATM AED 0-500 - share of cardholders | B54: =CHOOSE($C$6,C54,D54,E54) | C54: 0.6 | D54: 0.42 | E54: 0.74 | F54: % | G54: KEPT AS A DISTRIBUTION DELIBERATELY. The mean draw (~AED 940) sits just BELOW the free allowance of AED 1,000 BY DESIGN, so applying the fee to the mean returns EXACTLY ZERO and stream 4 silently loses a component. The distribution returns materially more, generated almost entirely by a small high-cash tail. ASSUMPTION.
A55: ATM AED 500-1,500 - share of cardholders | B55: =CHOOSE($C$6,C55,D55,E55) | C55: 0.25 | D55: 0.3 | E55: 0.18 | F55: % | G55: KEPT AS A DISTRIBUTION DELIBERATELY. The mean draw (~AED 940) sits just BELOW the free allowance of AED 1,000 BY DESIGN, so applying the fee to the mean returns EXACTLY ZERO and stream 4 silently loses a component. The distribution returns materially more, generated almost entirely by a small high-cash tail. ASSUMPTION.
A56: ATM AED 1,500-3,000 - share of cardholders | B56: =CHOOSE($C$6,C56,D56,E56) | C56: 0.12 | D56: 0.2 | E56: 0.06 | F56: % | G56: KEPT AS A DISTRIBUTION DELIBERATELY. The mean draw (~AED 940) sits just BELOW the free allowance of AED 1,000 BY DESIGN, so applying the fee to the mean returns EXACTLY ZERO and stream 4 silently loses a component. The distribution returns materially more, generated almost entirely by a small high-cash tail. ASSUMPTION.
A57: ATM AED 3,000+ - share of cardholders | B57: =CHOOSE($C$6,C57,D57,E57) | C57: 0.03 | D57: 0.08 | E57: 0.02 | F57: % | G57: KEPT AS A DISTRIBUTION DELIBERATELY. The mean draw (~AED 940) sits just BELOW the free allowance of AED 1,000 BY DESIGN, so applying the fee to the mean returns EXACTLY ZERO and stream 4 silently loses a component. The distribution returns materially more, generated almost entirely by a small high-cash tail. ASSUMPTION.
A58: ATM AED 0-500 - midpoint draw | B58: =CHOOSE($C$6,C58,D58,E58) | C58: 250 | D58: 300 | E58: 200 | F58: AED/month | G58: Raising the allowance at the top tier waives revenue from only the top ~3% of cardholders.
A59: ATM AED 500-1,500 - midpoint draw | B59: =CHOOSE($C$6,C59,D59,E59) | C59: 1000 | D59: 1100 | E59: 900 | F59: AED/month | G59: Raising the allowance at the top tier waives revenue from only the top ~3% of cardholders.
... A61: ATM AED 3,000+ - midpoint draw | B61: =CHOOSE($C$6,C61,D61,E61) | C61: 4000 | D61: 4500 | E61: 3600 | F61: AED/month | G61: Raising the allowance at the top tier waives revenue from only the top ~3% of cardholders.
A63: GROUP E: CREDIT, B2B AND FAMILY
A64: Parameter | B64: Active Value | C64: Base | D64: Aggressive | E64: Conservative | F64: Unit
A65: Drawn as % of permitted limit | B65: =CHOOSE($C$6,C65,D65,E65) | C65: 0.5 | D65: 0.7 | E65: 0.3 | F65: % | G65: Revolving facilities draw 40-55% of permitted. This now drives CARD SPEND as well as the loan balance, because the card is the drawdown mechanism. TRIANGULATED.
A66: Facility turnover, peak -> average | B66: =CHOOSE($C$6,C66,D66,E66) | C66: 0.42 | D66: 0.55 | E66: 0.3 | F66: x peak drawn | G66: AN ARITHMETIC CORRECTION, not a sensitivity, derived from Manappuram's 71-day realised tenor. It cuts the lending stream by 1.88x. DERIVED.
A67: Draw events per borrower per year | B67: =CHOOSE($C$6,C67,D67,E67) | C67: 2.1 | D67: 3.2 | E67: 1.3 | F67: events/yr | G67: MOVES WITH facility turnover - do not flex independently. DERIVED.
A68: Family plan attach rate | B68: =CHOOSE($C$6,C68,D68,E68) | C68: 0.15 | D68: 0.25 | E68: 0.08 | F68: % of NEW customers | G68: SET AT 0.15 on 2026-08-21, client instruction - the same day it came DOWN from 0.20 to 0.08, so it has landed close to where it started. What has genuinely changed is not the number but the STRUCTURE. THE UNIT ALSO CHANGED, AND THAT MATTERS: it is now the share of NEW customers who take the plan when they join, feeding a SUBSCRIBER BALANCE that then churns - not a standing share of the whole book that could never fall. The steady-state share of paying customers holding a plan therefore lands BELOW this number. NOTHING IS STATED ANYWHERE IN THE CORPUS and no attach benchmark exists for this kind of add-on; 20% is at the top of the normal range for an OPTIONAL PAID extra on a savings product, which is low single digits to low teens. IT IS NOT EQUIVALENT TO THE OLD 20% AND SHOULD NOT BE READ AS A PARTIAL REVERSAL: 20% was a permanent share of the whole book that could never decay, while 15% applies once, on joining, to a balance that then churns at ~7.1% a month. The standing share of paying customers holding a plan settles near 10.5%, not 15%. NOTHING IS STATED ANYWHERE IN THE CORPUS and no attach benchmark exists for this kind of add-on. ASSUMPTION.
A69: Family plan cancellation rate (incremental) | B69: =CHOOSE($C$6,C69,D69,E69) | C69: 0.25 | D69: 0.15 | E69: 0.4 | F69: %/yr | G69: ADDED 2026-08-21. INCREMENTAL IS THE KEY WORD: this is cancellation by customers who STAY WITH AURUMIX. Subscribers already disappear when they stop paying their SIP, and that was the only churn stream 3 had - which implicitly assumed nobody ever cancels the plan while remaining a customer. NO PRODUCT-SPECIFIC DATA EXISTS - not for digital will memberships, not for finance-app family plans; Trust & Will, Farewill and Epilogue publish none. The only benchmark is generic mobile subscription apps: above 10%/month poor, 6-10%/month average, under 6%/month good. 25%/yr is ~2.4%/month, INSIDE the 'good' band, which is the right place for an add-on bundled into an ongoing savings relationship rather than a standalone app fighting for attention every month. ASSUMPTION on a generic benchmark.
A70: Beneficiaries named per plan | B70: =CHOOSE($C$6,C70,D70,E70) | C70: 2.5 | D70: 3.5 | E70: 1.6 | F70: beneficiaries | G70: ADDED 2026-08-21. THE FIRST IS INCLUDED IN THE PLAN PRICE, so only the excess over 1.0 is charged - at 2.5 that is 1.5 chargeable. No platform publishes beneficiaries-per-will. What anchors it is who these customers are: South Asian migrant workers who remit ~80% of income to families at home, typically supporting a spouse, children and parents. Household sizes in the source countries run ~4.4 in India, ~4.5 in Bangladesh and ~6.8 in Pakistan, so naming 2-3 beneficiaries is conservative against the family they actually support. NOT THE SAME AS HOUSEHOLD SIZE - a beneficiary is a named, identity-verified person on a legal instrument, and people name fewer than they support. ASSUMPTION anchored on demographics.
A71: Family plan monthly churn, combined (derived) | B71: =1-(1-'Scenario Parameters'!$B$16)*(1-'Scenario Parameters'!$B$69)^(1/12) | F71: %/month | G71: TWO WAYS TO LOSE A SUBSCRIBER, COMBINED MULTIPLICATIVELY, NOT ADDED: they leave Aurumix entirely (the SIP churn on the left) or they stay and cancel the plan (the incremental rate on the right). Adding the two would double-count the overlap - a customer cannot both leave and separately cancel. DERIVED.
A72: B2B partners - Y1 | B72: =CHOOSE($C$6,C72,D72,E72) | C72: 0 | D72: 0 | E72: 0 | F72: partners | G72: RAISED 2026-08-21. Base now reaches 11 by Y7, against ~20 nameable Gulf candidates without a gold product - roughly a 55% win rate on the addressable partner market, which is aggressive but arguable for a category with one incumbent. Partner 1 signs in Y2, matching the M13 B2B go-live. THE CANDIDATE LIST IS THE JUSTIFICATION AND IT IS FINITE: e& money, Payit, Careem Pay, Al Ansari, LuLu Money, Rise, NOW Money, Wio, Liv, Mashreq Neo, Klip, PayBy, Jingle Pay, Thawani, BenefitPay, CWallet, Amanat and a handful of banks and exchange houses. Going much above this count means claiming partners that have not been named. ASSUMPTION on a sourced candidate set.
A73: B2B partners - Y2 | B73: =CHOOSE($C$6,C73,D73,E73) | C73: 1 | D73: 2 | E73: 1 | F73: partners | G73: RAISED 2026-08-21. Base now reaches 11 by Y7, against ~20 nameable Gulf candidates without a gold product - roughly a 55% win rate on the addressable partner market, which is aggressive but arguable for a category with one incumbent. Partner 1 signs in Y2, matching the M13 B2B go-live. THE CANDIDATE LIST IS THE JUSTIFICATION AND IT IS FINITE: e& money, Payit, Careem Pay, Al Ansari, LuLu Money, Rise, NOW Money, Wio, Liv, Mashreq Neo, Klip, PayBy, Jingle Pay, Thawani, BenefitPay, CWallet, Amanat and a handful of banks and exchange houses. Going much above this count means claiming partners that have not been named. ASSUMPTION on a sourced candidate set.
A74: B2B partners - Y3 | B74: =CHOOSE($C$6,C74,D74,E74) | C74: 3 | D74: 5 | E74: 1 | F74: partners | G74: RAISED 2026-08-21. Base now reaches 11 by Y7, against ~20 nameable Gulf candidates without a gold product - roughly a 55% win rate on the addressable partner market, which is aggressive but arguable for a category with one incumbent. Partner 1 signs in Y2, matching the M13 B2B go-live. THE CANDIDATE LIST IS THE JUSTIFICATION AND IT IS FINITE: e& money, Payit, Careem Pay, Al Ansari, LuLu Money, Rise, NOW Money, Wio, Liv, Mashreq Neo, Klip, PayBy, Jingle Pay, Thawani, BenefitPay, CWallet, Amanat and a handful of banks and exchange houses. Going much above this count means claiming partners that have not been named. ASSUMPTION on a sourced candidate set.
A75: B2B partners - Y4 | B75: =CHOOSE($C$6,C75,D75,E75) | C75: 5 | D75: 8 | E75: 2 | F75: partners | G75: RAISED 2026-08-21. Base now reaches 11 by Y7, against ~20 nameable Gulf candidates without a gold product - roughly a 55% win rate on the addressable partner market, which is aggressive but arguable for a category with one incumbent. Partner 1 signs in Y2, matching the M13 B2B go-live. THE CANDIDATE LIST IS THE JUSTIFICATION AND IT IS FINITE: e& money, Payit, Careem Pay, Al Ansari, LuLu Money, Rise, NOW Money, Wio, Liv, Mashreq Neo, Klip, PayBy, Jingle Pay, Thawani, BenefitPay, CWallet, Amanat and a handful of banks and exchange houses. Going much above this count means claiming partners that have not been named. ASSUMPTION on a sourced candidate set.
A76: B2B partners - Y5 | B76: =CHOOSE($C$6,C76,D76,E76) | C76: 7 | D76: 11 | E76: 3 | F76: partners | G76: RAISED 2026-08-21. Base now reaches 11 by Y7, against ~20 nameable Gulf candidates without a gold product - roughly a 55% win rate on the addressable partner market, which is aggressive but arguable for a category with one incumbent. Partner 1 signs in Y2, matching the M13 B2B go-live. THE CANDIDATE LIST IS THE JUSTIFICATION AND IT IS FINITE: e& money, Payit, Careem Pay, Al Ansari, LuLu Money, Rise, NOW Money, Wio, Liv, Mashreq Neo, Klip, PayBy, Jingle Pay, Thawani, BenefitPay, CWallet, Amanat and a handful of banks and exchange houses. Going much above this count means claiming partners that have not been named. ASSUMPTION on a sourced candidate set.
A77: B2B partners - Y6 | B77: =CHOOSE($C$6,C77,D77,E77) | C77: 9 | D77: 14 | E77: 4 | F77: partners | G77: RAISED 2026-08-21. Base now reaches 11 by Y7, against ~20 nameable Gulf candidates without a gold product - roughly a 55% win rate on the addressable partner market, which is aggressive but arguable for a category with one incumbent. Partner 1 signs in Y2, matching the M13 B2B go-live. THE CANDIDATE LIST IS THE JUSTIFICATION AND IT IS FINITE: e& money, Payit, Careem Pay, Al Ansari, LuLu Money, Rise, NOW Money, Wio, Liv, Mashreq Neo, Klip, PayBy, Jingle Pay, Thawani, BenefitPay, CWallet, Amanat and a handful of banks and exchange houses. Going much above this count means claiming partners that have not been named. ASSUMPTION on a sourced candidate set.
A78: B2B partners - Y7 | B78: =CHOOSE($C$6,C78,D78,E78) | C78: 11 | D78: 17 | E78: 5 | F78: partners | G78: RAISED 2026-08-21. Base now reaches 11 by Y7, against ~20 nameable Gulf candidates without a gold product - roughly a 55% win rate on the addressable partner market, which is aggressive but arguable for a category with one incumbent. Partner 1 signs in Y2, matching the M13 B2B go-live. THE CANDIDATE LIST IS THE JUSTIFICATION AND IT IS FINITE: e& money, Payit, Careem Pay, Al Ansari, LuLu Money, Rise, NOW Money, Wio, Liv, Mashreq Neo, Klip, PayBy, Jingle Pay, Thawani, BenefitPay, CWallet, Amanat and a handful of banks and exchange houses. Going much above this count means claiming partners that have not been named. ASSUMPTION on a sourced candidate set.
A79: B2B platform fee | B79: =CHOOSE($C$6,C79,D79,E79) | C79: 0.0075 | D79: 0.009 | E79: 0.005 | F79: % of partner AUM/yr | G79: RAISED 2026-08-21 from 0.625%, client instruction, and PROMOTED FROM A HARDCODED ASSUMPTION TO A SCENARIO PARAMETER at the same time - it drives the largest stream in the model and had no band at all, which is the wrong place to be certain. 0.75% IS THE TOP OF THE CITED 0.5-0.75% BAND, NOT THE MIDDLE OF IT. That has a consequence worth stating plainly: the aggressive case at 0.90% NOW SITS OUTSIDE THE EVIDENCE, because there is no headroom left inside the band. Conservative at 0.50% is the band's floor. So the downside is sourced and the upside is not - the reverse of how a scenario range should usually be built, and the direct result of putting the base at the ceiling. The fee is COUPLED TO THE PARTNER SET: a platform fee is what a partner will pay for gold infrastructure it does not have to build, and the more bargaining power the partner has the lower it goes. Indian precedent is the warning - the three incumbent providers work on a 3-6% SPREAD that compresses hard for large partners, so a partner the size of Botim would push back on 0.75% harder than a small wallet would. Raising the partner count and the fee together assumes neither effect bites. ASSUMPTION at the ceiling of a cited band.
A80: Average partner user base | B80: =CHOOSE($C$6,C80,D80,E80) | C80: 900000 | D80: 1400000 | E80: 500000 | F80: active users | G80: THE MIX, NOT THE BIGGEST. A realistic six-partner Gulf book is roughly one Botim-scale (1.7m ACTIVE fintech users, of 8.2-8.5m app users), two at e& money scale (~1.5m subscribers), and three small wallets at a few hundred thousand - which averages near 900k. USE ACTIVE USERS, NOT REGISTERED: Botim's own numbers separate 8.5m app users, 3m KYC'd and 1.7m active fintech users, and adopting the headline would overstate this by 5x. CITED for the two largest, ASSUMPTION for the tail.
A81: Partner users adopting gold (mature) | B81: =CHOOSE($C$6,C81,D81,E81) | C81: 0.06 | D81: 0.1 | E81: 0.03 | F81: % of partner users | G81: OBSERVED ANCHOR: O Gold reports 75,000 ACTIVE users against Botim's 1.7m active fintech users - 4.4% - and 775,000 who merely explored the feature. Base is set at 6%, ABOVE the observed 4.4%, because that figure is roughly six months after the gold feature launched and adoption should mature; 6% is a 1.4x maturation, not a doubling. THE 4.4% IS THE ONLY OBSERVED GOLD-ADOPTION RATE FOR A GULF WALLET THAT EXISTS. TRIANGULATED.
A82: AUM per adopting partner user | B82: =CHOOSE($C$6,C82,D82,E82) | C82: 350 | D82: 500 | E82: 220 | F82: USD | G82: DERIVED FROM BOTIM'S OWN DISCLOSURES AND CROSS-CHECKED AGAINST OUR OWN BOOK - two independent routes to nearly the same number, which is why this is the firmest input in the B2B block. Botim: AED 100m+ of gold across 128,000 trades since Aug 2025, against 75,000 active O Gold users, implies ~USD 363 per active user. Aurumix's own direct book runs at ~USD 302 of gold per customer. A partner's users are buying the same product with the same wallets. DERIVED.
A83: AUM per partner (derived) | B83: ='Scenario Parameters'!$B$80*'Scenario Parameters'!$B$81*'Scenario Parameters'!$B$82 | F83: USD | G83: NO LONGER A TYPED NUMBER. Was a flat USD 32m asserted as 'mature AUM per partner' with no derivation. Now users x adoption x AUM per adopting user, every term of which has an external anchor. THE POINT OF THE CHANGE: the only remaining argument is the PARTNER COUNT, which rests on a nameable candidate list and is the argument that can actually be won. DERIVED.
A85: GROUP F: REGIONS
A86: Parameter | B86: Active Value | C86: Base | D86: Aggressive | E86: Conservative | F86: Unit
A87: Average monthly ticket - UAE | B87: =CHOOSE($C$6,C87,D87,E87) | C87: 33.6 | D87: 41 | E87: 26.5 | F87: USD/month | G87: THE SIP AMOUNT - the recurring monthly gold contribution. SAVINGS-CAPACITY anchored, not remittance anchored, because remittance is a committed obligation rather than discretionary money; a recurring gold debit realistically captures 10-15% of monthly savings capacity. Anchors: Joyalukkas has PRICE-DISCOVERED AED 100 (USD 27) as the viable mass-market monthly instalment for this exact demographic, and Malabar sits at AED 200. The blend lands BELOW AMFI's USD 34 Indian retail SIP average (Rs 31,961 crore over 10.63 crore accounts, current at July 2026), which is the correct direction since AMFI reflects domestic urban investors with more discretionary income than a Gulf blue-collar book - it is an upper bound, not a proxy. UAE is the ceiling-weighted blend of the former Indian (USD 38) and other South Asian (USD 26) rows. Book-weighted average ~USD 31.45. TRIANGULATED.
A88: Average monthly ticket - Oman and Bahrain | B88: =CHOOSE($C$6,C88,D88,E88) | C88: 26 | D88: 32 | E88: 21 | F88: USD/month | G88: THE SIP AMOUNT - the recurring monthly gold contribution. SAVINGS-CAPACITY anchored, not remittance anchored, because remittance is a committed obligation rather than discretionary money; a recurring gold debit realistically captures 10-15% of monthly savings capacity. Anchors: Joyalukkas has PRICE-DISCOVERED AED 100 (USD 27) as the viable mass-market monthly instalment for this exact demographic, and Malabar sits at AED 200. The blend lands BELOW AMFI's USD 34 Indian retail SIP average (Rs 31,961 crore over 10.63 crore accounts, current at July 2026), which is the correct direction since AMFI reflects domestic urban investors with more discretionary income than a Gulf blue-collar book - it is an upper bound, not a proxy. UAE is the ceiling-weighted blend of the former Indian (USD 38) and other South Asian (USD 26) rows. Book-weighted average ~USD 31.45. TRIANGULATED.
A89: Average monthly ticket - India | B89: =CHOOSE($C$6,C89,D89,E89) | C89: 30 | D89: 36 | E89: 24 | F89: USD/month | G89: THE SIP AMOUNT - the recurring monthly gold contribution. SAVINGS-CAPACITY anchored, not remittance anchored, because remittance is a committed obligation rather than discretionary money; a recurring gold debit realistically captures 10-15% of monthly savings capacity. Anchors: Joyalukkas has PRICE-DISCOVERED AED 100 (USD 27) as the viable mass-market monthly instalment for this exact demographic, and Malabar sits at AED 200. The blend lands BELOW AMFI's USD 34 Indian retail SIP average (Rs 31,961 crore over 10.63 crore accounts, current at July 2026), which is the correct direction since AMFI reflects domestic urban investors with more discretionary income than a Gulf blue-collar book - it is an upper bound, not a proxy. UAE is the ceiling-weighted blend of the former Indian (USD 38) and other South Asian (USD 26) rows. Book-weighted average ~USD 31.45. TRIANGULATED.
A91: STRUCTURAL SWITCHES - the two that move revenue
A92: Switch | B92: Active (1/0) | C92: State | D92: ON value
A93: GROUP G: THE COST BASE
A94: Parameter | B94: Active Value | C94: Base | D94: Aggressive | E94: Conservative | F94: Unit
A95: Vault storage fee | B95: =CHOOSE($C$6,C95,D95,E95) | C95: 0.0012 | D95: 0.00026 | E95: 0.004 | F95: %/yr of metal held | G95: WHAT AURUMIX PAYS THE VAULT, not what it charges customers - decision 42 makes retail storage free. BASE 0.12% IS BULLIONVAULT'S PUBLISHED TARIFF, insurance included, minimum USD 4/month (bullionvault.com/help/tariff.html, retrieved 2026-08-26). Used as an UPPER BOUND on wholesale cost because it is a RETAIL price and therefore already carries BullionVault's own margin. AGGRESSIVE 0.026% is the DGCX Spot Gold vaulting tariff read literally - USD 0.10 per kilo per day at today's gold price. IT IS CARRIED ONLY AS THE OPTIMISTIC CASE AND SHOULD NOT BE THE BASE: that notice is dated 7 DECEMBER 2015, it is a DELIVERY-CYCLE tariff for taking metal off a futures contract (three free days per cycle) rather than a custody contract, and it is a FIXED DOLLAR-PER-KILO charge set when gold was about USD 34/g. The same physical rate was 0.107%/yr in 2015 and only reads as 0.026% now because the metal quadrupled. No vault reprices that slowly. CONSERVATIVE 0.40% is the low end of the range secondary sources quote for Dubai institutional storage. For reference the Royal Mint publishes 1% + VAT for bar storage. BENCHMARKED, NOT OBSERVED: no Dubai operator publishes an institutional custody tariff. Brink's runs the DGCX-approved Dubai vaults (Gold Souk, DAFZ, Almas Tower) and quotes privately. GET A QUOTE - it is the same conversation as naming the dealer.
A96: Vault minimum charge | B96: =CHOOSE($C$6,C96,D96,E96) | C96: 25 | D96: 5 | E96: 65 | F96: USD/day | G96: Professional vault contracts carry a minimum invoice, and it BITES WHILE THE BOOK IS SMALL - which is most of this horizon. BASE USD 25/day is the only MINIMUM published by any Dubai-approved vault operator (DGCX Spot Gold vaulting notice, 7 December 2015). AGGRESSIVE USD 5/day is nearer BullionVault's USD 4/MONTH. CONSERVATIVE USD 65/day is roughly USD 2,000/month, a plausible institutional floor. AT BASE THE MINIMUM BINDS UNTIL ABOUT YEAR 3, which is the point: early-year unit economics look worse than steady state because of minimum-commitment structures, and this is one of three in the cost base - the others are the KYC platform minimum and the card programme minimums. ASSUMPTION. Replace with the Brink's quote.
A97: VARA annual supervision fee | B97: =CHOOSE($C$6,C97,D97,E97) | C97: 400000 | D97: 200000 | E97: 600000 | F97: AED/yr | G97: VARA Schedule 2 - Supervision and Authorisation Fees, Virtual Assets and Related Activities Regulations 2023 (rulebooks.vara.ae, retrieved 2026-08-26). PUBLISHED AND EXACT: AED 200,000 per year for each of Category 1 VA Issuance, Broker-Dealer, Exchange and Custody; AED 80,000 for VA Transfer and Settlement. Payable IN ADVANCE of conducting the activity. VARA LICENSES ACTIVITIES, NOT THE TOKEN - you need each licence only if you actually perform that activity, so the ladder is a BUSINESS-MODEL question, not a risk band. BASE AED 400,000 = ISSUANCE + BROKER-DEALER. Issuance is mandatory for a gold-backed ARVA and is not negotiable. Broker-Dealer is added because Aurumix SELLS DIRECTLY TO RETAIL through its own app and agent network, and the definition catches 'soliciting or accepting orders for Virtual Assets and accepting fiat currency for such orders' - which is the SIP exactly. There is NO CARVE-OUT letting an issuer distribute its own token without it; the footnote checked on 2026-08-26 only requires issuers to comply with the Issuance Rulebook. AGGRESSIVE AED 200,000 = ISSUANCE ALONE, and it is a REAL STRATEGIC OPTION rather than optimism: mint and let a VARA-licensed broker-dealer handle distribution. Saves USD 54,459/yr of supervision and AED 600,000 of locked capital, at the cost of margin and control. CONSERVATIVE AED 600,000 adds CUSTODY, which bites only if Aurumix safekeeps client VAs - and only qualifies at all if each client's assets sit in SEPARATE WALLETS, so it turns on the wallet design. EXCHANGE IS DELIBERATELY EXCLUDED: no trading venue, no order matching. VA TRANSFER AND SETTLEMENT TOO: that definition targets moving CLIENTS' assets as a rail, not delivering your own issue to its buyer. VERIFIED AGAINST VARA'S PUBLIC REGISTER 2026-08-26, and the register settles it. Of 56 licensed VASPs, EXACTLY TWO hold Category 1 VA Issuance - Ctrl Alt Solutions DMCC and Tokinvest DMCC - and BOTH ALSO HOLD BROKER-DEALER SERVICES. Neither holds issuance alone. Issuance + Broker-Dealer is the only observed pattern in Dubai, which is why it is the Base. Both are tokenisation platforms rather than exchanges, so they are the closest comparators Aurumix has. THE SAMPLE IS TWO COMPANIES - it is the entire population of issuance licensees, not a survey, and it should be quoted as such. NEITHER HOLDS CUSTODY, and that is informative: on the register custody sits with specialists - Ceffu, BitGo, Hex Trust, Komainu, Bitpanda, Zand Bank - not with issuers. So Conservative is really the 'Aurumix builds its own custody instead of partnering' case, and it has no Dubai precedent. AGGRESSIVE HAS NO DUBAI PRECEDENT EITHER: no licensee holds issuance alone, so outsourcing distribution is a strategy nobody local has taken, not merely a cheaper option. Schedule 2 also lets VARA impose additional fees at its sole discretion.
A98: VARA licence application fee (one-off) | B98: =CHOOSE($C$6,C98,D98,E98) | C98: 150000 | D98: 100000 | E98: 200000 | F98: AED | G98: VARA Schedule 2, same source. AED 100,000 for one regulated VA Activity, payable at SUBMISSION - the application is not processed until it is received, so it is spent whether or not the licence is granted. Each additional activity adds a Licence Extension Fee of 50% OF THE LOWER application fee. Base 150,000 = Issuance 100,000 + 50% of Broker-Dealer's 100,000. Conservative 200,000 adds Custody at another 50,000. VARA PUBLISHES NO APPROVAL TIMELINE ANYWHERE - never give the client a date.
A99: DMCC company licence | B99: =CHOOSE($C$6,C99,D99,E99) | C99: 20265 | D99: 20265 | E99: 20265 | F99: AED/yr | G99: DMCC published Schedule of Charges (dmcc.ae, retrieved 2026-08-26): standard trading and service licence AED 20,265/yr. THE COST OF EXISTING AS A COMPANY, separate from and additional to the VARA licence, which is the cost of doing virtual asset business. You pay both. THE ESTABLISHMENT CARD (AED 1,825/yr) WAS REMOVED FROM THIS LINE ON 2026-08-26. It exists to sponsor residence visas, so its driver is headcount, not regulation - it belongs with visas and office, where a flexi-desk runs AED 16,000-19,000 and an employment residence permit about AED 2,972 each. DMCC states charges are subject to change without notice and publishes no effective date. NO SCENARIO VARIATION: it is a published tariff, not an estimate.
A100: DMCC incorporation (one-off) | B100: =CHOOSE($C$6,C100,D100,E100) | C100: 12035 | D100: 12035 | E100: 12035 | F100: AED | G100: DMCC published Schedule of Charges: application AED 1,015 + new company registration AED 9,000 + articles of association AED 2,020. One-off, Year 1.
A101: KYC and AML - per verification | B101: =CHOOSE($C$6,C101,D101,E101) | C101: 1.85 | D101: 1.35 | E101: 1.85 | F101: USD/check | G101: Sumsub published pricing (sumsub.com/pricing, retrieved 2026-08-26). COMPLIANCE TIER USD 1.85 IS THE RIGHT ONE, not the USD 1.35 Basic tier: Basic is sold for NON-REGULATED businesses and excludes AML screening, ongoing AML monitoring and proof-of-address, all three of which a VARA-licensed issuer needs. Aggressive carries 1.35 only to show what the cheaper tier would be worth. Sumsub charges for SUCCESSFUL verifications only.
A102: Paid-up capital - Category 1 VA Issuance | B102: =CHOOSE($C$6,C102,D102,E102) | C102: 1500000 | D102: 1500000 | E102: 1500000 | F102: AED | G102: VARA Virtual Asset Issuance Rulebook, ARVA Rules G.1 (retrieved 2026-08-26): Paid-Up Capital of at least THE HIGHER OF (a) AED 1,500,000 and (b) 2% of the 24-month average value of Reserve Assets, WHERE APPLICABLE. UNDER OPTION A (DIRECT OWNERSHIP) LIMB (b) DOES NOT APPLY, because Rule III.C.1 attaches Reserve Assets only to ARVAs which purport to maintain a stable value in respect of a Referenced Asset - and Aurumix's customers own specific allocated grams rather than a claim on a stabilised pool. There are no Reserve Assets to take 2% of. THE FLOOR IS NOT CONDITIONAL. Choosing Option A removes the ESCALATOR, not the AED 1,500,000. The rule reads at least the higher of, so with (b) inapplicable (a) governs. Flat in every scenario for that reason. LOCKED, NOT SPENT: balance sheet only, never the P&L.
A103: Paid-up capital - licensed activities | B103: =CHOOSE($C$6,C103,D103,E103) | C103: 600000 | D103: 0 | E103: 1200000 | F103: AED | G103: VARA Company Rulebook Part VI.B, per licensed VA Activity: Broker-Dealer without custody is the HIGHER of AED 600,000 or 25% of fixed annual overheads; Custody likewise. IT IS CUMULATIVE, NOT THE HIGHEST SINGLE TEST. Part VI.A requires the capital for EACH VA Activity for which the VASP is Licensed. Verified 2026-08-26. TRACKS THE ACTIVITY LADDER on the supervision-fee row: Aggressive 0 (issuance alone, distribution outsourced), Base 600,000 (Broker-Dealer), Conservative 1,200,000 (Broker-Dealer plus Custody). NOTHING TO DO WITH THE ARVA OPTION A / OPTION B CHOICE - this attaches to the LICENCE, not to the token design.
A104: Net liquid assets - months of opex | B104: =CHOOSE($C$6,C104,D104,E104) | C104: 1.2 | D104: 1.2 | E104: 1.2 | F104: x monthly opex | G104: VARA Company Rulebook Part VI.C: Net Liquid Assets at least 1.2 x monthly operating expenses. A CONTINUOUS LIQUIDITY TEST, not a one-off subscription, and it appears NOWHERE IN THE CORPUS - added 2026-08-26. NOT ADDITIVE TO PAID-UP CAPITAL: the same cash can satisfy both, so the two are shown side by side and never summed. It constrains the FORM the capital is held in, not the amount.
A105: Insurance - PI, D&O and crime | B105: =CHOOSE($C$6,C105,D105,E105) | C105: 45000 | D105: 20000 | E105: 90000 | F105: USD/yr | G105: MANDATORY, and the rulebook names the policies. VARA Company Rulebook Part VI.D requires professional indemnity, directors' and officers', and COMMERCIAL CRIME COVER FOR VIRTUAL ASSETS IN HOT WALLETS, all held with a regulated insurer, in an amount 'adequate to the size and complexity of the business'. VARA sets no minimum sum and judges adequacy at licensing. Verified 2026-08-26. BENCHMARKED, NOT OBSERVED - no insurer publishes VASP rates. Base USD 45,000 builds from UAE broker rate guides: PI for a regulated financial firm at AED 10m limit runs AED 60,000-155,000/yr and D&O at the same limit AED 55,000-145,000/yr; Base takes the BOTTOM of both ranges (about USD 31,300 combined) plus about USD 13,700 for crime cover. Aggressive assumes SME limits (PI AED 22,000, D&O AED 14,000); Conservative takes the top of the regulated ranges. THE CRIME ELEMENT IS THE UNPRICED ONE and it is the hardest to place: S&P reports hot and warm wallet crime capacity at roughly USD 75m per risk against USD 900m for cold specie, and a CFTC presentation calls hot-wallet cover 'extremely limited', layered in USD 1-5m blocks. Aurumix's hot-wallet exposure is operational treasury only, so a low limit should suffice - but the market is thin and the price is not published. THE PHYSICAL GOLD IS NOT INSURED HERE. Vault storage at 0.12% already includes insurance on the metal, so covering it again would double-count. FLAT ACROSS THE HORIZON, which is a simplification: PI and D&O scale with turnover, so this should be re-quoted as the book grows. GET A BROKER QUOTE.
A106: Audit and reserve attestation | B106: =CHOOSE($C$6,C106,D106,E106) | C106: 25000 | D106: 12000 | E106: 60000 | F106: USD/yr | G106: TWO SEPARATE ENGAGEMENTS, both mandatory under VARA Issuance Rulebook Rule III.D (verified 2026-08-26): a SIX-MONTHLY independent audit, and an ANNUAL independent audit of financial statements. A named independent auditor must be appointed and notified to VARA, and Senior Management must submit an ATTESTATION to the accuracy of each audit. OPTION A NARROWS THE SIX-MONTHLY ONE. Rule III.D.2.a covers (a) the number and value of ARVAs in circulation and (b) the composition and value of Reserve Assets 'IF APPLICABLE'. Under direct ownership there are no Reserve Assets, so limb (b) drops out and the engagement audits token supply against gold held rather than a reserve pool. NARROWER SCOPE SHOULD PRICE LOWER than the brief assumes. THE ATTESTATION FEE IS GENUINELY UNPRICED. No issuer, auditor or regulator has ever published one. Paxos uses Withum and now KPMG, Tether uses BDO Italia, Circle uses Deloitte - all disclose scope, standard and frequency, none disclose fee. The only figure found anywhere is a secondary estimate of USD 2-12m/yr for LARGE issuers using Big Four, which is not this business. BASE USD 25,000 = about USD 5,400 for the statutory audit (UAE market guides put a regulated SME at AED 12,000-25,000/yr) plus about USD 20,000 for two six-monthly engagements at USD 10,000 each. THE SECOND HALF IS A PLACEHOLDER, NOT A QUOTE. Get one from Bureau Veritas or an equivalent.
... A128: KYC and AML - monthly minimum | B128: =CHOOSE($C$6,C128,D128,E128) | C128: 299 | D128: 149 | E128: 299 | F128: USD/month | G128: Sumsub published minimum monthly commitment for the Compliance tier, same source. THE SECOND OF THREE MINIMUM-COMMITMENT STRUCTURES in this cost base - the vault minimum is the first, the card programme minimums are the third. It binds below about 162 verifications a month, which on this book is most of the first two years.
A130: Prepaid instead of credit | B130: =IF($C$130="Prepaid",1,0) | C130: Credit | D130: Prepaid | G130: ON (Prepaid) caps interchange at 1.00% and removes the credit stream entirely. 'NOT A PRODUCT CHOICE, IT IS THE BUSINESS MODEL.' Worth ~USD 2.3m of Y10 revenue on the ten-year run.
A131: Holders keep the card | B131: =IF($C$131="ON",1,0) | C131: ON | D131: ON | G131: DECIDED 2026-09-22 (decision 54): a customer who stops paying keeps the card and the credit line; only the collateral ladder, the customer or the lender can close them. So ON is the design, and the card streams do not decay with churn. OFF is kept as a sensitivity: recalculated 2026-09-24, it takes Y7 revenue from USD 4.49m to 3.88m (-13.7%) and streams 2, 4 and 5 together down 58%.
A132: Fabrication premium borne by | B132: =IF($C$132="Aurumix",1,0) | C132: Aurumix | D132: Aurumix | G132: DEFAULT AURUMIX, which REVERSES the 2026-08-21 client decision and does so deliberately. That review put the premium on the customer - grams delivered short by (1+premium), stream 1 keeping the full headline fee - which is standard for gold products where the quoted price includes the dealer spread. The model now shows procurement as a COST instead, because a cost the client can see is the point of the cost build, and because charging the customer for it is better presented as UPSIDE than baked into the base case. Switching back to Customer restores the 2026-08-21 treatment exactly: grams fall 1.50%, the COGS line goes to zero, and gross profit rises by the same amount. THE TWO SETTINGS ARE MUTUALLY EXCLUSIVE BY CONSTRUCTION, which is what stops the double-count fixed at 29f98e0 returning.
A133: Premium charged on gross inflow | B133: =IF($C$133="Gross",1,0) | C133: Net new | D133: Gross | G133: D30: the premium is paid on NET NEW grams. Gold returned by redemption is already a fabricated bar sitting in the float, and a bar that exists does not need making twice. Switching to Gross charges every gram, which is correct ONLY if redeemed metal is sold back to the dealer rather than recycled. GATED ON CORRECTION 30, WHICH IS UNDESIGNED - nobody has written down which way redeemed gold goes. Worth USD 165,755 of retained margin over the horizon, so the undesigned question has a price.

Sheet Model
A1: =Cover!$B$2
A2: Period # | B2: 1..29 | C2: 1 | D2: 2 | E2: 3 | F2: 4 | G2: 5 | H2: 6 | I2: 7 | J2: 8 | K2: 9 | L2: 10 | M2: 11 | N2: 12 | O2: 13 | P2: 14 | Q2: 15 | R2: 16 | S2: 17 | T2: 18 | U2: 19 | V2: 20 | W2: 21 | X2: 22 | Y2: 23 | Z2: 24 | AA2: 25 | AB2: 26 | AC2: 27 | AD2: 28 | AE2: 29
A3: Period | B3: - | C3: M1 | D3: M2 | E3: M3 | F3: M4 | G3: M5 | H3: M6 | I3: M7 | J3: M8 | K3: M9 | L3: M10 | M3: M11 | N3: M12 | O3: M13 | P3: M14 | Q3: M15 | R3: M16 | S3: M17 | T3: M18 | U3: M19 | V3: M20 | W3: M21 | X3: M22 | Y3: M23 | Z3: M24 | AA3: Y3 | AB3: Y4 | AC3: Y5 | AD3: Y6 | AE3: Y7
A4: Period type | B4: - | C4: Monthly | D4: Monthly | E4: Monthly | F4: Monthly | G4: Monthly | H4: Monthly | I4: Monthly | J4: Monthly | K4: Monthly | L4: Monthly | M4: Monthly | N4: Monthly | O4: Monthly | P4: Monthly | Q4: Monthly | R4: Monthly | S4: Monthly | T4: Monthly | U4: Monthly | V4: Monthly | W4: Monthly | X4: Monthly | Y4: Monthly | Z4: Monthly | AA4: Annual | AB4: Annual | AC4: Annual | AD4: Annual | AE4: Annual
A5: Model year | B5: 1..7 | C5: 1 | D5: 1 | E5: 1 | F5: 1 | G5: 1 | H5: 1 | I5: 1 | J5: 1 | K5: 1 | L5: 1 | M5: 1 | N5: 1 | O5: 2 | P5: 2 | Q5: 2 | R5: 2 | S5: 2 | T5: 2 | U5: 2 | V5: 2 | W5: 2 | X5: 2 | Y5: 2 | Z5: 2 | AA5: 3 | AB5: 4 | AC5: 5 | AD5: 6 | AE5: 7
A6: Calendar month | B6: 0 = annual | C6: 1 | D6: 2 | E6: 3 | F6: 4 | G6: 5 | H6: 6 | I6: 7 | J6: 8 | K6: 9 | L6: 10 | M6: 11 | N6: 12 | O6: 1 | P6: 2 | Q6: 3 | R6: 4 | S6: 5 | T6: 6 | U6: 7 | V6: 8 | W6: 9 | X6: 10 | Y6: 11 | Z6: 12 | AA6: 0 | AB6: 0 | AC6: 0 | AD6: 0 | AE6: 0
A7: Months in period | B7: months | C7: 1 | D7: 1 | E7: 1 | F7: 1 | G7: 1 | H7: 1 | I7: 1 | J7: 1 | K7: 1 | L7: 1 | M7: 1 | N7: 1 | O7: 1 | P7: 1 | Q7: 1 | R7: 1 | S7: 1 | T7: 1 | U7: 1 | V7: 1 | W7: 1 | X7: 1 | Y7: 1 | Z7: 1 | AA7: 12 | AB7: 12 | AC7: 12 | AD7: 12 | AE7: 12
A8: Financial-year end | B8: 1/0 | C8: 0 | D8: 0 | E8: 0 | F8: 0 | G8: 0 | H8: 0 | I8: 0 | J8: 0 | K8: 0 | L8: 0 | M8: 0 | N8: 1 | O8: 0 | P8: 0 | Q8: 0 | R8: 0 | S8: 0 | T8: 0 | U8: 0 | V8: 0 | W8: 0 | X8: 0 | Y8: 0 | Z8: 1 | AA8: 1 | AB8: 1 | AC8: 1 | AD8: 1 | AE8: 1
A10: SEASONALITY - normalised to EXACTLY 12.000 by construction
A11: Acquisition seasonality - normalised | B11: Jan..Dec | C11: =(1+(Assumptions!$F$61-1)*Assumptions!$B$148)*12/SUMPRODUCT(1+(Assumptions!$F$61:$Q$61-1)*Assumptions!$B$148) | D11: =(1+(Assumptions!$G$61-1)*Assumptions!$B$148)*12/SUMPRODUCT(1+(Assumptions!$F$61:$Q$61-1)*Assumptions!$B$148) | E11: =(1+(Assumptions!$H$61-1)*Assumptions!$B$148)*12/SUMPRODUCT(1+(Assumptions!$F$61:$Q$61-1)*Assumptions!$B$148) | F11: =(1+(Assumptions!$I$61-1)*Assumptions!$B$148)*12/SUMPRODUCT(1+(Assumptions!$F$61:$Q$61-1)*Assumptions!$B$148) | G11: =(1+(Assumptions!$J$61-1)*Assumptions!$B$148)*12/SUMPRODUCT(1+(Assumptions!$F$61:$Q$61-1)*Assumptions!$B$148) | H11: =(1+(Assumptions!$K$61-1)*Assumptions!$B$148)*12/SUMPRODUCT(1+(Assumptions!$F$61:$Q$61-1)*Assumptions!$B$148) | I11: =(1+(Assumptions!$L$61-1)*Assumptions!$B$148)*12/SUMPRODUCT(1+(Assumptions!$F$61:$Q$61-1)*Assumptions!$B$148) | J11: =(1+(Assumptions!$M$61-1)*Assumptions!$B$148)*12/SUMPRODUCT(1+(Assumptions!$F$61:$Q$61-1)*Assumptions!$B$148) | K11: =(1+(Assumptions!$N$61-1)*Assumptions!$B$148)*12/SUMPRODUCT(1+(Assumptions!$F$61:$Q$61-1)*Assumptions!$B$148) | L11: =(1+(Assumptions!$O$61-1)*Assumptions!$B$148)*12/SUMPRODUCT(1+(Assumptions!$F$61:$Q$61-1)*Assumptions!$B$148) | M11: =(1+(Assumptions!$P$61-1)*Assumptions!$B$148)*12/SUMPRODUCT(1+(Assumptions!$F$61:$Q$61-1)*Assumptions!$B$148) | N11: =(1+(Assumptions!$Q$61-1)*Assumptions!$B$148)*12/SUMPRODUCT(1+(Assumptions!$F$61:$Q$61-1)*Assumptions!$B$148)
A12: Card spend seasonality - normalised | B12: Jan..Dec | C12: =(1+(Assumptions!$F$62-1)*Assumptions!$B$148)*12/SUMPRODUCT(1+(Assumptions!$F$62:$Q$62-1)*Assumptions!$B$148) | D12: =(1+(Assumptions!$G$62-1)*Assumptions!$B$148)*12/SUMPRODUCT(1+(Assumptions!$F$62:$Q$62-1)*Assumptions!$B$148) | E12: =(1+(Assumptions!$H$62-1)*Assumptions!$B$148)*12/SUMPRODUCT(1+(Assumptions!$F$62:$Q$62-1)*Assumptions!$B$148) | F12: =(1+(Assumptions!$I$62-1)*Assumptions!$B$148)*12/SUMPRODUCT(1+(Assumptions!$F$62:$Q$62-1)*Assumptions!$B$148) | G12: =(1+(Assumptions!$J$62-1)*Assumptions!$B$148)*12/SUMPRODUCT(1+(Assumptions!$F$62:$Q$62-1)*Assumptions!$B$148) | H12: =(1+(Assumptions!$K$62-1)*Assumptions!$B$148)*12/SUMPRODUCT(1+(Assumptions!$F$62:$Q$62-1)*Assumptions!$B$148) | I12: =(1+(Assumptions!$L$62-1)*Assumptions!$B$148)*12/SUMPRODUCT(1+(Assumptions!$F$62:$Q$62-1)*Assumptions!$B$148) | J12: =(1+(Assumptions!$M$62-1)*Assumptions!$B$148)*12/SUMPRODUCT(1+(Assumptions!$F$62:$Q$62-1)*Assumptions!$B$148) | K12: =(1+(Assumptions!$N$62-1)*Assumptions!$B$148)*12/SUMPRODUCT(1+(Assumptions!$F$62:$Q$62-1)*Assumptions!$B$148) | L12: =(1+(Assumptions!$O$62-1)*Assumptions!$B$148)*12/SUMPRODUCT(1+(Assumptions!$F$62:$Q$62-1)*Assumptions!$B$148) | M12: =(1+(Assumptions!$P$62-1)*Assumptions!$B$148)*12/SUMPRODUCT(1+(Assumptions!$F$62:$Q$62-1)*Assumptions!$B$148) | N12: =(1+(Assumptions!$Q$62-1)*Assumptions!$B$148)*12/SUMPRODUCT(1+(Assumptions!$F$62:$Q$62-1)*Assumptions!$B$148)
A13: Foreign-spend share - rescaled to the mean | B13: Jan..Dec | C13: =Assumptions!$F$63/AVERAGE(Assumptions!$F$63:$Q$63)*Assumptions!$B$160 | D13: =Assumptions!$G$63/AVERAGE(Assumptions!$F$63:$Q$63)*Assumptions!$B$160 | E13: =Assumptions!$H$63/AVERAGE(Assumptions!$F$63:$Q$63)*Assumptions!$B$160 | F13: =Assumptions!$I$63/AVERAGE(Assumptions!$F$63:$Q$63)*Assumptions!$B$160 | G13: =Assumptions!$J$63/AVERAGE(Assumptions!$F$63:$Q$63)*Assumptions!$B$160 | H13: =Assumptions!$K$63/AVERAGE(Assumptions!$F$63:$Q$63)*Assumptions!$B$160 | I13: =Assumptions!$L$63/AVERAGE(Assumptions!$F$63:$Q$63)*Assumptions!$B$160 | J13: =Assumptions!$M$63/AVERAGE(Assumptions!$F$63:$Q$63)*Assumptions!$B$160 | K13: =Assumptions!$N$63/AVERAGE(Assumptions!$F$63:$Q$63)*Assumptions!$B$160 | L13: =Assumptions!$O$63/AVERAGE(Assumptions!$F$63:$Q$63)*Assumptions!$B$160 | M13: =Assumptions!$P$63/AVERAGE(Assumptions!$F$63:$Q$63)*Assumptions!$B$160 | N13: =Assumptions!$Q$63/AVERAGE(Assumptions!$F$63:$Q$63)*Assumptions!$B$160
A14: Seasonality sum check (must be exactly 12.000) | B14: acq | spend | C14: =SUM($C$11:$N$11) | D14: =SUM($C$12:$N$12)
A15: Acquisition seasonality applied | B15: multiplier | C15: =IF(C7=1,INDEX($C$11:$N$11,1,C6),1) | D15: =IF(D7=1,INDEX($C$11:$N$11,1,D6),1) | E15: =IF(E7=1,INDEX($C$11:$N$11,1,E6),1) | F15: =IF(F7=1,INDEX($C$11:$N$11,1,F6),1) | G15: =IF(G7=1,INDEX($C$11:$N$11,1,G6),1) | H15: =IF(H7=1,INDEX($C$11:$N$11,1,H6),1) | I15: =IF(I7=1,INDEX($C$11:$N$11,1,I6),1) | J15: =IF(J7=1,INDEX($C$11:$N$11,1,J6),1) | ... AE15: =IF(AE7=1,INDEX($C$11:$N$11,1,AE6),1)
A16: Card spend seasonality applied | B16: multiplier | C16: =IF(C7=1,INDEX($C$12:$N$12,1,C6),1) | D16: =IF(D7=1,INDEX($C$12:$N$12,1,D6),1) | E16: =IF(E7=1,INDEX($C$12:$N$12,1,E6),1) | F16: =IF(F7=1,INDEX($C$12:$N$12,1,F6),1) | G16: =IF(G7=1,INDEX($C$12:$N$12,1,G6),1) | H16: =IF(H7=1,INDEX($C$12:$N$12,1,H6),1) | I16: =IF(I7=1,INDEX($C$12:$N$12,1,I6),1) | J16: =IF(J7=1,INDEX($C$12:$N$12,1,J6),1) | ... AE16: =IF(AE7=1,INDEX($C$12:$N$12,1,AE6),1)
A17: Foreign-spend share applied | B17: % | C17: =IF(C7=1,INDEX($C$13:$N$13,1,C6),AVERAGE($C$13:$N$13)) | D17: =IF(D7=1,INDEX($C$13:$N$13,1,D6),AVERAGE($C$13:$N$13)) | E17: =IF(E7=1,INDEX($C$13:$N$13,1,E6),AVERAGE($C$13:$N$13)) | F17: =IF(F7=1,INDEX($C$13:$N$13,1,F6),AVERAGE($C$13:$N$13)) | G17: =IF(G7=1,INDEX($C$13:$N$13,1,G6),AVERAGE($C$13:$N$13)) | H17: =IF(H7=1,INDEX($C$13:$N$13,1,H6),AVERAGE($C$13:$N$13)) | I17: =IF(I7=1,INDEX($C$13:$N$13,1,I6),AVERAGE($C$13:$N$13)) | J17: =IF(J7=1,INDEX($C$13:$N$13,1,J6),AVERAGE($C$13:$N$13)) | ... AE17: =IF(AE7=1,INDEX($C$13:$N$13,1,AE6),AVERAGE($C$13:$N$13))
A19: ACQUISITION - all channels, then split across regions
A20: Gold price (this period) | B20: USD/g | C20: =Assumptions!$B$6*(1+Assumptions!$B$131)^(C5-1) | D20: =Assumptions!$B$6*(1+Assumptions!$B$131)^(D5-1) | E20: =Assumptions!$B$6*(1+Assumptions!$B$131)^(E5-1) | F20: =Assumptions!$B$6*(1+Assumptions!$B$131)^(F5-1) | G20: =Assumptions!$B$6*(1+Assumptions!$B$131)^(G5-1) | H20: =Assumptions!$B$6*(1+Assumptions!$B$131)^(H5-1) | I20: =Assumptions!$B$6*(1+Assumptions!$B$131)^(I5-1) | J20: =Assumptions!$B$6*(1+Assumptions!$B$131)^(J5-1) | ... AE20: =Assumptions!$B$6*(1+Assumptions!$B$131)^(AE5-1)
A21: RISING GOLD CUTS BOTH WAYS AND THE MODEL CAPTURES BOTH. Metal already held appreciates, but a fixed USD contribution BUYS FEWER GRAMS each year - so AUM does NOT simply compound at the headline rate. Only the collateral-linked streams move with this row (card limit, and lending through it); the entry fee is a percentage of a USD contribution and is untouched by the gold price.
A22: REVENUE - the customer engine and the six streams, by region
A24: REGION: UAE
A25: Marketing CAC this period (ramping Y1 to Y7) | B25: USD/customer | C25: =Assumptions!$B$136+(Assumptions!$B$139-Assumptions!$B$136)*(C5-1)/6 | D25: =Assumptions!$B$136+(Assumptions!$B$139-Assumptions!$B$136)*(D5-1)/6 | E25: =Assumptions!$B$136+(Assumptions!$B$139-Assumptions!$B$136)*(E5-1)/6 | F25: =Assumptions!$B$136+(Assumptions!$B$139-Assumptions!$B$136)*(F5-1)/6 | G25: =Assumptions!$B$136+(Assumptions!$B$139-Assumptions!$B$136)*(G5-1)/6 | H25: =Assumptions!$B$136+(Assumptions!$B$139-Assumptions!$B$136)*(H5-1)/6 | I25: =Assumptions!$B$136+(Assumptions!$B$139-Assumptions!$B$136)*(I5-1)/6 | J25: =Assumptions!$B$136+(Assumptions!$B$139-Assumptions!$B$136)*(J5-1)/6 | ... AE25: =Assumptions!$B$136+(Assumptions!$B$139-Assumptions!$B$136)*(AE5-1)/6
A26: Direct-driven (this market's budget at its own CAC) | B26: accounts | C26: =INDEX(Assumptions!$B$114:$B$120,C5)*Assumptions!$B$142/12*C7/C25*(1+Assumptions!$B$147)*1 | D26: =INDEX(Assumptions!$B$114:$B$120,D5)*Assumptions!$B$142/12*D7/D25*(1+Assumptions!$B$147)*1 | E26: =INDEX(Assumptions!$B$114:$B$120,E5)*Assumptions!$B$142/12*E7/E25*(1+Assumptions!$B$147)*1 | F26: =INDEX(Assumptions!$B$114:$B$120,F5)*Assumptions!$B$142/12*F7/F25*(1+Assumptions!$B$147)*1 | G26: =INDEX(Assumptions!$B$114:$B$120,G5)*Assumptions!$B$142/12*G7/G25*(1+Assumptions!$B$147)*1 | H26: =INDEX(Assumptions!$B$114:$B$120,H5)*Assumptions!$B$142/12*H7/H25*(1+Assumptions!$B$147)*1 | I26: =INDEX(Assumptions!$B$114:$B$120,I5)*Assumptions!$B$142/12*I7/I25*(1+Assumptions!$B$147)*1 | J26: =INDEX(Assumptions!$B$114:$B$120,J5)*Assumptions!$B$142/12*J7/J25*(1+Assumptions!$B$147)*1 | ... AE26: =INDEX(Assumptions!$B$114:$B$120,AE5)*Assumptions!$B$142/12*AE7/AE25*(1+Assumptions!$B$147)*1
A27: Referral-driven (from this market's own base) | B27: accounts | C27: 0 | D27: =IF(D2>=Assumptions!$B$55,C32*Assumptions!$B$145/12*Assumptions!$B$146*D7,0) | E27: =IF(E2>=Assumptions!$B$55,D32*Assumptions!$B$145/12*Assumptions!$B$146*E7,0) | F27: =IF(F2>=Assumptions!$B$55,E32*Assumptions!$B$145/12*Assumptions!$B$146*F7,0) | G27: =IF(G2>=Assumptions!$B$55,F32*Assumptions!$B$145/12*Assumptions!$B$146*G7,0) | H27: =IF(H2>=Assumptions!$B$55,G32*Assumptions!$B$145/12*Assumptions!$B$146*H7,0) | I27: =IF(I2>=Assumptions!$B$55,H32*Assumptions!$B$145/12*Assumptions!$B$146*I7,0) | J27: =IF(J2>=Assumptions!$B$55,I32*Assumptions!$B$145/12*Assumptions!$B$146*J7,0) | K27: =IF(K2>=Assumptions!$B$55,J32*Assumptions!$B$145/12*Assumptions!$B$146*K7,0) | ... AE27: =IF(AE2>=Assumptions!$B$55,AD32*Assumptions!$B$145/12*Assumptions!$B$146*AE7,0)
A28: Agent-driven (this market's own agents) | B28: accounts | C28: =INDEX(Assumptions!$B$93:$B$99,C5)*Assumptions!$B$135*INDEX(Assumptions!$B$121:$B$127,C5)*C7*1 | D28: =INDEX(Assumptions!$B$93:$B$99,D5)*Assumptions!$B$135*INDEX(Assumptions!$B$121:$B$127,D5)*D7*1 | E28: =INDEX(Assumptions!$B$93:$B$99,E5)*Assumptions!$B$135*INDEX(Assumptions!$B$121:$B$127,E5)*E7*1 | F28: =INDEX(Assumptions!$B$93:$B$99,F5)*Assumptions!$B$135*INDEX(Assumptions!$B$121:$B$127,F5)*F7*1 | G28: =INDEX(Assumptions!$B$93:$B$99,G5)*Assumptions!$B$135*INDEX(Assumptions!$B$121:$B$127,G5)*G7*1 | H28: =INDEX(Assumptions!$B$93:$B$99,H5)*Assumptions!$B$135*INDEX(Assumptions!$B$121:$B$127,H5)*H7*1 | I28: =INDEX(Assumptions!$B$93:$B$99,I5)*Assumptions!$B$135*INDEX(Assumptions!$B$121:$B$127,I5)*I7*1 | J28: =INDEX(Assumptions!$B$93:$B$99,J5)*Assumptions!$B$135*INDEX(Assumptions!$B$121:$B$127,J5)*J7*1 | ... AE28: =INDEX(Assumptions!$B$93:$B$99,AE5)*Assumptions!$B$135*INDEX(Assumptions!$B$121:$B$127,AE5)*AE7*1
A29: Raw demand | B29: accounts | C29: =C26+C27+C28 | D29: =D26+D27+D28 | E29: =E26+E27+E28 | F29: =F26+F27+F28 | G29: =G26+G27+G28 | H29: =H26+H27+H28 | I29: =I26+I27+I28 | J29: =J26+J27+J28 | ... AE29: =AE26+AE27+AE28
A30: Saturation (this region's own headroom) | B30: x | C30: 1 | D30: =MAX(0,1-C35/Assumptions!$B$84) | E30: =MAX(0,1-D35/Assumptions!$B$84) | F30: =MAX(0,1-E35/Assumptions!$B$84) | G30: =MAX(0,1-F35/Assumptions!$B$84) | H30: =MAX(0,1-G35/Assumptions!$B$84) | I30: =MAX(0,1-H35/Assumptions!$B$84) | J30: =MAX(0,1-I35/Assumptions!$B$84) | K30: =MAX(0,1-J35/Assumptions!$B$84) | ... AE30: =MAX(0,1-AD35/Assumptions!$B$84)
A31: New customers | B31: accounts | C31: =C29*C30*C15 | D31: =D29*D30*D15 | E31: =E29*E30*E15 | F31: =F29*F30*F15 | G31: =G29*G30*G15 | H31: =H29*H30*H15 | I31: =I29*I30*I15 | J31: =J29*J30*J15 | ... AE31: =AE29*AE30*AE15
A32: Paying customers | B32: accounts | C32: =C31*(1-Assumptions!$B$134)^(C7/2) | D32: =C32*(1-Assumptions!$B$134)^D7+D31*(1-Assumptions!$B$134)^(D7/2) | E32: =D32*(1-Assumptions!$B$134)^E7+E31*(1-Assumptions!$B$134)^(E7/2) | F32: =E32*(1-Assumptions!$B$134)^F7+F31*(1-Assumptions!$B$134)^(F7/2) | G32: =F32*(1-Assumptions!$B$134)^G7+G31*(1-Assumptions!$B$134)^(G7/2) | H32: =G32*(1-Assumptions!$B$134)^H7+H31*(1-Assumptions!$B$134)^(H7/2) | I32: =H32*(1-Assumptions!$B$134)^I7+I31*(1-Assumptions!$B$134)^(I7/2) | J32: =I32*(1-Assumptions!$B$134)^J7+J31*(1-Assumptions!$B$134)^(J7/2) | K32: =J32*(1-Assumptions!$B$134)^K7+K31*(1-Assumptions!$B$134)^(K7/2) | ... AE32: =AD32*(1-Assumptions!$B$134)^AE7+AE31*(1-Assumptions!$B$134)^(AE7/2)
A33: Churned this period | B33: accounts | C33: =C31-C32 | D33: =C32+D31-D32 | E33: =D32+E31-E32 | F33: =E32+F31-F32 | G33: =F32+G31-G32 | H33: =G32+H31-H32 | I33: =H32+I31-I32 | J33: =I32+J31-J32 | K33: =J32+K31-K32 | ... AE33: =AD32+AE31-AE32
A34: Holders (stopped paying, still hold gold) | B34: accounts | C34: =C33 | D34: =C34+D33 | E34: =D34+E33 | F34: =E34+F33 | G34: =F34+G33 | H34: =G34+H33 | I34: =H34+I33 | J34: =I34+J33 | K34: =J34+K33 | ... AE34: =AD34+AE33
A35: Cumulative ever acquired | B35: accounts | C35: =C31 | D35: =C35+D31 | E35: =D35+E31 | F35: =E35+F31 | G35: =F35+G31 | H35: =G35+H31 | I35: =H35+I31 | J35: =I35+J31 | K35: =J35+K31 | ... AE35: =AD35+AE31
A36: SIP contributions | B36: USD | C36: =IF(C2>=Assumptions!$B$47,C32*Assumptions!$B$190*C7,0) | D36: =IF(D2>=Assumptions!$B$47,D32*Assumptions!$B$190*D7,0) | E36: =IF(E2>=Assumptions!$B$47,E32*Assumptions!$B$190*E7,0) | F36: =IF(F2>=Assumptions!$B$47,F32*Assumptions!$B$190*F7,0) | G36: =IF(G2>=Assumptions!$B$47,G32*Assumptions!$B$190*G7,0) | H36: =IF(H2>=Assumptions!$B$47,H32*Assumptions!$B$190*H7,0) | I36: =IF(I2>=Assumptions!$B$47,I32*Assumptions!$B$190*I7,0) | J36: =IF(J2>=Assumptions!$B$47,J32*Assumptions!$B$190*J7,0) | ... AE36: =IF(AE2>=Assumptions!$B$47,AE32*Assumptions!$B$190*AE7,0)
A37: Spot purchase volume | B37: USD | C37: =IF(C2>=Assumptions!$B$48,C32*Assumptions!$B$35*Assumptions!$B$154*Assumptions!$B$156*Assumptions!$B$32*Assumptions!$B$155/12*C7,0) | D37: =IF(D2>=Assumptions!$B$48,D32*Assumptions!$B$35*Assumptions!$B$154*Assumptions!$B$156*Assumptions!$B$32*Assumptions!$B$155/12*D7,0) | E37: =IF(E2>=Assumptions!$B$48,E32*Assumptions!$B$35*Assumptions!$B$154*Assumptions!$B$156*Assumptions!$B$32*Assumptions!$B$155/12*E7,0) | F37: =IF(F2>=Assumptions!$B$48,F32*Assumptions!$B$35*Assumptions!$B$154*Assumptions!$B$156*Assumptions!$B$32*Assumptions!$B$155/12*F7,0) | G37: =IF(G2>=Assumptions!$B$48,G32*Assumptions!$B$35*Assumptions!$B$154*Assumptions!$B$156*Assumptions!$B$32*Assumptions!$B$155/12*G7,0) | H37: =IF(H2>=Assumptions!$B$48,H32*Assumptions!$B$35*Assumptions!$B$154*Assumptions!$B$156*Assumptions!$B$32*Assumptions!$B$155/12*H7,0) | I37: =IF(I2>=Assumptions!$B$48,I32*Assumptions!$B$35*Assumptions!$B$154*Assumptions!$B$156*Assumptions!$B$32*Assumptions!$B$155/12*I7,0) | J37: =IF(J2>=Assumptions!$B$48,J32*Assumptions!$B$35*Assumptions!$B$154*Assumptions!$B$156*Assumptions!$B$32*Assumptions!$B$155/12*J7,0) | ... AE37: =IF(AE2>=Assumptions!$B$48,AE32*Assumptions!$B$35*Assumptions!$B$154*Assumptions!$B$156*Assumptions!$B$32*Assumptions!$B$155/12*AE7,0)
A38: Grams purchased | B38: grams | C38: =(C36+C37)*(1-Assumptions!$B$8)/C20/(1+Assumptions!$B$9*(1-Assumptions!$B$229)) | D38: =(D36+D37)*(1-Assumptions!$B$8)/D20/(1+Assumptions!$B$9*(1-Assumptions!$B$229)) | E38: =(E36+E37)*(1-Assumptions!$B$8)/E20/(1+Assumptions!$B$9*(1-Assumptions!$B$229)) | F38: =(F36+F37)*(1-Assumptions!$B$8)/F20/(1+Assumptions!$B$9*(1-Assumptions!$B$229)) | G38: =(G36+G37)*(1-Assumptions!$B$8)/G20/(1+Assumptions!$B$9*(1-Assumptions!$B$229)) | H38: =(H36+H37)*(1-Assumptions!$B$8)/H20/(1+Assumptions!$B$9*(1-Assumptions!$B$229)) | I38: =(I36+I37)*(1-Assumptions!$B$8)/I20/(1+Assumptions!$B$9*(1-Assumptions!$B$229)) | J38: =(J36+J37)*(1-Assumptions!$B$8)/J20/(1+Assumptions!$B$9*(1-Assumptions!$B$229)) | ... AE38: =(AE36+AE37)*(1-Assumptions!$B$8)/AE20/(1+Assumptions!$B$9*(1-Assumptions!$B$229))
A39: Collateral-eligible AUM decay rate (holder-weighted) | B39: %/period | C39: =(Assumptions!$B$151+Assumptions!$B$152*IF(C32+C34=0,1,(C32+C34*Assumptions!$B$153)/(C32+C34)))*C7/12 | D39: =(Assumptions!$B$151+Assumptions!$B$152*IF(D32+D34=0,1,(D32+D34*Assumptions!$B$153)/(D32+D34)))*D7/12 | E39: =(Assumptions!$B$151+Assumptions!$B$152*IF(E32+E34=0,1,(E32+E34*Assumptions!$B$153)/(E32+E34)))*E7/12 | F39: =(Assumptions!$B$151+Assumptions!$B$152*IF(F32+F34=0,1,(F32+F34*Assumptions!$B$153)/(F32+F34)))*F7/12 | G39: =(Assumptions!$B$151+Assumptions!$B$152*IF(G32+G34=0,1,(G32+G34*Assumptions!$B$153)/(G32+G34)))*G7/12 | H39: =(Assumptions!$B$151+Assumptions!$B$152*IF(H32+H34=0,1,(H32+H34*Assumptions!$B$153)/(H32+H34)))*H7/12 | I39: =(Assumptions!$B$151+Assumptions!$B$152*IF(I32+I34=0,1,(I32+I34*Assumptions!$B$153)/(I32+I34)))*I7/12 | J39: =(Assumptions!$B$151+Assumptions!$B$152*IF(J32+J34=0,1,(J32+J34*Assumptions!$B$153)/(J32+J34)))*J7/12 | ... AE39: =(Assumptions!$B$151+Assumptions!$B$152*IF(AE32+AE34=0,1,(AE32+AE34*Assumptions!$B$153)/(AE32+AE34)))*AE7/12
A40: Redemption-only decay rate (metal actually leaving) | B40: %/period | C40: =Assumptions!$B$152*IF(C32+C34=0,1,(C32+C34*Assumptions!$B$153)/(C32+C34))*C7/12 | D40: =Assumptions!$B$152*IF(D32+D34=0,1,(D32+D34*Assumptions!$B$153)/(D32+D34))*D7/12 | E40: =Assumptions!$B$152*IF(E32+E34=0,1,(E32+E34*Assumptions!$B$153)/(E32+E34))*E7/12 | F40: =Assumptions!$B$152*IF(F32+F34=0,1,(F32+F34*Assumptions!$B$153)/(F32+F34))*F7/12 | G40: =Assumptions!$B$152*IF(G32+G34=0,1,(G32+G34*Assumptions!$B$153)/(G32+G34))*G7/12 | H40: =Assumptions!$B$152*IF(H32+H34=0,1,(H32+H34*Assumptions!$B$153)/(H32+H34))*H7/12 | I40: =Assumptions!$B$152*IF(I32+I34=0,1,(I32+I34*Assumptions!$B$153)/(I32+I34))*I7/12 | J40: =Assumptions!$B$152*IF(J32+J34=0,1,(J32+J34*Assumptions!$B$153)/(J32+J34))*J7/12 | ... AE40: =Assumptions!$B$152*IF(AE32+AE34=0,1,(AE32+AE34*Assumptions!$B$153)/(AE32+AE34))*AE7/12
A41: Grams held (collateral-eligible) | B41: grams | C41: =C38 | D41: =C41*(1-D39)+D38 | E41: =D41*(1-E39)+E38 | F41: =E41*(1-F39)+F38 | G41: =F41*(1-G39)+G38 | H41: =G41*(1-H39)+H38 | I41: =H41*(1-I39)+I38 | J41: =I41*(1-J39)+J38 | K41: =J41*(1-K39)+K38 | ... AE41: =AD41*(1-AE39)+AE38
A42: Grams under custody (vaulted, incl. self-custodied) | B42: grams | C42: =C38 | D42: =C42*(1-D40)+D38 | E42: =D42*(1-E40)+E38 | F42: =E42*(1-F40)+F38 | G42: =F42*(1-G40)+G38 | H42: =G42*(1-H40)+H38 | I42: =H42*(1-I40)+I38 | J42: =I42*(1-J40)+J38 | K42: =J42*(1-K40)+K38 | ... AE42: =AD42*(1-AE40)+AE38
A43: AUM | B43: USD | C43: =C41*C20 | D43: =D41*D20 | E43: =E41*E20 | F43: =F41*F20 | G43: =G41*G20 | H43: =H41*H20 | I43: =I41*I20 | J43: =J41*J20 | ... AE43: =AE41*AE20
A44: Card-eligible base | B44: accounts | C44: =C32+C34*Assumptions!$B$228 | D44: =D32+D34*Assumptions!$B$228 | E44: =E32+E34*Assumptions!$B$228 | F44: =F32+F34*Assumptions!$B$228 | G44: =G32+G34*Assumptions!$B$228 | H44: =H32+H34*Assumptions!$B$228 | I44: =I32+I34*Assumptions!$B$228 | J44: =J32+J34*Assumptions!$B$228 | ... AE44: =AE32+AE34*Assumptions!$B$228
A45: Reaches an ICS benefit tier (memo - drives discounts, not access) | B45: accounts | C45: =IF(C7>1,C44*Assumptions!$B$149,IF(C2>Assumptions!$B$150,INDEX($C$44:$AE$44,1,C2-Assumptions!$B$150)*Assumptions!$B$149,0)) | D45: =IF(D7>1,D44*Assumptions!$B$149,IF(D2>Assumptions!$B$150,INDEX($C$44:$AE$44,1,D2-Assumptions!$B$150)*Assumptions!$B$149,0)) | E45: =IF(E7>1,E44*Assumptions!$B$149,IF(E2>Assumptions!$B$150,INDEX($C$44:$AE$44,1,E2-Assumptions!$B$150)*Assumptions!$B$149,0)) | F45: =IF(F7>1,F44*Assumptions!$B$149,IF(F2>Assumptions!$B$150,INDEX($C$44:$AE$44,1,F2-Assumptions!$B$150)*Assumptions!$B$149,0)) | G45: =IF(G7>1,G44*Assumptions!$B$149,IF(G2>Assumptions!$B$150,INDEX($C$44:$AE$44,1,G2-Assumptions!$B$150)*Assumptions!$B$149,0)) | H45: =IF(H7>1,H44*Assumptions!$B$149,IF(H2>Assumptions!$B$150,INDEX($C$44:$AE$44,1,H2-Assumptions!$B$150)*Assumptions!$B$149,0)) | I45: =IF(I7>1,I44*Assumptions!$B$149,IF(I2>Assumptions!$B$150,INDEX($C$44:$AE$44,1,I2-Assumptions!$B$150)*Assumptions!$B$149,0)) | J45: =IF(J7>1,J44*Assumptions!$B$149,IF(J2>Assumptions!$B$150,INDEX($C$44:$AE$44,1,J2-Assumptions!$B$150)*Assumptions!$B$149,0)) | ... AE45: =IF(AE7>1,AE44*Assumptions!$B$149,IF(AE2>Assumptions!$B$150,INDEX($C$44:$AE$44,1,AE2-Assumptions!$B$150)*Assumptions!$B$149,0))
A46: Active cards | B46: cards | C46: =IF(C2>=Assumptions!$B$51,C44*Assumptions!$B$158,0) | D46: =IF(D2>=Assumptions!$B$51,D44*Assumptions!$B$158,0) | E46: =IF(E2>=Assumptions!$B$51,E44*Assumptions!$B$158,0) | F46: =IF(F2>=Assumptions!$B$51,F44*Assumptions!$B$158,0) | G46: =IF(G2>=Assumptions!$B$51,G44*Assumptions!$B$158,0) | H46: =IF(H2>=Assumptions!$B$51,H44*Assumptions!$B$158,0) | I46: =IF(I2>=Assumptions!$B$51,I44*Assumptions!$B$158,0) | J46: =IF(J2>=Assumptions!$B$51,J44*Assumptions!$B$158,0) | ... AE46: =IF(AE2>=Assumptions!$B$51,AE44*Assumptions!$B$158,0)
A47: ...of which have a live credit line (now all of them) | B47: cards | C47: =C46 | D47: =D46 | E47: =E46 | F47: =F46 | G47: =G46 | H47: =H46 | I47: =I46 | J47: =J46 | ... AE47: =AE46
A48: ...newly issued this period (flow, drives the issuance fee) | B48: cards | C48: =C46 | D48: =MAX(0,D46-C46) | E48: =MAX(0,E46-D46) | F48: =MAX(0,F46-E46) | G48: =MAX(0,G46-F46) | H48: =MAX(0,H46-G46) | I48: =MAX(0,I46-H46) | J48: =MAX(0,J46-I46) | K48: =MAX(0,K46-J46) | ... AE48: =MAX(0,AE46-AD46)
A49: Credit limit per customer (gold x LTV) | B49: USD | C49: =IF(C44=0,0,C43/C44*Assumptions!$B$31) | D49: =IF(D44=0,0,D43/D44*Assumptions!$B$31) | E49: =IF(E44=0,0,E43/E44*Assumptions!$B$31) | F49: =IF(F44=0,0,F43/F44*Assumptions!$B$31) | G49: =IF(G44=0,0,G43/G44*Assumptions!$B$31) | H49: =IF(H44=0,0,H43/H44*Assumptions!$B$31) | I49: =IF(I44=0,0,I43/I44*Assumptions!$B$31) | J49: =IF(J44=0,0,J43/J44*Assumptions!$B$31) | ... AE49: =IF(AE44=0,0,AE43/AE44*Assumptions!$B$31)
A50: Annual drawdown per card (limit x drawn x draws) | B50: USD/yr | C50: =C49*Assumptions!$B$171*Assumptions!$B$173 | D50: =D49*Assumptions!$B$171*Assumptions!$B$173 | E50: =E49*Assumptions!$B$171*Assumptions!$B$173 | F50: =F49*Assumptions!$B$171*Assumptions!$B$173 | G50: =G49*Assumptions!$B$171*Assumptions!$B$173 | H50: =H49*Assumptions!$B$171*Assumptions!$B$173 | I50: =I49*Assumptions!$B$171*Assumptions!$B$173 | J50: =J49*Assumptions!$B$171*Assumptions!$B$173 | ... AE50: =AE49*Assumptions!$B$171*Assumptions!$B$173
A51: Card spend per card per month | B51: USD | C51: =C50/12*C16 | D51: =D50/12*D16 | E51: =E50/12*E16 | F51: =F50/12*F16 | G51: =G50/12*G16 | H51: =H50/12*H16 | I51: =I50/12*I16 | J51: =J50/12*J16 | ... AE51: =AE50/12*AE16
A52: Card spend | B52: AED | C52: =C47*C51*Assumptions!$B$7*C7 | D52: =D47*D51*Assumptions!$B$7*D7 | E52: =E47*E51*Assumptions!$B$7*E7 | F52: =F47*F51*Assumptions!$B$7*F7 | G52: =G47*G51*Assumptions!$B$7*G7 | H52: =H47*H51*Assumptions!$B$7*H7 | I52: =I47*I51*Assumptions!$B$7*I7 | J52: =J47*J51*Assumptions!$B$7*J7 | ... AE52: =AE47*AE51*Assumptions!$B$7*AE7
A53: Card spend | B53: USD | C53: =C52/Assumptions!$B$7 | D53: =D52/Assumptions!$B$7 | E53: =E52/Assumptions!$B$7 | F53: =F52/Assumptions!$B$7 | G53: =G52/Assumptions!$B$7 | H53: =H52/Assumptions!$B$7 | I53: =I52/Assumptions!$B$7 | J53: =J52/Assumptions!$B$7 | ... AE53: =AE52/Assumptions!$B$7
A54: Average transaction size (derived) | B54: AED | C54: =IF(Assumptions!$B$159=0,0,C49*Assumptions!$B$171*Assumptions!$B$7/Assumptions!$B$159) | D54: =IF(Assumptions!$B$159=0,0,D49*Assumptions!$B$171*Assumptions!$B$7/Assumptions!$B$159) | E54: =IF(Assumptions!$B$159=0,0,E49*Assumptions!$B$171*Assumptions!$B$7/Assumptions!$B$159) | F54: =IF(Assumptions!$B$159=0,0,F49*Assumptions!$B$171*Assumptions!$B$7/Assumptions!$B$159) | G54: =IF(Assumptions!$B$159=0,0,G49*Assumptions!$B$171*Assumptions!$B$7/Assumptions!$B$159) | H54: =IF(Assumptions!$B$159=0,0,H49*Assumptions!$B$171*Assumptions!$B$7/Assumptions!$B$159) | I54: =IF(Assumptions!$B$159=0,0,I49*Assumptions!$B$171*Assumptions!$B$7/Assumptions!$B$159) | J54: =IF(Assumptions!$B$159=0,0,J49*Assumptions!$B$171*Assumptions!$B$7/Assumptions!$B$159) | ... AE54: =IF(Assumptions!$B$159=0,0,AE49*Assumptions!$B$171*Assumptions!$B$7/Assumptions!$B$159)
A55: Card authorisations (memo - drives cost, not revenue) | B55: auths | C55: =C47*Assumptions!$B$173*Assumptions!$B$159*C7/12*(1+Assumptions!$B$16) | D55: =D47*Assumptions!$B$173*Assumptions!$B$159*D7/12*(1+Assumptions!$B$16) | E55: =E47*Assumptions!$B$173*Assumptions!$B$159*E7/12*(1+Assumptions!$B$16) | F55: =F47*Assumptions!$B$173*Assumptions!$B$159*F7/12*(1+Assumptions!$B$16) | G55: =G47*Assumptions!$B$173*Assumptions!$B$159*G7/12*(1+Assumptions!$B$16) | H55: =H47*Assumptions!$B$173*Assumptions!$B$159*H7/12*(1+Assumptions!$B$16) | I55: =I47*Assumptions!$B$173*Assumptions!$B$159*I7/12*(1+Assumptions!$B$16) | J55: =J47*Assumptions!$B$173*Assumptions!$B$159*J7/12*(1+Assumptions!$B$16) | ... AE55: =AE47*Assumptions!$B$173*Assumptions!$B$159*AE7/12*(1+Assumptions!$B$16)
A56: Stream 1a - Entry fee, SIP | B56: USD | C56: =C36*Assumptions!$B$8 | D56: =D36*Assumptions!$B$8 | E56: =E36*Assumptions!$B$8 | F56: =F36*Assumptions!$B$8 | G56: =G36*Assumptions!$B$8 | H56: =H36*Assumptions!$B$8 | I56: =I36*Assumptions!$B$8 | J56: =J36*Assumptions!$B$8 | ... AE56: =AE36*Assumptions!$B$8
A57: Stream 1b - Entry fee, SPOT | B57: USD | C57: =C37*Assumptions!$B$8 | D57: =D37*Assumptions!$B$8 | E57: =E37*Assumptions!$B$8 | F57: =F37*Assumptions!$B$8 | G57: =G37*Assumptions!$B$8 | H57: =H37*Assumptions!$B$8 | I57: =I37*Assumptions!$B$8 | J57: =J37*Assumptions!$B$8 | ... AE57: =AE37*Assumptions!$B$8
A58: Stream 2 - Card interchange | B58: USD | C58: =C53*IF(Assumptions!$B$227=1,MIN(Assumptions!$B$14,1%),Assumptions!$B$14)*(1-Assumptions!$B$157) | D58: =D53*IF(Assumptions!$B$227=1,MIN(Assumptions!$B$14,1%),Assumptions!$B$14)*(1-Assumptions!$B$157) | E58: =E53*IF(Assumptions!$B$227=1,MIN(Assumptions!$B$14,1%),Assumptions!$B$14)*(1-Assumptions!$B$157) | F58: =F53*IF(Assumptions!$B$227=1,MIN(Assumptions!$B$14,1%),Assumptions!$B$14)*(1-Assumptions!$B$157) | G58: =G53*IF(Assumptions!$B$227=1,MIN(Assumptions!$B$14,1%),Assumptions!$B$14)*(1-Assumptions!$B$157) | H58: =H53*IF(Assumptions!$B$227=1,MIN(Assumptions!$B$14,1%),Assumptions!$B$14)*(1-Assumptions!$B$157) | I58: =I53*IF(Assumptions!$B$227=1,MIN(Assumptions!$B$14,1%),Assumptions!$B$14)*(1-Assumptions!$B$157) | J58: =J53*IF(Assumptions!$B$227=1,MIN(Assumptions!$B$14,1%),Assumptions!$B$14)*(1-Assumptions!$B$157) | ... AE58: =AE53*IF(Assumptions!$B$227=1,MIN(Assumptions!$B$14,1%),Assumptions!$B$14)*(1-Assumptions!$B$157)
A59: Family plan subscribers | B59: subscribers | C59: =IF(C2>=Assumptions!$B$50,C31*Assumptions!$B$174*(1-Assumptions!$B$177)^(C7/2),0) | D59: =IF(D2>=Assumptions!$B$50,C59*(1-Assumptions!$B$177)^D7+D31*Assumptions!$B$174*(1-Assumptions!$B$177)^(D7/2),0) | E59: =IF(E2>=Assumptions!$B$50,D59*(1-Assumptions!$B$177)^E7+E31*Assumptions!$B$174*(1-Assumptions!$B$177)^(E7/2),0) | F59: =IF(F2>=Assumptions!$B$50,E59*(1-Assumptions!$B$177)^F7+F31*Assumptions!$B$174*(1-Assumptions!$B$177)^(F7/2),0) | G59: =IF(G2>=Assumptions!$B$50,F59*(1-Assumptions!$B$177)^G7+G31*Assumptions!$B$174*(1-Assumptions!$B$177)^(G7/2),0) | H59: =IF(H2>=Assumptions!$B$50,G59*(1-Assumptions!$B$177)^H7+H31*Assumptions!$B$174*(1-Assumptions!$B$177)^(H7/2),0) | I59: =IF(I2>=Assumptions!$B$50,H59*(1-Assumptions!$B$177)^I7+I31*Assumptions!$B$174*(1-Assumptions!$B$177)^(I7/2),0) | J59: =IF(J2>=Assumptions!$B$50,I59*(1-Assumptions!$B$177)^J7+J31*Assumptions!$B$174*(1-Assumptions!$B$177)^(J7/2),0) | K59: =IF(K2>=Assumptions!$B$50,J59*(1-Assumptions!$B$177)^K7+K31*Assumptions!$B$174*(1-Assumptions!$B$177)^(K7/2),0) | ... AE59: =IF(AE2>=Assumptions!$B$50,AD59*(1-Assumptions!$B$177)^AE7+AE31*Assumptions!$B$174*(1-Assumptions!$B$177)^(AE7/2),0)
A60: Stream 3 - Family plan and Digital Will | B60: USD | C60: =C59*(Assumptions!$B$25+MAX(0,Assumptions!$B$176-1)*Assumptions!$B$26)/12*C7 | D60: =D59*(Assumptions!$B$25+MAX(0,Assumptions!$B$176-1)*Assumptions!$B$26)/12*D7 | E60: =E59*(Assumptions!$B$25+MAX(0,Assumptions!$B$176-1)*Assumptions!$B$26)/12*E7 | F60: =F59*(Assumptions!$B$25+MAX(0,Assumptions!$B$176-1)*Assumptions!$B$26)/12*F7 | G60: =G59*(Assumptions!$B$25+MAX(0,Assumptions!$B$176-1)*Assumptions!$B$26)/12*G7 | H60: =H59*(Assumptions!$B$25+MAX(0,Assumptions!$B$176-1)*Assumptions!$B$26)/12*H7 | I60: =I59*(Assumptions!$B$25+MAX(0,Assumptions!$B$176-1)*Assumptions!$B$26)/12*I7 | J60: =J59*(Assumptions!$B$25+MAX(0,Assumptions!$B$176-1)*Assumptions!$B$26)/12*J7 | ... AE60: =AE59*(Assumptions!$B$25+MAX(0,Assumptions!$B$176-1)*Assumptions!$B$26)/12*AE7
A61: Stream 4 - Cardholder fees (FX, ATM, events) | B61: USD | C61: =IF(C2>=Assumptions!$B$52,C53*C17*Assumptions!$B$17+C47*(Assumptions!$B$163*MAX(0,Assumptions!$B$167-Assumptions!$B$18)+Assumptions!$B$164*MAX(0,Assumptions!$B$168-Assumptions!$B$18)+Assumptions!$B$165*MAX(0,Assumptions!$B$169-Assumptions!$B$18)+Assumptions!$B$166*MAX(0,Assumptions!$B$170-Assumptions!$B$18))*Assumptions!$B$19/Assumptions!$B$7*C7+C48*Assumptions!$B$20/Assumptions!$B$7+C46*(Assumptions!$B$161*Assumptions!$B$20+Assumptions!$B$162*Assumptions!$B$21)/12/Assumptions!$B$7*C7,0) | D61: =IF(D2>=Assumptions!$B$52,D53*D17*Assumptions!$B$17+D47*(Assumptions!$B$163*MAX(0,Assumptions!$B$167-Assumptions!$B$18)+Assumptions!$B$164*MAX(0,Assumptions!$B$168-Assumptions!$B$18)+Assumptions!$B$165*MAX(0,Assumptions!$B$169-Assumptions!$B$18)+Assumptions!$B$166*MAX(0,Assumptions!$B$170-Assumptions!$B$18))*Assumptions!$B$19/Assumptions!$B$7*D7+D48*Assumptions!$B$20/Assumptions!$B$7+D46*(Assumptions!$B$161*Assumptions!$B$20+Assumptions!$B$162*Assumptions!$B$21)/12/Assumptions!$B$7*D7,0) | E61: =IF(E2>=Assumptions!$B$52,E53*E17*Assumptions!$B$17+E47*(Assumptions!$B$163*MAX(0,Assumptions!$B$167-Assumptions!$B$18)+Assumptions!$B$164*MAX(0,Assumptions!$B$168-Assumptions!$B$18)+Assumptions!$B$165*MAX(0,Assumptions!$B$169-Assumptions!$B$18)+Assumptions!$B$166*MAX(0,Assumptions!$B$170-Assumptions!$B$18))*Assumptions!$B$19/Assumptions!$B$7*E7+E48*Assumptions!$B$20/Assumptions!$B$7+E46*(Assumptions!$B$161*Assumptions!$B$20+Assumptions!$B$162*Assumptions!$B$21)/12/Assumptions!$B$7*E7,0) | F61: =IF(F2>=Assumptions!$B$52,F53*F17*Assumptions!$B$17+F47*(Assumptions!$B$163*MAX(0,Assumptions!$B$167-Assumptions!$B$18)+Assumptions!$B$164*MAX(0,Assumptions!$B$168-Assumptions!$B$18)+Assumptions!$B$165*MAX(0,Assumptions!$B$169-Assumptions!$B$18)+Assumptions!$B$166*MAX(0,Assumptions!$B$170-Assumptions!$B$18))*Assumptions!$B$19/Assumptions!$B$7*F7+F48*Assumptions!$B$20/Assumptions!$B$7+F46*(Assumptions!$B$161*Assumptions!$B$20+Assumptions!$B$162*Assumptions!$B$21)/12/Assumptions!$B$7*F7,0) | G61: =IF(G2>=Assumptions!$B$52,G53*G17*Assumptions!$B$17+G47*(Assumptions!$B$163*MAX(0,Assumptions!$B$167-Assumptions!$B$18)+Assumptions!$B$164*MAX(0,Assumptions!$B$168-Assumptions!$B$18)+Assumptions!$B$165*MAX(0,Assumptions!$B$169-Assumptions!$B$18)+Assumptions!$B$166*MAX(0,Assumptions!$B$170-Assumptions!$B$18))*Assumptions!$B$19/Assumptions!$B$7*G7+G48*Assumptions!$B$20/Assumptions!$B$7+G46*(Assumptions!$B$161*Assumptions!$B$20+Assumptions!$B$162*Assumptions!$B$21)/12/Assumptions!$B$7*G7,0) | H61: =IF(H2>=Assumptions!$B$52,H53*H17*Assumptions!$B$17+H47*(Assumptions!$B$163*MAX(0,Assumptions!$B$167-Assumptions!$B$18)+Assumptions!$B$164*MAX(0,Assumptions!$B$168-Assumptions!$B$18)+Assumptions!$B$165*MAX(0,Assumptions!$B$169-Assumptions!$B$18)+Assumptions!$B$166*MAX(0,Assumptions!$B$170-Assumptions!$B$18))*Assumptions!$B$19/Assumptions!$B$7*H7+H48*Assumptions!$B$20/Assumptions!$B$7+H46*(Assumptions!$B$161*Assumptions!$B$20+Assumptions!$B$162*Assumptions!$B$21)/12/Assumptions!$B$7*H7,0) | I61: =IF(I2>=Assumptions!$B$52,I53*I17*Assumptions!$B$17+I47*(Assumptions!$B$163*MAX(0,Assumptions!$B$167-Assumptions!$B$18)+Assumptions!$B$164*MAX(0,Assumptions!$B$168-Assumptions!$B$18)+Assumptions!$B$165*MAX(0,Assumptions!$B$169-Assumptions!$B$18)+Assumptions!$B$166*MAX(0,Assumptions!$B$170-Assumptions!$B$18))*Assumptions!$B$19/Assumptions!$B$7*I7+I48*Assumptions!$B$20/Assumptions!$B$7+I46*(Assumptions!$B$161*Assumptions!$B$20+Assumptions!$B$162*Assumptions!$B$21)/12/Assumptions!$B$7*I7,0) | J61: =IF(J2>=Assumptions!$B$52,J53*J17*Assumptions!$B$17+J47*(Assumptions!$B$163*MAX(0,Assumptions!$B$167-Assumptions!$B$18)+Assumptions!$B$164*MAX(0,Assumptions!$B$168-Assumptions!$B$18)+Assumptions!$B$165*MAX(0,Assumptions!$B$169-Assumptions!$B$18)+Assumptions!$B$166*MAX(0,Assumptions!$B$170-Assumptions!$B$18))*Assumptions!$B$19/Assumptions!$B$7*J7+J48*Assumptions!$B$20/Assumptions!$B$7+J46*(Assumptions!$B$161*Assumptions!$B$20+Assumptions!$B$162*Assumptions!$B$21)/12/Assumptions!$B$7*J7,0) | ... AE61: =IF(AE2>=Assumptions!$B$52,AE53*AE17*Assumptions!$B$17+AE47*(Assumptions!$B$163*MAX(0,Assumptions!$B$167-Assumptions!$B$18)+Assumptions!$B$164*MAX(0,Assumptions!$B$168-Assumptions!$B$18)+Assumptions!$B$165*MAX(0,Assumptions!$B$169-Assumptions!$B$18)+Assumptions!$B$166*MAX(0,Assumptions!$B$170-Assumptions!$B$18))*Assumptions!$B$19/Assumptions!$B$7*AE7+AE48*Assumptions!$B$20/Assumptions!$B$7+AE46*(Assumptions!$B$161*Assumptions!$B$20+Assumptions!$B$162*Assumptions!$B$21)/12/Assumptions!$B$7*AE7,0)
A62: Average drawn balance outstanding | B62: USD | C62: =IF(C2>=Assumptions!$B$53,C46*C49*(1-Assumptions!$B$227)*Assumptions!$B$171*Assumptions!$B$172,0) | D62: =IF(D2>=Assumptions!$B$53,D46*D49*(1-Assumptions!$B$227)*Assumptions!$B$171*Assumptions!$B$172,0) | E62: =IF(E2>=Assumptions!$B$53,E46*E49*(1-Assumptions!$B$227)*Assumptions!$B$171*Assumptions!$B$172,0) | F62: =IF(F2>=Assumptions!$B$53,F46*F49*(1-Assumptions!$B$227)*Assumptions!$B$171*Assumptions!$B$172,0) | G62: =IF(G2>=Assumptions!$B$53,G46*G49*(1-Assumptions!$B$227)*Assumptions!$B$171*Assumptions!$B$172,0) | H62: =IF(H2>=Assumptions!$B$53,H46*H49*(1-Assumptions!$B$227)*Assumptions!$B$171*Assumptions!$B$172,0) | I62: =IF(I2>=Assumptions!$B$53,I46*I49*(1-Assumptions!$B$227)*Assumptions!$B$171*Assumptions!$B$172,0) | J62: =IF(J2>=Assumptions!$B$53,J46*J49*(1-Assumptions!$B$227)*Assumptions!$B$171*Assumptions!$B$172,0) | ... AE62: =IF(AE2>=Assumptions!$B$53,AE46*AE49*(1-Assumptions!$B$227)*Assumptions!$B$171*Assumptions!$B$172,0)
A63: Stream 5 - Lending revenue share | B63: USD | C63: =IF(C2>=Assumptions!$B$53,(C62*Assumptions!$B$29*Assumptions!$B$30+C47*C50*(1-Assumptions!$B$227)*Assumptions!$B$27*Assumptions!$B$28)*C7/12,0) | D63: =IF(D2>=Assumptions!$B$53,(D62*Assumptions!$B$29*Assumptions!$B$30+D47*D50*(1-Assumptions!$B$227)*Assumptions!$B$27*Assumptions!$B$28)*D7/12,0) | E63: =IF(E2>=Assumptions!$B$53,(E62*Assumptions!$B$29*Assumptions!$B$30+E47*E50*(1-Assumptions!$B$227)*Assumptions!$B$27*Assumptions!$B$28)*E7/12,0) | F63: =IF(F2>=Assumptions!$B$53,(F62*Assumptions!$B$29*Assumptions!$B$30+F47*F50*(1-Assumptions!$B$227)*Assumptions!$B$27*Assumptions!$B$28)*F7/12,0) | G63: =IF(G2>=Assumptions!$B$53,(G62*Assumptions!$B$29*Assumptions!$B$30+G47*G50*(1-Assumptions!$B$227)*Assumptions!$B$27*Assumptions!$B$28)*G7/12,0) | H63: =IF(H2>=Assumptions!$B$53,(H62*Assumptions!$B$29*Assumptions!$B$30+H47*H50*(1-Assumptions!$B$227)*Assumptions!$B$27*Assumptions!$B$28)*H7/12,0) | I63: =IF(I2>=Assumptions!$B$53,(I62*Assumptions!$B$29*Assumptions!$B$30+I47*I50*(1-Assumptions!$B$227)*Assumptions!$B$27*Assumptions!$B$28)*I7/12,0) | J63: =IF(J2>=Assumptions!$B$53,(J62*Assumptions!$B$29*Assumptions!$B$30+J47*J50*(1-Assumptions!$B$227)*Assumptions!$B$27*Assumptions!$B$28)*J7/12,0) | ... AE63: =IF(AE2>=Assumptions!$B$53,(AE62*Assumptions!$B$29*Assumptions!$B$30+AE47*AE50*(1-Assumptions!$B$227)*Assumptions!$B$27*Assumptions!$B$28)*AE7/12,0)
A64: Redemption events (memo - drives cost, not revenue) | B64: events | C64: =IF(C2>=Assumptions!$B$49,(C32+C34*Assumptions!$B$153)*Assumptions!$B$152*C7/12,0) | D64: =IF(D2>=Assumptions!$B$49,(D32+D34*Assumptions!$B$153)*Assumptions!$B$152*D7/12,0) | E64: =IF(E2>=Assumptions!$B$49,(E32+E34*Assumptions!$B$153)*Assumptions!$B$152*E7/12,0) | F64: =IF(F2>=Assumptions!$B$49,(F32+F34*Assumptions!$B$153)*Assumptions!$B$152*F7/12,0) | G64: =IF(G2>=Assumptions!$B$49,(G32+G34*Assumptions!$B$153)*Assumptions!$B$152*G7/12,0) | H64: =IF(H2>=Assumptions!$B$49,(H32+H34*Assumptions!$B$153)*Assumptions!$B$152*H7/12,0) | I64: =IF(I2>=Assumptions!$B$49,(I32+I34*Assumptions!$B$153)*Assumptions!$B$152*I7/12,0) | J64: =IF(J2>=Assumptions!$B$49,(J32+J34*Assumptions!$B$153)*Assumptions!$B$152*J7/12,0) | ... AE64: =IF(AE2>=Assumptions!$B$49,(AE32+AE34*Assumptions!$B$153)*Assumptions!$B$152*AE7/12,0)
A65: SUBTOTAL - UAE | B65: USD | C65: =C56+C57+C58+C60+C61+C63 | D65: =D56+D57+D58+D60+D61+D63 | E65: =E56+E57+E58+E60+E61+E63 | F65: =F56+F57+F58+F60+F61+F63 | G65: =G56+G57+G58+G60+G61+G63 | H65: =H56+H57+H58+H60+H61+H63 | I65: =I56+I57+I58+I60+I61+I63 | J65: =J56+J57+J58+J60+J61+J63 | ... AE65: =AE56+AE57+AE58+AE60+AE61+AE63
A67: REGION: OMAN AND BAHRAIN
A68: Marketing CAC this period (ramping Y1 to Y7) | B68: USD/customer | C68: =Assumptions!$B$137+(Assumptions!$B$140-Assumptions!$B$137)*(C5-1)/6 | D68: =Assumptions!$B$137+(Assumptions!$B$140-Assumptions!$B$137)*(D5-1)/6 | E68: =Assumptions!$B$137+(Assumptions!$B$140-Assumptions!$B$137)*(E5-1)/6 | F68: =Assumptions!$B$137+(Assumptions!$B$140-Assumptions!$B$137)*(F5-1)/6 | G68: =Assumptions!$B$137+(Assumptions!$B$140-Assumptions!$B$137)*(G5-1)/6 | H68: =Assumptions!$B$137+(Assumptions!$B$140-Assumptions!$B$137)*(H5-1)/6 | I68: =Assumptions!$B$137+(Assumptions!$B$140-Assumptions!$B$137)*(I5-1)/6 | J68: =Assumptions!$B$137+(Assumptions!$B$140-Assumptions!$B$137)*(J5-1)/6 | ... AE68: =Assumptions!$B$137+(Assumptions!$B$140-Assumptions!$B$137)*(AE5-1)/6
A69: Direct-driven (this market's budget at its own CAC) | B69: accounts | C69: =INDEX(Assumptions!$B$114:$B$120,C5)*Assumptions!$B$143/12*C7/C68*(1+Assumptions!$B$147)*IF(C2>=Assumptions!$B$56,1,0) | D69: =INDEX(Assumptions!$B$114:$B$120,D5)*Assumptions!$B$143/12*D7/D68*(1+Assumptions!$B$147)*IF(D2>=Assumptions!$B$56,1,0) | E69: =INDEX(Assumptions!$B$114:$B$120,E5)*Assumptions!$B$143/12*E7/E68*(1+Assumptions!$B$147)*IF(E2>=Assumptions!$B$56,1,0) | F69: =INDEX(Assumptions!$B$114:$B$120,F5)*Assumptions!$B$143/12*F7/F68*(1+Assumptions!$B$147)*IF(F2>=Assumptions!$B$56,1,0) | G69: =INDEX(Assumptions!$B$114:$B$120,G5)*Assumptions!$B$143/12*G7/G68*(1+Assumptions!$B$147)*IF(G2>=Assumptions!$B$56,1,0) | H69: =INDEX(Assumptions!$B$114:$B$120,H5)*Assumptions!$B$143/12*H7/H68*(1+Assumptions!$B$147)*IF(H2>=Assumptions!$B$56,1,0) | I69: =INDEX(Assumptions!$B$114:$B$120,I5)*Assumptions!$B$143/12*I7/I68*(1+Assumptions!$B$147)*IF(I2>=Assumptions!$B$56,1,0) | J69: =INDEX(Assumptions!$B$114:$B$120,J5)*Assumptions!$B$143/12*J7/J68*(1+Assumptions!$B$147)*IF(J2>=Assumptions!$B$56,1,0) | ... AE69: =INDEX(Assumptions!$B$114:$B$120,AE5)*Assumptions!$B$143/12*AE7/AE68*(1+Assumptions!$B$147)*IF(AE2>=Assumptions!$B$56,1,0)
A70: Referral-driven (from this market's own base) | B70: accounts | C70: 0 | D70: =IF(D2>=Assumptions!$B$55,C75*Assumptions!$B$145/12*Assumptions!$B$146*D7,0) | E70: =IF(E2>=Assumptions!$B$55,D75*Assumptions!$B$145/12*Assumptions!$B$146*E7,0) | F70: =IF(F2>=Assumptions!$B$55,E75*Assumptions!$B$145/12*Assumptions!$B$146*F7,0) | G70: =IF(G2>=Assumptions!$B$55,F75*Assumptions!$B$145/12*Assumptions!$B$146*G7,0) | H70: =IF(H2>=Assumptions!$B$55,G75*Assumptions!$B$145/12*Assumptions!$B$146*H7,0) | I70: =IF(I2>=Assumptions!$B$55,H75*Assumptions!$B$145/12*Assumptions!$B$146*I7,0) | J70: =IF(J2>=Assumptions!$B$55,I75*Assumptions!$B$145/12*Assumptions!$B$146*J7,0) | K70: =IF(K2>=Assumptions!$B$55,J75*Assumptions!$B$145/12*Assumptions!$B$146*K7,0) | ... AE70: =IF(AE2>=Assumptions!$B$55,AD75*Assumptions!$B$145/12*Assumptions!$B$146*AE7,0)
A71: Agent-driven (this market's own agents) | B71: accounts | C71: =INDEX(Assumptions!$B$100:$B$106,C5)*Assumptions!$B$135*INDEX(Assumptions!$B$121:$B$127,C5)*C7*IF(C2>=Assumptions!$B$56,1,0) | D71: =INDEX(Assumptions!$B$100:$B$106,D5)*Assumptions!$B$135*INDEX(Assumptions!$B$121:$B$127,D5)*D7*IF(D2>=Assumptions!$B$56,1,0) | E71: =INDEX(Assumptions!$B$100:$B$106,E5)*Assumptions!$B$135*INDEX(Assumptions!$B$121:$B$127,E5)*E7*IF(E2>=Assumptions!$B$56,1,0) | F71: =INDEX(Assumptions!$B$100:$B$106,F5)*Assumptions!$B$135*INDEX(Assumptions!$B$121:$B$127,F5)*F7*IF(F2>=Assumptions!$B$56,1,0) | G71: =INDEX(Assumptions!$B$100:$B$106,G5)*Assumptions!$B$135*INDEX(Assumptions!$B$121:$B$127,G5)*G7*IF(G2>=Assumptions!$B$56,1,0) | H71: =INDEX(Assumptions!$B$100:$B$106,H5)*Assumptions!$B$135*INDEX(Assumptions!$B$121:$B$127,H5)*H7*IF(H2>=Assumptions!$B$56,1,0) | I71: =INDEX(Assumptions!$B$100:$B$106,I5)*Assumptions!$B$135*INDEX(Assumptions!$B$121:$B$127,I5)*I7*IF(I2>=Assumptions!$B$56,1,0) | J71: =INDEX(Assumptions!$B$100:$B$106,J5)*Assumptions!$B$135*INDEX(Assumptions!$B$121:$B$127,J5)*J7*IF(J2>=Assumptions!$B$56,1,0) | ... AE71: =INDEX(Assumptions!$B$100:$B$106,AE5)*Assumptions!$B$135*INDEX(Assumptions!$B$121:$B$127,AE5)*AE7*IF(AE2>=Assumptions!$B$56,1,0)
A72: Raw demand | B72: accounts | C72: =C69+C70+C71 | D72: =D69+D70+D71 | E72: =E69+E70+E71 | F72: =F69+F70+F71 | G72: =G69+G70+G71 | H72: =H69+H70+H71 | I72: =I69+I70+I71 | J72: =J69+J70+J71 | ... AE72: =AE69+AE70+AE71
A73: Saturation (this region's own headroom) | B73: x | C73: 1 | D73: =MAX(0,1-C78/Assumptions!$B$85) | E73: =MAX(0,1-D78/Assumptions!$B$85) | F73: =MAX(0,1-E78/Assumptions!$B$85) | G73: =MAX(0,1-F78/Assumptions!$B$85) | H73: =MAX(0,1-G78/Assumptions!$B$85) | I73: =MAX(0,1-H78/Assumptions!$B$85) | J73: =MAX(0,1-I78/Assumptions!$B$85) | K73: =MAX(0,1-J78/Assumptions!$B$85) | ... AE73: =MAX(0,1-AD78/Assumptions!$B$85)
A74: New customers | B74: accounts | C74: =C72*C73*C15 | D74: =D72*D73*D15 | E74: =E72*E73*E15 | F74: =F72*F73*F15 | G74: =G72*G73*G15 | H74: =H72*H73*H15 | I74: =I72*I73*I15 | J74: =J72*J73*J15 | ... AE74: =AE72*AE73*AE15
A75: Paying customers | B75: accounts | C75: =C74*(1-Assumptions!$B$134)^(C7/2) | D75: =C75*(1-Assumptions!$B$134)^D7+D74*(1-Assumptions!$B$134)^(D7/2) | E75: =D75*(1-Assumptions!$B$134)^E7+E74*(1-Assumptions!$B$134)^(E7/2) | F75: =E75*(1-Assumptions!$B$134)^F7+F74*(1-Assumptions!$B$134)^(F7/2) | G75: =F75*(1-Assumptions!$B$134)^G7+G74*(1-Assumptions!$B$134)^(G7/2) | H75: =G75*(1-Assumptions!$B$134)^H7+H74*(1-Assumptions!$B$134)^(H7/2) | I75: =H75*(1-Assumptions!$B$134)^I7+I74*(1-Assumptions!$B$134)^(I7/2) | J75: =I75*(1-Assumptions!$B$134)^J7+J74*(1-Assumptions!$B$134)^(J7/2) | K75: =J75*(1-Assumptions!$B$134)^K7+K74*(1-Assumptions!$B$134)^(K7/2) | ... AE75: =AD75*(1-Assumptions!$B$134)^AE7+AE74*(1-Assumptions!$B$134)^(AE7/2)
A76: Churned this period | B76: accounts | C76: =C74-C75 | D76: =C75+D74-D75 | E76: =D75+E74-E75 | F76: =E75+F74-F75 | G76: =F75+G74-G75 | H76: =G75+H74-H75 | I76: =H75+I74-I75 | J76: =I75+J74-J75 | K76: =J75+K74-K75 | ... AE76: =AD75+AE74-AE75
A77: Holders (stopped paying, still hold gold) | B77: accounts | C77: =C76 | D77: =C77+D76 | E77: =D77+E76 | F77: =E77+F76 | G77: =F77+G76 | H77: =G77+H76 | I77: =H77+I76 | J77: =I77+J76 | K77: =J77+K76 | ... AE77: =AD77+AE76
A78: Cumulative ever acquired | B78: accounts | C78: =C74 | D78: =C78+D74 | E78: =D78+E74 | F78: =E78+F74 | G78: =F78+G74 | H78: =G78+H74 | I78: =H78+I74 | J78: =I78+J74 | K78: =J78+K74 | ... AE78: =AD78+AE74
A79: SIP contributions | B79: USD | C79: =IF(C2>=Assumptions!$B$47,C75*Assumptions!$B$191*C7,0) | D79: =IF(D2>=Assumptions!$B$47,D75*Assumptions!$B$191*D7,0) | E79: =IF(E2>=Assumptions!$B$47,E75*Assumptions!$B$191*E7,0) | F79: =IF(F2>=Assumptions!$B$47,F75*Assumptions!$B$191*F7,0) | G79: =IF(G2>=Assumptions!$B$47,G75*Assumptions!$B$191*G7,0) | H79: =IF(H2>=Assumptions!$B$47,H75*Assumptions!$B$191*H7,0) | I79: =IF(I2>=Assumptions!$B$47,I75*Assumptions!$B$191*I7,0) | J79: =IF(J2>=Assumptions!$B$47,J75*Assumptions!$B$191*J7,0) | ... AE79: =IF(AE2>=Assumptions!$B$47,AE75*Assumptions!$B$191*AE7,0)
A80: Spot purchase volume | B80: USD | C80: =IF(C2>=Assumptions!$B$48,C75*Assumptions!$B$36*Assumptions!$B$154*Assumptions!$B$156*Assumptions!$B$33*Assumptions!$B$155/12*C7,0) | D80: =IF(D2>=Assumptions!$B$48,D75*Assumptions!$B$36*Assumptions!$B$154*Assumptions!$B$156*Assumptions!$B$33*Assumptions!$B$155/12*D7,0) | E80: =IF(E2>=Assumptions!$B$48,E75*Assumptions!$B$36*Assumptions!$B$154*Assumptions!$B$156*Assumptions!$B$33*Assumptions!$B$155/12*E7,0) | F80: =IF(F2>=Assumptions!$B$48,F75*Assumptions!$B$36*Assumptions!$B$154*Assumptions!$B$156*Assumptions!$B$33*Assumptions!$B$155/12*F7,0) | G80: =IF(G2>=Assumptions!$B$48,G75*Assumptions!$B$36*Assumptions!$B$154*Assumptions!$B$156*Assumptions!$B$33*Assumptions!$B$155/12*G7,0) | H80: =IF(H2>=Assumptions!$B$48,H75*Assumptions!$B$36*Assumptions!$B$154*Assumptions!$B$156*Assumptions!$B$33*Assumptions!$B$155/12*H7,0) | I80: =IF(I2>=Assumptions!$B$48,I75*Assumptions!$B$36*Assumptions!$B$154*Assumptions!$B$156*Assumptions!$B$33*Assumptions!$B$155/12*I7,0) | J80: =IF(J2>=Assumptions!$B$48,J75*Assumptions!$B$36*Assumptions!$B$154*Assumptions!$B$156*Assumptions!$B$33*Assumptions!$B$155/12*J7,0) | ... AE80: =IF(AE2>=Assumptions!$B$48,AE75*Assumptions!$B$36*Assumptions!$B$154*Assumptions!$B$156*Assumptions!$B$33*Assumptions!$B$155/12*AE7,0)
A81: Grams purchased | B81: grams | C81: =(C79+C80)*(1-Assumptions!$B$8)/C20/(1+Assumptions!$B$9*(1-Assumptions!$B$229)) | D81: =(D79+D80)*(1-Assumptions!$B$8)/D20/(1+Assumptions!$B$9*(1-Assumptions!$B$229)) | E81: =(E79+E80)*(1-Assumptions!$B$8)/E20/(1+Assumptions!$B$9*(1-Assumptions!$B$229)) | F81: =(F79+F80)*(1-Assumptions!$B$8)/F20/(1+Assumptions!$B$9*(1-Assumptions!$B$229)) | G81: =(G79+G80)*(1-Assumptions!$B$8)/G20/(1+Assumptions!$B$9*(1-Assumptions!$B$229)) | H81: =(H79+H80)*(1-Assumptions!$B$8)/H20/(1+Assumptions!$B$9*(1-Assumptions!$B$229)) | I81: =(I79+I80)*(1-Assumptions!$B$8)/I20/(1+Assumptions!$B$9*(1-Assumptions!$B$229)) | J81: =(J79+J80)*(1-Assumptions!$B$8)/J20/(1+Assumptions!$B$9*(1-Assumptions!$B$229)) | ... AE81: =(AE79+AE80)*(1-Assumptions!$B$8)/AE20/(1+Assumptions!$B$9*(1-Assumptions!$B$229))
A82: Collateral-eligible AUM decay rate (holder-weighted) | B82: %/period | C82: =(Assumptions!$B$151+Assumptions!$B$152*IF(C75+C77=0,1,(C75+C77*Assumptions!$B$153)/(C75+C77)))*C7/12 | D82: =(Assumptions!$B$151+Assumptions!$B$152*IF(D75+D77=0,1,(D75+D77*Assumptions!$B$153)/(D75+D77)))*D7/12 | E82: =(Assumptions!$B$151+Assumptions!$B$152*IF(E75+E77=0,1,(E75+E77*Assumptions!$B$153)/(E75+E77)))*E7/12 | F82: =(Assumptions!$B$151+Assumptions!$B$152*IF(F75+F77=0,1,(F75+F77*Assumptions!$B$153)/(F75+F77)))*F7/12 | G82: =(Assumptions!$B$151+Assumptions!$B$152*IF(G75+G77=0,1,(G75+G77*Assumptions!$B$153)/(G75+G77)))*G7/12 | H82: =(Assumptions!$B$151+Assumptions!$B$152*IF(H75+H77=0,1,(H75+H77*Assumptions!$B$153)/(H75+H77)))*H7/12 | I82: =(Assumptions!$B$151+Assumptions!$B$152*IF(I75+I77=0,1,(I75+I77*Assumptions!$B$153)/(I75+I77)))*I7/12 | J82: =(Assumptions!$B$151+Assumptions!$B$152*IF(J75+J77=0,1,(J75+J77*Assumptions!$B$153)/(J75+J77)))*J7/12 | ... AE82: =(Assumptions!$B$151+Assumptions!$B$152*IF(AE75+AE77=0,1,(AE75+AE77*Assumptions!$B$153)/(AE75+AE77)))*AE7/12
A83: Redemption-only decay rate (metal actually leaving) | B83: %/period | C83: =Assumptions!$B$152*IF(C75+C77=0,1,(C75+C77*Assumptions!$B$153)/(C75+C77))*C7/12 | D83: =Assumptions!$B$152*IF(D75+D77=0,1,(D75+D77*Assumptions!$B$153)/(D75+D77))*D7/12 | E83: =Assumptions!$B$152*IF(E75+E77=0,1,(E75+E77*Assumptions!$B$153)/(E75+E77))*E7/12 | F83: =Assumptions!$B$152*IF(F75+F77=0,1,(F75+F77*Assumptions!$B$153)/(F75+F77))*F7/12 | G83: =Assumptions!$B$152*IF(G75+G77=0,1,(G75+G77*Assumptions!$B$153)/(G75+G77))*G7/12 | H83: =Assumptions!$B$152*IF(H75+H77=0,1,(H75+H77*Assumptions!$B$153)/(H75+H77))*H7/12 | I83: =Assumptions!$B$152*IF(I75+I77=0,1,(I75+I77*Assumptions!$B$153)/(I75+I77))*I7/12 | J83: =Assumptions!$B$152*IF(J75+J77=0,1,(J75+J77*Assumptions!$B$153)/(J75+J77))*J7/12 | ... AE83: =Assumptions!$B$152*IF(AE75+AE77=0,1,(AE75+AE77*Assumptions!$B$153)/(AE75+AE77))*AE7/12
A84: Grams held (collateral-eligible) | B84: grams | C84: =C81 | D84: =C84*(1-D82)+D81 | E84: =D84*(1-E82)+E81 | F84: =E84*(1-F82)+F81 | G84: =F84*(1-G82)+G81 | H84: =G84*(1-H82)+H81 | I84: =H84*(1-I82)+I81 | J84: =I84*(1-J82)+J81 | K84: =J84*(1-K82)+K81 | ... AE84: =AD84*(1-AE82)+AE81
A85: Grams under custody (vaulted, incl. self-custodied) | B85: grams | C85: =C81 | D85: =C85*(1-D83)+D81 | E85: =D85*(1-E83)+E81 | F85: =E85*(1-F83)+F81 | G85: =F85*(1-G83)+G81 | H85: =G85*(1-H83)+H81 | I85: =H85*(1-I83)+I81 | J85: =I85*(1-J83)+J81 | K85: =J85*(1-K83)+K81 | ... AE85: =AD85*(1-AE83)+AE81
A86: AUM | B86: USD | C86: =C84*C20 | D86: =D84*D20 | E86: =E84*E20 | F86: =F84*F20 | G86: =G84*G20 | H86: =H84*H20 | I86: =I84*I20 | J86: =J84*J20 | ... AE86: =AE84*AE20
A87: Card-eligible base | B87: accounts | C87: =C75+C77*Assumptions!$B$228 | D87: =D75+D77*Assumptions!$B$228 | E87: =E75+E77*Assumptions!$B$228 | F87: =F75+F77*Assumptions!$B$228 | G87: =G75+G77*Assumptions!$B$228 | H87: =H75+H77*Assumptions!$B$228 | I87: =I75+I77*Assumptions!$B$228 | J87: =J75+J77*Assumptions!$B$228 | ... AE87: =AE75+AE77*Assumptions!$B$228
A88: Reaches an ICS benefit tier (memo - drives discounts, not access) | B88: accounts | C88: =IF(C7>1,C87*Assumptions!$B$149,IF(C2>Assumptions!$B$150,INDEX($C$87:$AE$87,1,C2-Assumptions!$B$150)*Assumptions!$B$149,0)) | D88: =IF(D7>1,D87*Assumptions!$B$149,IF(D2>Assumptions!$B$150,INDEX($C$87:$AE$87,1,D2-Assumptions!$B$150)*Assumptions!$B$149,0)) | E88: =IF(E7>1,E87*Assumptions!$B$149,IF(E2>Assumptions!$B$150,INDEX($C$87:$AE$87,1,E2-Assumptions!$B$150)*Assumptions!$B$149,0)) | F88: =IF(F7>1,F87*Assumptions!$B$149,IF(F2>Assumptions!$B$150,INDEX($C$87:$AE$87,1,F2-Assumptions!$B$150)*Assumptions!$B$149,0)) | G88: =IF(G7>1,G87*Assumptions!$B$149,IF(G2>Assumptions!$B$150,INDEX($C$87:$AE$87,1,G2-Assumptions!$B$150)*Assumptions!$B$149,0)) | H88: =IF(H7>1,H87*Assumptions!$B$149,IF(H2>Assumptions!$B$150,INDEX($C$87:$AE$87,1,H2-Assumptions!$B$150)*Assumptions!$B$149,0)) | I88: =IF(I7>1,I87*Assumptions!$B$149,IF(I2>Assumptions!$B$150,INDEX($C$87:$AE$87,1,I2-Assumptions!$B$150)*Assumptions!$B$149,0)) | J88: =IF(J7>1,J87*Assumptions!$B$149,IF(J2>Assumptions!$B$150,INDEX($C$87:$AE$87,1,J2-Assumptions!$B$150)*Assumptions!$B$149,0)) | ... AE88: =IF(AE7>1,AE87*Assumptions!$B$149,IF(AE2>Assumptions!$B$150,INDEX($C$87:$AE$87,1,AE2-Assumptions!$B$150)*Assumptions!$B$149,0))
A89: Active cards | B89: cards | C89: =IF(C2>=Assumptions!$B$51,C87*Assumptions!$B$158,0) | D89: =IF(D2>=Assumptions!$B$51,D87*Assumptions!$B$158,0) | E89: =IF(E2>=Assumptions!$B$51,E87*Assumptions!$B$158,0) | F89: =IF(F2>=Assumptions!$B$51,F87*Assumptions!$B$158,0) | G89: =IF(G2>=Assumptions!$B$51,G87*Assumptions!$B$158,0) | H89: =IF(H2>=Assumptions!$B$51,H87*Assumptions!$B$158,0) | I89: =IF(I2>=Assumptions!$B$51,I87*Assumptions!$B$158,0) | J89: =IF(J2>=Assumptions!$B$51,J87*Assumptions!$B$158,0) | ... AE89: =IF(AE2>=Assumptions!$B$51,AE87*Assumptions!$B$158,0)
A90: ...of which have a live credit line (now all of them) | B90: cards | C90: =C89 | D90: =D89 | E90: =E89 | F90: =F89 | G90: =G89 | H90: =H89 | I90: =I89 | J90: =J89 | ... AE90: =AE89
A91: ...newly issued this period (flow, drives the issuance fee) | B91: cards | C91: =C89 | D91: =MAX(0,D89-C89) | E91: =MAX(0,E89-D89) | F91: =MAX(0,F89-E89) | G91: =MAX(0,G89-F89) | H91: =MAX(0,H89-G89) | I91: =MAX(0,I89-H89) | J91: =MAX(0,J89-I89) | K91: =MAX(0,K89-J89) | ... AE91: =MAX(0,AE89-AD89)
A92: Credit limit per customer (gold x LTV) | B92: USD | C92: =IF(C87=0,0,C86/C87*Assumptions!$B$31) | D92: =IF(D87=0,0,D86/D87*Assumptions!$B$31) | E92: =IF(E87=0,0,E86/E87*Assumptions!$B$31) | F92: =IF(F87=0,0,F86/F87*Assumptions!$B$31) | G92: =IF(G87=0,0,G86/G87*Assumptions!$B$31) | H92: =IF(H87=0,0,H86/H87*Assumptions!$B$31) | I92: =IF(I87=0,0,I86/I87*Assumptions!$B$31) | J92: =IF(J87=0,0,J86/J87*Assumptions!$B$31) | ... AE92: =IF(AE87=0,0,AE86/AE87*Assumptions!$B$31)
A93: Annual drawdown per card (limit x drawn x draws) | B93: USD/yr | C93: =C92*Assumptions!$B$171*Assumptions!$B$173 | D93: =D92*Assumptions!$B$171*Assumptions!$B$173 | E93: =E92*Assumptions!$B$171*Assumptions!$B$173 | F93: =F92*Assumptions!$B$171*Assumptions!$B$173 | G93: =G92*Assumptions!$B$171*Assumptions!$B$173 | H93: =H92*Assumptions!$B$171*Assumptions!$B$173 | I93: =I92*Assumptions!$B$171*Assumptions!$B$173 | J93: =J92*Assumptions!$B$171*Assumptions!$B$173 | ... AE93: =AE92*Assumptions!$B$171*Assumptions!$B$173
A94: Card spend per card per month | B94: USD | C94: =C93/12*C16 | D94: =D93/12*D16 | E94: =E93/12*E16 | F94: =F93/12*F16 | G94: =G93/12*G16 | H94: =H93/12*H16 | I94: =I93/12*I16 | J94: =J93/12*J16 | ... AE94: =AE93/12*AE16
A95: Card spend | B95: AED | C95: =C90*C94*Assumptions!$B$7*C7 | D95: =D90*D94*Assumptions!$B$7*D7 | E95: =E90*E94*Assumptions!$B$7*E7 | F95: =F90*F94*Assumptions!$B$7*F7 | G95: =G90*G94*Assumptions!$B$7*G7 | H95: =H90*H94*Assumptions!$B$7*H7 | I95: =I90*I94*Assumptions!$B$7*I7 | J95: =J90*J94*Assumptions!$B$7*J7 | ... AE95: =AE90*AE94*Assumptions!$B$7*AE7
A96: Card spend | B96: USD | C96: =C95/Assumptions!$B$7 | D96: =D95/Assumptions!$B$7 | E96: =E95/Assumptions!$B$7 | F96: =F95/Assumptions!$B$7 | G96: =G95/Assumptions!$B$7 | H96: =H95/Assumptions!$B$7 | I96: =I95/Assumptions!$B$7 | J96: =J95/Assumptions!$B$7 | ... AE96: =AE95/Assumptions!$B$7
A97: Average transaction size (derived) | B97: AED | C97: =IF(Assumptions!$B$159=0,0,C92*Assumptions!$B$171*Assumptions!$B$7/Assumptions!$B$159) | D97: =IF(Assumptions!$B$159=0,0,D92*Assumptions!$B$171*Assumptions!$B$7/Assumptions!$B$159) | E97: =IF(Assumptions!$B$159=0,0,E92*Assumptions!$B$171*Assumptions!$B$7/Assumptions!$B$159) | F97: =IF(Assumptions!$B$159=0,0,F92*Assumptions!$B$171*Assumptions!$B$7/Assumptions!$B$159) | G97: =IF(Assumptions!$B$159=0,0,G92*Assumptions!$B$171*Assumptions!$B$7/Assumptions!$B$159) | H97: =IF(Assumptions!$B$159=0,0,H92*Assumptions!$B$171*Assumptions!$B$7/Assumptions!$B$159) | I97: =IF(Assumptions!$B$159=0,0,I92*Assumptions!$B$171*Assumptions!$B$7/Assumptions!$B$159) | J97: =IF(Assumptions!$B$159=0,0,J92*Assumptions!$B$171*Assumptions!$B$7/Assumptions!$B$159) | ... AE97: =IF(Assumptions!$B$159=0,0,AE92*Assumptions!$B$171*Assumptions!$B$7/Assumptions!$B$159)
A98: Card authorisations (memo - drives cost, not revenue) | B98: auths | C98: =C90*Assumptions!$B$173*Assumptions!$B$159*C7/12*(1+Assumptions!$B$16) | D98: =D90*Assumptions!$B$173*Assumptions!$B$159*D7/12*(1+Assumptions!$B$16) | E98: =E90*Assumptions!$B$173*Assumptions!$B$159*E7/12*(1+Assumptions!$B$16) | F98: =F90*Assumptions!$B$173*Assumptions!$B$159*F7/12*(1+Assumptions!$B$16) | G98: =G90*Assumptions!$B$173*Assumptions!$B$159*G7/12*(1+Assumptions!$B$16) | H98: =H90*Assumptions!$B$173*Assumptions!$B$159*H7/12*(1+Assumptions!$B$16) | I98: =I90*Assumptions!$B$173*Assumptions!$B$159*I7/12*(1+Assumptions!$B$16) | J98: =J90*Assumptions!$B$173*Assumptions!$B$159*J7/12*(1+Assumptions!$B$16) | ... AE98: =AE90*Assumptions!$B$173*Assumptions!$B$159*AE7/12*(1+Assumptions!$B$16)
A99: Stream 1a - Entry fee, SIP | B99: USD | C99: =C79*Assumptions!$B$8 | D99: =D79*Assumptions!$B$8 | E99: =E79*Assumptions!$B$8 | F99: =F79*Assumptions!$B$8 | G99: =G79*Assumptions!$B$8 | H99: =H79*Assumptions!$B$8 | I99: =I79*Assumptions!$B$8 | J99: =J79*Assumptions!$B$8 | ... AE99: =AE79*Assumptions!$B$8
A100: Stream 1b - Entry fee, SPOT | B100: USD | C100: =C80*Assumptions!$B$8 | D100: =D80*Assumptions!$B$8 | E100: =E80*Assumptions!$B$8 | F100: =F80*Assumptions!$B$8 | G100: =G80*Assumptions!$B$8 | H100: =H80*Assumptions!$B$8 | I100: =I80*Assumptions!$B$8 | J100: =J80*Assumptions!$B$8 | ... AE100: =AE80*Assumptions!$B$8
A101: Stream 2 - Card interchange | B101: USD | C101: =C96*IF(Assumptions!$B$227=1,MIN(Assumptions!$B$14,1%),Assumptions!$B$14)*(1-Assumptions!$B$157) | D101: =D96*IF(Assumptions!$B$227=1,MIN(Assumptions!$B$14,1%),Assumptions!$B$14)*(1-Assumptions!$B$157) | E101: =E96*IF(Assumptions!$B$227=1,MIN(Assumptions!$B$14,1%),Assumptions!$B$14)*(1-Assumptions!$B$157) | F101: =F96*IF(Assumptions!$B$227=1,MIN(Assumptions!$B$14,1%),Assumptions!$B$14)*(1-Assumptions!$B$157) | G101: =G96*IF(Assumptions!$B$227=1,MIN(Assumptions!$B$14,1%),Assumptions!$B$14)*(1-Assumptions!$B$157) | H101: =H96*IF(Assumptions!$B$227=1,MIN(Assumptions!$B$14,1%),Assumptions!$B$14)*(1-Assumptions!$B$157) | I101: =I96*IF(Assumptions!$B$227=1,MIN(Assumptions!$B$14,1%),Assumptions!$B$14)*(1-Assumptions!$B$157) | J101: =J96*IF(Assumptions!$B$227=1,MIN(Assumptions!$B$14,1%),Assumptions!$B$14)*(1-Assumptions!$B$157) | ... AE101: =AE96*IF(Assumptions!$B$227=1,MIN(Assumptions!$B$14,1%),Assumptions!$B$14)*(1-Assumptions!$B$157)
A102: Family plan subscribers | B102: subscribers | C102: =IF(C2>=Assumptions!$B$50,C74*Assumptions!$B$174*(1-Assumptions!$B$177)^(C7/2),0) | D102: =IF(D2>=Assumptions!$B$50,C102*(1-Assumptions!$B$177)^D7+D74*Assumptions!$B$174*(1-Assumptions!$B$177)^(D7/2),0) | E102: =IF(E2>=Assumptions!$B$50,D102*(1-Assumptions!$B$177)^E7+E74*Assumptions!$B$174*(1-Assumptions!$B$177)^(E7/2),0) | F102: =IF(F2>=Assumptions!$B$50,E102*(1-Assumptions!$B$177)^F7+F74*Assumptions!$B$174*(1-Assumptions!$B$177)^(F7/2),0) | G102: =IF(G2>=Assumptions!$B$50,F102*(1-Assumptions!$B$177)^G7+G74*Assumptions!$B$174*(1-Assumptions!$B$177)^(G7/2),0) | H102: =IF(H2>=Assumptions!$B$50,G102*(1-Assumptions!$B$177)^H7+H74*Assumptions!$B$174*(1-Assumptions!$B$177)^(H7/2),0) | I102: =IF(I2>=Assumptions!$B$50,H102*(1-Assumptions!$B$177)^I7+I74*Assumptions!$B$174*(1-Assumptions!$B$177)^(I7/2),0) | J102: =IF(J2>=Assumptions!$B$50,I102*(1-Assumptions!$B$177)^J7+J74*Assumptions!$B$174*(1-Assumptions!$B$177)^(J7/2),0) | K102: =IF(K2>=Assumptions!$B$50,J102*(1-Assumptions!$B$177)^K7+K74*Assumptions!$B$174*(1-Assumptions!$B$177)^(K7/2),0) | ... AE102: =IF(AE2>=Assumptions!$B$50,AD102*(1-Assumptions!$B$177)^AE7+AE74*Assumptions!$B$174*(1-Assumptions!$B$177)^(AE7/2),0)
A103: Stream 3 - Family plan and Digital Will | B103: USD | C103: =C102*(Assumptions!$B$25+MAX(0,Assumptions!$B$176-1)*Assumptions!$B$26)/12*C7 | D103: =D102*(Assumptions!$B$25+MAX(0,Assumptions!$B$176-1)*Assumptions!$B$26)/12*D7 | E103: =E102*(Assumptions!$B$25+MAX(0,Assumptions!$B$176-1)*Assumptions!$B$26)/12*E7 | F103: =F102*(Assumptions!$B$25+MAX(0,Assumptions!$B$176-1)*Assumptions!$B$26)/12*F7 | G103: =G102*(Assumptions!$B$25+MAX(0,Assumptions!$B$176-1)*Assumptions!$B$26)/12*G7 | H103: =H102*(Assumptions!$B$25+MAX(0,Assumptions!$B$176-1)*Assumptions!$B$26)/12*H7 | I103: =I102*(Assumptions!$B$25+MAX(0,Assumptions!$B$176-1)*Assumptions!$B$26)/12*I7 | J103: =J102*(Assumptions!$B$25+MAX(0,Assumptions!$B$176-1)*Assumptions!$B$26)/12*J7 | ... AE103: =AE102*(Assumptions!$B$25+MAX(0,Assumptions!$B$176-1)*Assumptions!$B$26)/12*AE7
